Workbook

Sheet FRETE MÁQUINAS
A1: STATUS | B1: FRETE | C1: HR | D1: KM | E1: R$ PROP | F1: R$ TERC | G1: CHASSI | H1: PREVISÃO | I1: REAL | J1: NOTA | K1: SOLICITANTE | L1: ESTÁ: | M1: VAI: | N1: TIPO | O1: ESTÁ EM: | P1: VAI PARA: | Q1: OBS
A2: CONCLUIDO | B2: TERCEIRO DEMETRIO | C2: 0.11944444 | D2: 115 | E2: =IFERROR((D2*7),"?") -> 805 | F2: 300 | G2: 1BM5080EEP4112594 | H2: 45964 | I2: 45964 | J2: CLIENTE → MANUTENÇÃO | K2: daisy.kakol | L2: CLIENTE | M2: IRATI | N2: DE CLIENTE PARA LOJA | O2: https://maps.app.goo.gl/MTXwpjxVEM4SBPA46 | P2: MPA | Q2: jose | R2: =IF( OR( IFERROR(FIND("BM",G2),0)>0, IFERROR(FIND("PY",G2),0)>0 ), MID(TRIM(SUBSTITUTE(SUBSTITUTE(G2,CHAR(160),""),CHAR(9),"")),4,5), MID(TRIM(SUBSTITUTE(SUBSTITUTE(G2,CHAR(160),""),CHAR(9),"")),4,4) ) -> 5080E | S2: {=_xlfn.LET( _xlpm.ch, TRIM(SUBSTITUTE(G2,CHAR(160),"")), _xlpm.ehTrator, OR(IFERROR(FIND("BM",_xlpm.ch),0)>0, IFERROR(FIND("PY",_xlpm.ch),0)>0), _xlpm.chave, IF(_xlpm.ehTrator, MID(_xlpm.ch,4,5), MID(_xlpm.ch,4,4)), _xlpm.fonte, IF(LEN(_xlpm.chave)=5, UTIL!BV:BV, UTIL!BU:BU), _xlpm.modelo, TRIM(SUBSTITUTE(R2,CHAR(160),"")), _xlpm.nomeMod, IFERROR(_xlfn.XLOOKUP("*"&_xlpm.modelo&"*", UTIL!D:D, UTIL!B:B, "", 2), IFERROR(_xlfn.XLOOKUP("*"&_xlpm.modelo&"*", UTIL!E:E, UTIL!B:B, "", 2), "")), _xlpm.tipoMod, IF(_xlpm.nomeMod="", "", IFERROR(LEFT(_xlpm.nomeMod, FIND(" ", _xlpm.nomeMod)-1), _xlpm.nomeMod)), _xlpm.dimMod, IFERROR(_xlfn.XLOOKUP("*"&_xlpm.modelo&"*", UTIL!D:D, UTIL!K:K, "", 2), IFERROR(_xlfn.XLOOKUP("*"&_xlpm.modelo&"*", UTIL!E:E, UTIL!K:K, "", 2), "")), _xlpm.tipotxt_antigo, IF(_xlpm.ehTrator, "TRATOR", IFERROR(_xlfn.XLOOKUP(_xlpm.chave, _xlpm.fonte, UTIL!BS:BS, "", 0), IFERROR(_xlfn.XLOOKUP("*"&_xlpm.chave&"*", _xlpm.fonte, UTIL!BS:BS, "", 2), "Não encontrado"))), _xlpm.dimtxt_antigo, IFERROR(_xlfn.XLOOKUP(_xlpm.chave, _xlpm.fonte, UTIL!CB:CB, "", 0), IFERROR(_xlfn.XLOOKUP("*"&_xlpm.chave&"*", _xlpm.fonte, UTIL!CB:CB, "", 2), "Não encontrado")), _xlpm.tipotxt, IF(_xlpm.tipoMod<>"", _xlpm.tipoMod, _xlpm.tipotxt_antigo), _xlpm.dimtxt, IF(_xlpm.dimMod<>"", _xlpm.dimMod, _xlpm.dimtxt_antigo), _xlpm.deTxt, IF(L2="CLIENTE", O2, IF(LEFT(L2,4)="http", L2, "MACPONTA AGRO DE "&L2)), _xlpm.paraBase, IF(M2="CLIENTE", P2, M2), _xlpm.paraTxt, IF(LEFT(_xlpm.paraBase,4)="http", _xlpm.paraBase, "MACPONTA AGRO DE "&_xlpm.paraBase), _xlpm.nfParte, IF(LEN(TRIM(I2))=0, "", " -NF "&TRIM(I2)), "- " & _xlpm.tipotxt & ": *" & G2 & "*" & CHAR(13)&CHAR(10) & "- " & _xlpm.dimtxt & CHAR(13)&CHAR(10) & "- *Cliente*: " & J2 & _xlpm.nfParte & CHAR(13)&CHAR(10) & "- *Obs:* " & Q2 & CHAR(13)&CHAR(10) & CHAR(10) & "- *De*: " & _xlpm.deTxt & CHAR(13)&CHAR(10) & "- *Para*: " & _xlpm.paraTxt & CHAR(13)&CHAR(10) & "- *Ida e volta*: +/- " & TEXT(((D2*1.5)/1440),"h:mm") & "h | " & D2 & "km" )} -> - TRATOR: *1BM5080EEP4112594*_x000D_ - _x000D_ - *Cliente*: CLIENTE → MANUTENÇÃO -NF 45964_x000D_ - *Obs:* jose_x000D_ - *De*: https://maps.app.goo.gl/MTXwpjxVEM4SBPA46_x000D_ - *Para*: MACPONTA AGRO DE IRATI_x000D_ - *Ida e volta*: +/- 2:52h | 115km
A3: CONCLUIDO | B3: TERCEIRO DEMETRIO | C3: 0.11944444 | D3: 115 | E3: =IFERROR((D3*7),"?") -> 805 | F3: 500 | G3: 1BM5080ECP4111950 | H3: 45964 | I3: 45964 | J3: MANUTENÇÃO → CLIENTE | K3: daisy.kakol | L3: IRATI | M3: CLIENTE | N3: DE LOJA PARA CLIENTE | O3: MPA | P3: https://maps.app.goo.gl/rYQLkSMERduCoffL8 | Q3: RICARDO DRANKA | R3: =IF( OR( IFERROR(FIND("BM",G3),0)>0, IFERROR(FIND("PY",G3),0)>0 ), MID(TRIM(SUBSTITUTE(SUBSTITUTE(G3,CHAR(160),""),CHAR(9),"")),4,5), MID(TRIM(SUBSTITUTE(SUBSTITUTE(G3,CHAR(160),""),CHAR(9),"")),4,4) ) -> 5080E | S3: {=_xlfn.LET( _xlpm.ch, TRIM(SUBSTITUTE(G3,CHAR(160),"")), _xlpm.ehTrator, OR(IFERROR(FIND("BM",_xlpm.ch),0)>0, IFERROR(FIND("PY",_xlpm.ch),0)>0), _xlpm.chave, IF(_xlpm.ehTrator, MID(_xlpm.ch,4,5), MID(_xlpm.ch,4,4)), _xlpm.fonte, IF(LEN(_xlpm.chave)=5, UTIL!BV:BV, UTIL!BU:BU), _xlpm.modelo, TRIM(SUBSTITUTE(R3,CHAR(160),"")), _xlpm.nomeMod, IFERROR(_xlfn.XLOOKUP("*"&_xlpm.modelo&"*", UTIL!D:D, UTIL!B:B, "", 2), IFERROR(_xlfn.XLOOKUP("*"&_xlpm.modelo&"*", UTIL!E:E, UTIL!B:B, "", 2), "")), _xlpm.tipoMod, IF(_xlpm.nomeMod="", "", IFERROR(LEFT(_xlpm.nomeMod, FIND(" ", _xlpm.nomeMod)-1), _xlpm.nomeMod)), _xlpm.dimMod, IFERROR(_xlfn.XLOOKUP("*"&_xlpm.modelo&"*", UTIL!D:D, UTIL!K:K, "", 2), IFERROR(_xlfn.XLOOKUP("*"&_xlpm.modelo&"*", UTIL!E:E, UTIL!K:K, "", 2), "")), _xlpm.tipotxt_antigo, IF(_xlpm.ehTrator, "TRATOR", IFERROR(_xlfn.XLOOKUP(_xlpm.chave, _xlpm.fonte, UTIL!BS:BS, "", 0), IFERROR(_xlfn.XLOOKUP("*"&_xlpm.chave&"*", _xlpm.fonte, UTIL!BS:BS, "", 2), "Não encontrado"))), _xlpm.dimtxt_antigo, IFERROR(_xlfn.XLOOKUP(_xlpm.chave, _xlpm.fonte, UTIL!CB:CB, "", 0), IFERROR(_xlfn.XLOOKUP("*"&_xlpm.chave&"*", _xlpm.fonte, UTIL!CB:CB, "", 2), "Não encontrado")), _xlpm.tipotxt, IF(_xlpm.tipoMod<>"", _xlpm.tipoMod, _xlpm.tipotxt_antigo), _xlpm.dimtxt, IF(_xlpm.dimMod<>"", _xlpm.dimMod, _xlpm.dimtxt_antigo), _xlpm.deTxt, IF(L3="CLIENTE", O3, IF(LEFT(L3,4)="http", L3, "MACPONTA AGRO DE "&L3)), _xlpm.paraBase, IF(M3="CLIENTE", P3, M3), _xlpm.paraTxt, IF(LEFT(_xlpm.paraBase,4)="http", _xlpm.paraBase, "MACPONTA AGRO DE "&_xlpm.paraBase), _xlpm.nfParte, IF(LEN(TRIM(I3))=0, "", " -NF "&TRIM(I3)), "- " & _xlpm.tipotxt & ": *" & G3 & "*" & CHAR(13)&CHAR(10) & "- " & _xlpm.dimtxt & CHAR(13)&CHAR(10) & "- *Cliente*: " & J3 & _xlpm.nfParte & CHAR(13)&CHAR(10) & "- *Obs:* " & Q3 & CHAR(13)&CHAR(10) & CHAR(10) & "- *De*: " & _xlpm.deTxt & CHAR(13)&CHAR(10) & "- *Para*: " & _xlpm.paraTxt & CHAR(13)&CHAR(10) & "- *Ida e volta*: +/- " & TEXT(((D3*1.5)/1440),"h:mm") & "h | " & D3 & "km" )} -> - TRATOR: *1BM5080ECP4111950*_x000D_ - _x000D_ - *Cliente*: MANUTENÇÃO → CLIENTE -NF 45964_x000D_ - *Obs:* RICARDO DRANKA_x000D_ - *De*: MACPONTA AGRO DE IRATI_x000D_ - *Para*: https://maps.app.goo.gl/rYQLkSMERduCoffL8_x000D_ - *Ida e volta*: +/- 2:52h | 115km
A4: CONCLUIDO | B4: TERCEIRO DEMETRIO | C4: 0.10208333 | D4: 98 | E4: =IFERROR((D4*7),"?") -> 686 | F4: 300 | G4: 1BM5060ECN4103629 | H4: 45964 | I4: 45964 | J4: MANUTENÇÃO → CLIENTE | K4: daisy.kakol | L4: IRATI | M4: CLIENTE | N4: DE LOJA PARA CLIENTE | O4: MPA | P4: https://maps.app.goo.gl/MLVchYQrLvQGhWWp6 | Q4: cezar | R4: =IF( OR( IFERROR(FIND("BM",G4),0)>0, IFERROR(FIND("PY",G4),0)>0 ), MID(TRIM(SUBSTITUTE(SUBSTITUTE(G4,CHAR(160),""),CHAR(9),"")),4,5), MID(TRIM(SUBSTITUTE(SUBSTITUTE(G4,CHAR(160),""),CHAR(9),"")),4,4) ) -> 5060E | S4: {=_xlfn.LET( _xlpm.ch, TRIM(SUBSTITUTE(G4,CHAR(160),"")), _xlpm.ehTrator, OR(IFERROR(FIND("BM",_xlpm.ch),0)>0, IFERROR(FIND("PY",_xlpm.ch),0)>0), _xlpm.chave, IF(_xlpm.ehTrator, MID(_xlpm.ch,4,5), MID(_xlpm.ch,4,4)), _xlpm.fonte, IF(LEN(_xlpm.chave)=5, UTIL!BV:BV, UTIL!BU:BU), _xlpm.modelo, TRIM(SUBSTITUTE(R4,CHAR(160),"")), _xlpm.nomeMod, IFERROR(_xlfn.XLOOKUP("*"&_xlpm.modelo&"*", UTIL!D:D, UTIL!B:B, "", 2), IFERROR(_xlfn.XLOOKUP("*"&_xlpm.modelo&"*", UTIL!E:E, UTIL!B:B, "", 2), "")), _xlpm.tipoMod, IF(_xlpm.nomeMod="", "", IFERROR(LEFT(_xlpm.nomeMod, FIND(" ", _xlpm.nomeMod)-1), _xlpm.nomeMod)), _xlpm.dimMod, IFERROR(_xlfn.XLOOKUP("*"&_xlpm.modelo&"*", UTIL!D:D, UTIL!K:K, "", 2), IFERROR(_xlfn.XLOOKUP("*"&_xlpm.modelo&"*", UTIL!E:E, UTIL!K:K, "", 2), "")), _xlpm.tipotxt_antigo, IF(_xlpm.ehTrator, "TRATOR", IFERROR(_xlfn.XLOOKUP(_xlpm.chave, _xlpm.fonte, UTIL!BS:BS, "", 0), IFERROR(_xlfn.XLOOKUP("*"&_xlpm.chave&"*", _xlpm.fonte, UTIL!BS:BS, "", 2), "Não encontrado"))), _xlpm.dimtxt_antigo, IFERROR(_xlfn.XLOOKUP(_xlpm.chave, _xlpm.fonte, UTIL!CB:CB, "", 0), IFERROR(_xlfn.XLOOKUP("*"&_xlpm.chave&"*", _xlpm.fonte, UTIL!CB:CB, "", 2), "Não encontrado")), _xlpm.tipotxt, IF(_xlpm.tipoMod<>"", _xlpm.tipoMod, _xlpm.tipotxt_antigo), _xlpm.dimtxt, IF(_xlpm.dimMod<>"", _xlpm.dimMod, _xlpm.dimtxt_antigo), _xlpm.deTxt, IF(L4="CLIENTE", O4, IF(LEFT(L4,4)="http", L4, "MACPONTA AGRO DE "&L4)), _xlpm.paraBase, IF(M4="CLIENTE", P4, M4), _xlpm.paraTxt, IF(LEFT(_xlpm.paraBase,4)="http", _xlpm.paraBase, "MACPONTA AGRO DE "&_xlpm.paraBase), _xlpm.nfParte, IF(LEN(TRIM(I4))=0, "", " -NF "&TRIM(I4)), "- " & _xlpm.tipotxt & ": *" & G4 & "*" & CHAR(13)&CHAR(10) & "- " & _xlpm.dimtxt & CHAR(13)&CHAR(10) & "- *Cliente*: " & J4 & _xlpm.nfParte & CHAR(13)&CHAR(10) & "- *Obs:* " & Q4 & CHAR(13)&CHAR(10) & CHAR(10) & "- *De*: " & _xlpm.deTxt & CHAR(13)&CHAR(10) & "- *Para*: " & _xlpm.paraTxt & CHAR(13)&CHAR(10) & "- *Ida e volta*: +/- " & TEXT(((D4*1.5)/1440),"h:mm") & "h | " & D4 & "km" )} -> - TRATOR: *1BM5060ECN4103629*_x000D_ - _x000D_ - *Cliente*: MANUTENÇÃO → CLIENTE -NF 45964_x000D_ - *Obs:* cezar_x000D_ - *De*: MACPONTA AGRO DE IRATI_x000D_ - *Para*: https://maps.app.goo.gl/MLVchYQrLvQGhWWp6_x000D_ - *Ida e volta*: +/- 2:27h | 98km
A5: CONCLUIDO | B5: TERCEIRO MAZETTO | C5: 0.17916667 | D5: 172 | E5: =IFERROR((D5*7),"?") -> 1204 | F5: 750 | G5: 1CQS760ACS0160134 | H5: 45964 | I5: 45964 | J5: ARNALDO STOCK -NF107847 | K5: euclides.junior | L5: GUARAPUAVA | M5: CLIENTE | N5: DE LOJA PARA CLIENTE | O5: MPA | P5: https://maps.app.goo.gl/Kk5FKYUBPHUbo26P8 | Q5: Fabio | R5: =IF( OR( IFERROR(FIND("BM",G5),0)>0, IFERROR(FIND("PY",G5),0)>0 ), MID(TRIM(SUBSTITUTE(SUBSTITUTE(G5,CHAR(160),""),CHAR(9),"")),4,5), MID(TRIM(SUBSTITUTE(SUBSTITUTE(G5,CHAR(160),""),CHAR(9),"")),4,4) ) -> S760 | S5: {=_xlfn.LET( _xlpm.ch, TRIM(SUBSTITUTE(G5,CHAR(160),"")), _xlpm.ehTrator, OR(IFERROR(FIND("BM",_xlpm.ch),0)>0, IFERROR(FIND("PY",_xlpm.ch),0)>0), _xlpm.chave, IF(_xlpm.ehTrator, MID(_xlpm.ch,4,5), MID(_xlpm.ch,4,4)), _xlpm.fonte, IF(LEN(_xlpm.chave)=5, UTIL!BV:BV, UTIL!BU:BU), _xlpm.modelo, TRIM(SUBSTITUTE(R5,CHAR(160),"")), _xlpm.nomeMod, IFERROR(_xlfn.XLOOKUP("*"&_xlpm.modelo&"*", UTIL!D:D, UTIL!B:B, "", 2), IFERROR(_xlfn.XLOOKUP("*"&_xlpm.modelo&"*", UTIL!E:E, UTIL!B:B, "", 2), "")), _xlpm.tipoMod, IF(_xlpm.nomeMod="", "", IFERROR(LEFT(_xlpm.nomeMod, FIND(" ", _xlpm.nomeMod)-1), _xlpm.nomeMod)), _xlpm.dimMod, IFERROR(_xlfn.XLOOKUP("*"&_xlpm.modelo&"*", UTIL!D:D, UTIL!K:K, "", 2), IFERROR(_xlfn.XLOOKUP("*"&_xlpm.modelo&"*", UTIL!E:E, UTIL!K:K, "", 2), "")), _xlpm.tipotxt_antigo, IF(_xlpm.ehTrator, "TRATOR", IFERROR(_xlfn.XLOOKUP(_xlpm.chave, _xlpm.fonte, UTIL!BS:BS, "", 0), IFERROR(_xlfn.XLOOKUP("*"&_xlpm.chave&"*", _xlpm.fonte, UTIL!BS:BS, "", 2), "Não encontrado"))), _xlpm.dimtxt_antigo, IFERROR(_xlfn.XLOOKUP(_xlpm.chave, _xlpm.fonte, UTIL!CB:CB, "", 0), IFERROR(_xlfn.XLOOKUP("*"&_xlpm.chave&"*", _xlpm.fonte, UTIL!CB:CB, "", 2), "Não encontrado")), _xlpm.tipotxt, IF(_xlpm.tipoMod<>"", _xlpm.tipoMod, _xlpm.tipotxt_antigo), _xlpm.dimtxt, IF(_xlpm.dimMod<>"", _xlpm.dimMod, _xlpm.dimtxt_antigo), _xlpm.deTxt, IF(L5="CLIENTE", O5, IF(LEFT(L5,4)="http", L5, "MACPONTA AGRO DE "&L5)), _xlpm.paraBase, IF(M5="CLIENTE", P5, M5), _xlpm.paraTxt, IF(LEFT(_xlpm.paraBase,4)="http", _xlpm.paraBase, "MACPONTA AGRO DE "&_xlpm.paraBase), _xlpm.nfParte, IF(LEN(TRIM(I5))=0, "", " -NF "&TRIM(I5)), "- " & _xlpm.tipotxt & ": *" & G5 & "*" & CHAR(13)&CHAR(10) & "- " & _xlpm.dimtxt & CHAR(13)&CHAR(10) & "- *Cliente*: " & J5 & _xlpm.nfParte & CHAR(13)&CHAR(10) & "- *Obs:* " & Q5 & CHAR(13)&CHAR(10) & CHAR(10) & "- *De*: " & _xlpm.deTxt & CHAR(13)&CHAR(10) & "- *Para*: " & _xlpm.paraTxt & CHAR(13)&CHAR(10) & "- *Ida e volta*: +/- " & TEXT(((D5*1.5)/1440),"h:mm") & "h | " & D5 & "km" )} -> - COLHEITADEIRA: *1CQS760ACS0160134*_x000D_ - A:4,00 x C:10,60 x L:3,50-5,20 x P:18.599kg_x000D_ - *Cliente*: ARNALDO STOCK -NF107847 -NF 45964_x000D_ - *Obs:* Fabio _x000D_ - *De*: MACPONTA AGRO DE GUARAPUAVA_x000D_ - *Para*: https://maps.app.goo.gl/Kk5FKYUBPHUbo26P8_x000D_ - *Ida e volta*: +/- 4:18h | 172km
A6: CONCLUIDO | B6: TERCEIRO MAZETTO | C6: 0.17916667 | D6: 172 | E6: =IFERROR((D6*7),"?") -> 1204 | F6: 750 | G6: 1CQFA30AAS0160114 | H6: 45964 | I6: 45964 | J6: ARNALDO STOCK -NF107847 | K6: euclides.junior | L6: GUARAPUAVA | M6: CLIENTE | N6: DE LOJA PARA CLIENTE | O6: MPA | P6: https://maps.app.goo.gl/kFwUPivsMpYS8pGd8 | Q6: Fabio | R6: =IF( OR( IFERROR(FIND("BM",G6),0)>0, IFERROR(FIND("PY",G6),0)>0 ), MID(TRIM(SUBSTITUTE(SUBSTITUTE(G6,CHAR(160),""),CHAR(9),"")),4,5), MID(TRIM(SUBSTITUTE(SUBSTITUTE(G6,CHAR(160),""),CHAR(9),"")),4,4) ) -> FA30 | S6: {=_xlfn.LET( _xlpm.ch, TRIM(SUBSTITUTE(G6,CHAR(160),"")), _xlpm.ehTrator, OR(IFERROR(FIND("BM",_xlpm.ch),0)>0, IFERROR(FIND("PY",_xlpm.ch),0)>0), _xlpm.chave, IF(_xlpm.ehTrator, MID(_xlpm.ch,4,5), MID(_xlpm.ch,4,4)), _xlpm.fonte, IF(LEN(_xlpm.chave)=5, UTIL!BV:BV, UTIL!BU:BU), _xlpm.modelo, TRIM(SUBSTITUTE(R6,CHAR(160),"")), _xlpm.nomeMod, IFERROR(_xlfn.XLOOKUP("*"&_xlpm.modelo&"*", UTIL!D:D, UTIL!B:B, "", 2), IFERROR(_xlfn.XLOOKUP("*"&_xlpm.modelo&"*", UTIL!E:E, UTIL!B:B, "", 2), "")), _xlpm.tipoMod, IF(_xlpm.nomeMod="", "", IFERROR(LEFT(_xlpm.nomeMod, FIND(" ", _xlpm.nomeMod)-1), _xlpm.nomeMod)), _xlpm.dimMod, IFERROR(_xlfn.XLOOKUP("*"&_xlpm.modelo&"*", UTIL!D:D, UTIL!K:K, "", 2), IFERROR(_xlfn.XLOOKUP("*"&_xlpm.modelo&"*", UTIL!E:E, UTIL!K:K, "", 2), "")), _xlpm.tipotxt_antigo, IF(_xlpm.ehTrator, "TRATOR", IFERROR(_xlfn.XLOOKUP(_xlpm.chave, _xlpm.fonte, UTIL!BS:BS, "", 0), IFERROR(_xlfn.XLOOKUP("*"&_xlpm.chave&"*", _xlpm.fonte, UTIL!BS:BS, "", 2), "Não encontrado"))), _xlpm.dimtxt_antigo, IFERROR(_xlfn.XLOOKUP(_xlpm.chave, _xlpm.fonte, UTIL!CB:CB, "", 0), IFERROR(_xlfn.XLOOKUP("*"&_xlpm.chave&"*", _xlpm.fonte, UTIL!CB:CB, "", 2), "Não encontrado")), _xlpm.tipotxt, IF(_xlpm.tipoMod<>"", _xlpm.tipoMod, _xlpm.tipotxt_antigo), _xlpm.dimtxt, IF(_xlpm.dimMod<>"", _xlpm.dimMod, _xlpm.dimtxt_antigo), _xlpm.deTxt, IF(L6="CLIENTE", O6, IF(LEFT(L6,4)="http", L6, "MACPONTA AGRO DE "&L6)), _xlpm.paraBase, IF(M6="CLIENTE", P6, M6), _xlpm.paraTxt, IF(LEFT(_xlpm.paraBase,4)="http", _xlpm.paraBase, "MACPONTA AGRO DE "&_xlpm.paraBase), _xlpm.nfParte, IF(LEN(TRIM(I6))=0, "", " -NF "&TRIM(I6)), "- " & _xlpm.tipotxt & ": *" & G6 & "*" & CHAR(13)&CHAR(10) & "- " & _xlpm.dimtxt & CHAR(13)&CHAR(10) & "- *Cliente*: " & J6 & _xlpm.nfParte & CHAR(13)&CHAR(10) & "- *Obs:* " & Q6 & CHAR(13)&CHAR(10) & CHAR(10) & "- *De*: " & _xlpm.deTxt & CHAR(13)&CHAR(10) & "- *Para*: " & _xlpm.paraTxt & CHAR(13)&CHAR(10) & "- *Ida e volta*: +/- " & TEXT(((D6*1.5)/1440),"h:mm") & "h | " & D6 & "km" )} -> - PLATAFORMA: *1CQFA30AAS0160114*_x000D_ - A:1,60 x C:9,14 x L:1,80-1,80 x P:2.900kg_x000D_ - *Cliente*: ARNALDO STOCK -NF107847 -NF 45964_x000D_ - *Obs:* Fabio _x000D_ - *De*: MACPONTA AGRO DE GUARAPUAVA_x000D_ - *Para*: https://maps.app.goo.gl/kFwUPivsMpYS8pGd8_x000D_ - *Ida e volta*: +/- 4:18h | 172km
A7: CONCLUIDO | B7: TERCEIRO MAZETTO | C7: 0.15625 | D7: 150 | E7: =IFERROR((D7*7),"?") -> 1050 | F7: 1352 | G7: 1BM5080EPS4204124 | H7: 45964 | I7: 45964 | J7: LUIZ HENRIQUE GREIN -NF107347 | K7: euclides.junior | L7: GUARAPUAVA | M7: CLIENTE | N7: DE LOJA PARA CLIENTE | O7: MPA | P7: https://maps.app.goo.gl/jZEWqzLvNcpTnRBE8 | Q7: Emerson | R7: =IF( OR( IFERROR(FIND("BM",G7),0)>0, IFERROR(FIND("PY",G7),0)>0 ), MID(TRIM(SUBSTITUTE(SUBSTITUTE(G7,CHAR(160),""),CHAR(9),"")),4,5), MID(TRIM(SUBSTITUTE(SUBSTITUTE(G7,CHAR(160),""),CHAR(9),"")),4,4) ) -> 5080E | S7: {=_xlfn.LET( _xlpm.ch, TRIM(SUBSTITUTE(G7,CHAR(160),"")), _xlpm.ehTrator, OR(IFERROR(FIND("BM",_xlpm.ch),0)>0, IFERROR(FIND("PY",_xlpm.ch),0)>0), _xlpm.chave, IF(_xlpm.ehTrator, MID(_xlpm.ch,4,5), MID(_xlpm.ch,4,4)), _xlpm.fonte, IF(LEN(_xlpm.chave)=5, UTIL!BV:BV, UTIL!BU:BU), _xlpm.modelo, TRIM(SUBSTITUTE(R7,CHAR(160),"")), _xlpm.nomeMod, IFERROR(_xlfn.XLOOKUP("*"&_xlpm.modelo&"*", UTIL!D:D, UTIL!B:B, "", 2), IFERROR(_xlfn.XLOOKUP("*"&_xlpm.modelo&"*", UTIL!E:E, UTIL!B:B, "", 2), "")), _xlpm.tipoMod, IF(_xlpm.nomeMod="", "", IFERROR(LEFT(_xlpm.nomeMod, FIND(" ", _xlpm.nomeMod)-1), _xlpm.nomeMod)), _xlpm.dimMod, IFERROR(_xlfn.XLOOKUP("*"&_xlpm.modelo&"*", UTIL!D:D, UTIL!K:K, "", 2), IFERROR(_xlfn.XLOOKUP("*"&_xlpm.modelo&"*", UTIL!E:E, UTIL!K:K, "", 2), "")), _xlpm.tipotxt_antigo, IF(_xlpm.ehTrator, "TRATOR", IFERROR(_xlfn.XLOOKUP(_xlpm.chave, _xlpm.fonte, UTIL!BS:BS, "", 0), IFERROR(_xlfn.XLOOKUP("*"&_xlpm.chave&"*", _xlpm.fonte, UTIL!BS:BS, "", 2), "Não encontrado"))), _xlpm.dimtxt_antigo, IFERROR(_xlfn.XLOOKUP(_xlpm.chave, _xlpm.fonte, UTIL!CB:CB, "", 0), IFERROR(_xlfn.XLOOKUP("*"&_xlpm.chave&"*", _xlpm.fonte, UTIL!CB:CB, "", 2), "Não encontrado")), _xlpm.tipotxt, IF(_xlpm.tipoMod<>"", _xlpm.tipoMod, _xlpm.tipotxt_antigo), _xlpm.dimtxt, IF(_xlpm.dimMod<>"", _xlpm.dimMod, _xlpm.dimtxt_antigo), _xlpm.deTxt, IF(L7="CLIENTE", O7, IF(LEFT(L7,4)="http", L7, "MACPONTA AGRO DE "&L7)), _xlpm.paraBase, IF(M7="CLIENTE", P7, M7), _xlpm.paraTxt, IF(LEFT(_xlpm.paraBase,4)="http", _xlpm.paraBase, "MACPONTA AGRO DE "&_xlpm.paraBase), _xlpm.nfParte, IF(LEN(TRIM(I7))=0, "", " -NF "&TRIM(I7)), "- " & _xlpm.tipotxt & ": *" & G7 & "*" & CHAR(13)&CHAR(10) & "- " & _xlpm.dimtxt & CHAR(13)&CHAR(10) & "- *Cliente*: " & J7 & _xlpm.nfParte & CHAR(13)&CHAR(10) & "- *Obs:* " & Q7 & CHAR(13)&CHAR(10) & CHAR(10) & "- *De*: " & _xlpm.deTxt & CHAR(13)&CHAR(10) & "- *Para*: " & _xlpm.paraTxt & CHAR(13)&CHAR(10) & "- *Ida e volta*: +/- " & TEXT(((D7*1.5)/1440),"h:mm") & "h | " & D7 & "km" )} -> - TRATOR: *1BM5080EPS4204124*_x000D_ - _x000D_ - *Cliente*: LUIZ HENRIQUE GREIN -NF107347 -NF 45964_x000D_ - *Obs:* Emerson_x000D_ - *De*: MACPONTA AGRO DE GUARAPUAVA_x000D_ - *Para*: https://maps.app.goo.gl/jZEWqzLvNcpTnRBE8_x000D_ - *Ida e volta*: +/- 3:45h | 150km
A8: CONCLUIDO | B8: TERCEIRO STOSKI | C8: 0.072916667 | D8: 70 | E8: =IFERROR((D8*7),"?") -> 490 | F8: 910 | G8: 1BM6135MPSH000596 | H8: 45964 | I8: 45964 | J8: LAURO MIGUEL STRONA -NF76755 | K8: marcio.jacovossi | L8: IRATI | M8: CLIENTE | N8: DE LOJA PARA CLIENTE | O8: MPA | P8: https://maps.app.goo.gl/JxzGitfYRrvxzYUL9 | Q8: LAURO MIGUEL STRONA 42 999269190 | R8: =IF( OR( IFERROR(FIND("BM",G8),0)>0, IFERROR(FIND("PY",G8),0)>0 ), MID(TRIM(SUBSTITUTE(SUBSTITUTE(G8,CHAR(160),""),CHAR(9),"")),4,5), MID(TRIM(SUBSTITUTE(SUBSTITUTE(G8,CHAR(160),""),CHAR(9),"")),4,4) ) -> 6135M | S8: {=_xlfn.LET( _xlpm.ch, TRIM(SUBSTITUTE(G8,CHAR(160),"")), _xlpm.ehTrator, OR(IFERROR(FIND("BM",_xlpm.ch),0)>0, IFERROR(FIND("PY",_xlpm.ch),0)>0), _xlpm.chave, IF(_xlpm.ehTrator, MID(_xlpm.ch,4,5), MID(_xlpm.ch,4,4)), _xlpm.fonte, IF(LEN(_xlpm.chave)=5, UTIL!BV:BV, UTIL!BU:BU), _xlpm.modelo, TRIM(SUBSTITUTE(R8,CHAR(160),"")), _xlpm.nomeMod, IFERROR(_xlfn.XLOOKUP("*"&_xlpm.modelo&"*", UTIL!D:D, UTIL!B:B, "", 2), IFERROR(_xlfn.XLOOKUP("*"&_xlpm.modelo&"*", UTIL!E:E, UTIL!B:B, "", 2), "")), _xlpm.tipoMod, IF(_xlpm.nomeMod="", "", IFERROR(LEFT(_xlpm.nomeMod, FIND(" ", _xlpm.nomeMod)-1), _xlpm.nomeMod)), _xlpm.dimMod, IFERROR(_xlfn.XLOOKUP("*"&_xlpm.modelo&"*", UTIL!D:D, UTIL!K:K, "", 2), IFERROR(_xlfn.XLOOKUP("*"&_xlpm.modelo&"*", UTIL!E:E, UTIL!K:K, "", 2), "")), _xlpm.tipotxt_antigo, IF(_xlpm.ehTrator, "TRATOR", IFERROR(_xlfn.XLOOKUP(_xlpm.chave, _xlpm.fonte, UTIL!BS:BS, "", 0), IFERROR(_xlfn.XLOOKUP("*"&_xlpm.chave&"*", _xlpm.fonte, UTIL!BS:BS, "", 2), "Não encontrado"))), _xlpm.dimtxt_antigo, IFERROR(_xlfn.XLOOKUP(_xlpm.chave, _xlpm.fonte, UTIL!CB:CB, "", 0), IFERROR(_xlfn.XLOOKUP("*"&_xlpm.chave&"*", _xlpm.fonte, UTIL!CB:CB, "", 2), "Não encontrado")), _xlpm.tipotxt, IF(_xlpm.tipoMod<>"", _xlpm.tipoMod, _xlpm.tipotxt_antigo), _xlpm.dimtxt, IF(_xlpm.dimMod<>"", _xlpm.dimMod, _xlpm.dimtxt_antigo), _xlpm.deTxt, IF(L8="CLIENTE", O8, IF(LEFT(L8,4)="http", L8, "MACPONTA AGRO DE "&L8)), _xlpm.paraBase, IF(M8="CLIENTE", P8, M8), _xlpm.paraTxt, IF(LEFT(_xlpm.paraBase,4)="http", _xlpm.paraBase, "MACPONTA AGRO DE "&_xlpm.paraBase), _xlpm.nfParte, IF(LEN(TRIM(I8))=0, "", " -NF "&TRIM(I8)), "- " & _xlpm.tipotxt & ": *" & G8 & "*" & CHAR(13)&CHAR(10) & "- " & _xlpm.dimtxt & CHAR(13)&CHAR(10) & "- *Cliente*: " & J8 & _xlpm.nfParte & CHAR(13)&CHAR(10) & "- *Obs:* " & Q8 & CHAR(13)&CHAR(10) & CHAR(10) & "- *De*: " & _xlpm.deTxt & CHAR(13)&CHAR(10) & "- *Para*: " & _xlpm.paraTxt & CHAR(13)&CHAR(10) & "- *Ida e volta*: +/- " & TEXT(((D8*1.5)/1440),"h:mm") & "h | " & D8 & "km" )} -> - TRATOR: *1BM6135MPSH000596*_x000D_ - _x000D_ - *Cliente*: LAURO MIGUEL STRONA -NF76755 -NF 45964_x000D_ - *Obs:* LAURO MIGUEL STRONA 42 999269190_x000D_ - *De*: MACPONTA AGRO DE IRATI_x000D_ - *Para*: https://maps.app.goo.gl/JxzGitfYRrvxzYUL9_x000D_ - *Ida e volta*: +/- 1:45h | 70km
A9: CONCLUIDO | B9: PROPRIO VW | C9: 0.058333333 | D9: 56 | E9: =IFERROR((D9*7),"?") -> 392 | F9: 0 | G9: 1BM5060EES4201594 | H9: 45965 | I9: 45964 | J9: JOAQUIM MASCARENHAS -NF278279 | K9: marcos.ribas | L9: PONTA GROSSA | M9: CLIENTE | N9: DE LOJA PARA CLIENTE | O9: MPA | P9: https://maps.app.goo.gl/s5tPSxgcuWhSkcKc7 | Q9: PAULO - +55 42 9991-2229 - AVISAR ANGELO PARA ACOMPANHAR | R9: =IF( OR( IFERROR(FIND("BM",G9),0)>0, IFERROR(FIND("PY",G9),0)>0 ), MID(TRIM(SUBSTITUTE(SUBSTITUTE(G9,CHAR(160),""),CHAR(9),"")),4,5), MID(TRIM(SUBSTITUTE(SUBSTITUTE(G9,CHAR(160),""),CHAR(9),"")),4,4) ) -> 5060E | S9: {=_xlfn.LET( _xlpm.ch, TRIM(SUBSTITUTE(G9,CHAR(160),"")), _xlpm.ehTrator, OR(IFERROR(FIND("BM",_xlpm.ch),0)>0, IFERROR(FIND("PY",_xlpm.ch),0)>0), _xlpm.chave, IF(_xlpm.ehTrator, MID(_xlpm.ch,4,5), MID(_xlpm.ch,4,4)), _xlpm.fonte, IF(LEN(_xlpm.chave)=5, UTIL!BV:BV, UTIL!BU:BU), _xlpm.modelo, TRIM(SUBSTITUTE(R9,CHAR(160),"")), _xlpm.nomeMod, IFERROR(_xlfn.XLOOKUP("*"&_xlpm.modelo&"*", UTIL!D:D, UTIL!B:B, "", 2), IFERROR(_xlfn.XLOOKUP("*"&_xlpm.modelo&"*", UTIL!E:E, UTIL!B:B, "", 2), "")), _xlpm.tipoMod, IF(_xlpm.nomeMod="", "", IFERROR(LEFT(_xlpm.nomeMod, FIND(" ", _xlpm.nomeMod)-1), _xlpm.nomeMod)), _xlpm.dimMod, IFERROR(_xlfn.XLOOKUP("*"&_xlpm.modelo&"*", UTIL!D:D, UTIL!K:K, "", 2), IFERROR(_xlfn.XLOOKUP("*"&_xlpm.modelo&"*", UTIL!E:E, UTIL!K:K, "", 2), "")), _xlpm.tipotxt_antigo, IF(_xlpm.ehTrator, "TRATOR", IFERROR(_xlfn.XLOOKUP(_xlpm.chave, _xlpm.fonte, UTIL!BS:BS, "", 0), IFERROR(_xlfn.XLOOKUP("*"&_xlpm.chave&"*", _xlpm.fonte, UTIL!BS:BS, "", 2), "Não encontrado"))), _xlpm.dimtxt_antigo, IFERROR(_xlfn.XLOOKUP(_xlpm.chave, _xlpm.fonte, UTIL!CB:CB, "", 0), IFERROR(_xlfn.XLOOKUP("*"&_xlpm.chave&"*", _xlpm.fonte, UTIL!CB:CB, "", 2), "Não encontrado")), _xlpm.tipotxt, IF(_xlpm.tipoMod<>"", _xlpm.tipoMod, _xlpm.tipotxt_antigo), _xlpm.dimtxt, IF(_xlpm.dimMod<>"", _xlpm.dimMod, _xlpm.dimtxt_antigo), _xlpm.deTxt, IF(L9="CLIENTE", O9, IF(LEFT(L9,4)="http", L9, "MACPONTA AGRO DE "&L9)), _xlpm.paraBase, IF(M9="CLIENTE", P9, M9), _xlpm.paraTxt, IF(LEFT(_xlpm.paraBase,4)="http", _xlpm.paraBase, "MACPONTA AGRO DE "&_xlpm.paraBase), _xlpm.nfParte, IF(LEN(TRIM(I9))=0, "", " -NF "&TRIM(I9)), "- " & _xlpm.tipotxt & ": *" & G9 & "*" & CHAR(13)&CHAR(10) & "- " & _xlpm.dimtxt & CHAR(13)&CHAR(10) & "- *Cliente*: " & J9 & _xlpm.nfParte & CHAR(13)&CHAR(10) & "- *Obs:* " & Q9 & CHAR(13)&CHAR(10) & CHAR(10) & "- *De*: " & _xlpm.deTxt & CHAR(13)&CHAR(10) & "- *Para*: " & _xlpm.paraTxt & CHAR(13)&CHAR(10) & "- *Ida e volta*: +/- " & TEXT(((D9*1.5)/1440),"h:mm") & "h | " & D9 & "km" )} -> - TRATOR: *1BM5060EES4201594*_x000D_ - _x000D_ - *Cliente*: JOAQUIM MASCARENHAS -NF278279 -NF 45964_x000D_ - *Obs:* PAULO - +55 42 9991-2229 - AVISAR ANGELO PARA ACOMPANHAR_x000D_ - *De*: MACPONTA AGRO DE PONTA GROSSA_x000D_ - *Para*: https://maps.app.goo.gl/s5tPSxgcuWhSkcKc7_x000D_ - *Ida e volta*: +/- 1:24h | 56km
A10: CONCLUIDO | B10: PROPRIO VW | C10: 0.34375 | D10: 330 | E10: =IFERROR((D10*7),"?") -> 2310 | F10: 0 | G10: 1NW4025MVKF190132 | H10: 45965 | I10: 45965 | J10: MARLON BONILHA -NF61707 | K10: edenilson.mattos | L10: PONTA GROSSA | M10: CLIENTE | N10: DE LOJA PARA CLIENTE | O10: MPA | P10: Fazenda Irmãos II - Cidade Tomazina - PR | Q10: Contato CEN Alison 43.98409-2094 | R10: =IF( OR( IFERROR(FIND("BM",G10),0)>0, IFERROR(FIND("PY",G10),0)>0 ), MID(TRIM(SUBSTITUTE(SUBSTITUTE(G10,CHAR(160),""),CHAR(9),"")),4,5), MID(TRIM(SUBSTITUTE(SUBSTITUTE(G10,CHAR(160),""),CHAR(9),"")),4,4) ) -> 4025 | S10: {=_xlfn.LET( _xlpm.ch, TRIM(SUBSTITUTE(G10,CHAR(160),"")), _xlpm.ehTrator, OR(IFERROR(FIND("BM",_xlpm.ch),0)>0, IFERROR(FIND("PY",_xlpm.ch),0)>0), _xlpm.chave, IF(_xlpm.ehTrator, MID(_xlpm.ch,4,5), MID(_xlpm.ch,4,4)), _xlpm.fonte, IF(LEN(_xlpm.chave)=5, UTIL!BV:BV, UTIL!BU:BU), _xlpm.modelo, TRIM(SUBSTITUTE(R10,CHAR(160),"")), _xlpm.nomeMod, IFERROR(_xlfn.XLOOKUP("*"&_xlpm.modelo&"*", UTIL!D:D, UTIL!B:B, "", 2), IFERROR(_xlfn.XLOOKUP("*"&_xlpm.modelo&"*", UTIL!E:E, UTIL!B:B, "", 2), "")), _xlpm.tipoMod, IF(_xlpm.nomeMod="", "", IFERROR(LEFT(_xlpm.nomeMod, FIND(" ", _xlpm.nomeMod)-1), _xlpm.nomeMod)), _xlpm.dimMod, IFERROR(_xlfn.XLOOKUP("*"&_xlpm.modelo&"*", UTIL!D:D, UTIL!K:K, "", 2), IFERROR(_xlfn.XLOOKUP("*"&_xlpm.modelo&"*", UTIL!E:E, UTIL!K:K, "", 2), "")), _xlpm.tipotxt_antigo, IF(_xlpm.ehTrator, "TRATOR", IFERROR(_xlfn.XLOOKUP(_xlpm.chave, _xlpm.fonte, UTIL!BS:BS, "", 0), IFERROR(_xlfn.XLOOKUP("*"&_xlpm.chave&"*", _xlpm.fonte, UTIL!BS:BS, "", 2), "Não encontrado"))), _xlpm.dimtxt_antigo, IFERROR(_xlfn.XLOOKUP(_xlpm.chave, _xlpm.fonte, UTIL!CB:CB, "", 0), IFERROR(_xlfn.XLOOKUP("*"&_xlpm.chave&"*", _xlpm.fonte, UTIL!CB:CB, "", 2), "Não encontrado")), _xlpm.tipotxt, IF(_xlpm.tipoMod<>"", _xlpm.tipoMod, _xlpm.tipotxt_antigo), _xlpm.dimtxt, IF(_xlpm.dimMod<>"", _xlpm.dimMod, _xlpm.dimtxt_antigo), _xlpm.deTxt, IF(L10="CLIENTE", O10, IF(LEFT(L10,4)="http", L10, "MACPONTA AGRO DE "&L10)), _xlpm.paraBase, IF(M10="CLIENTE", P10, M10), _xlpm.paraTxt, IF(LEFT(_xlpm.paraBase,4)="http", _xlpm.paraBase, "MACPONTA AGRO DE "&_xlpm.paraBase), _xlpm.nfParte, IF(LEN(TRIM(I10))=0, "", " -NF "&TRIM(I10)), "- " & _xlpm.tipotxt & ": *" & G10 & "*" & CHAR(13)&CHAR(10) & "- " & _xlpm.dimtxt & CHAR(13)&CHAR(10) & "- *Cliente*: " & J10 & _xlpm.nfParte & CHAR(13)&CHAR(10) & "- *Obs:* " & Q10 & CHAR(13)&CHAR(10) & CHAR(10) & "- *De*: " & _xlpm.deTxt & CHAR(13)&CHAR(10) & "- *Para*: " & _xlpm.paraTxt & CHAR(13)&CHAR(10) & "- *Ida e volta*: +/- " & TEXT(((D10*1.5)/1440),"h:mm") & "h | " & D10 & "km" )} -> - PULVERIZADOR: *1NW4025MVKF190132*_x000D_ - A:3,34 x C:7,00 x L:2,72-3,30 x P:9.703kg_x000D_ - *Cliente*: MARLON BONILHA -NF61707 -NF 45965_x000D_ - *Obs:* Contato CEN Alison 43.98409-2094_x000D_ - *De*: MACPONTA AGRO DE PONTA GROSSA_x000D_ - *Para*: MACPONTA AGRO DE Fazenda Irmãos II - Cidade Tomazina - PR_x000D_ - *Ida e volta*: +/- 8:15h | 330km
A11: CONCLUIDO | B11: TERCEIRO NELSON | C11: 0.19236111 | D11: 185 | E11: =IFERROR((D11*7),"?") -> 1295 | F11: 1985 | G11: 1BM5060EAP4104558 | H11: 45965 | I11: 45965 | J11: MANUTENÇÃO → CLIENTE | K11: rafael.santos | L11: CLIENTE | M11: ARAPOTI | N11: DE CLIENTE PARA LOJA | O11: https://maps.app.goo.gl/PXTmMqoYPtx48Gex6 | P11: MPA | Q11: LUCIANO DE FREITAS - 43 99624-6946 | R11: =IF( OR( IFERROR(FIND("BM",G11),0)>0, IFERROR(FIND("PY",G11),0)>0 ), MID(TRIM(SUBSTITUTE(SUBSTITUTE(G11,CHAR(160),""),CHAR(9),"")),4,5), MID(TRIM(SUBSTITUTE(SUBSTITUTE(G11,CHAR(160),""),CHAR(9),"")),4,4) ) -> 5060E | S11: {=_xlfn.LET( _xlpm.ch, TRIM(SUBSTITUTE(G11,CHAR(160),"")), _xlpm.ehTrator, OR(IFERROR(FIND("BM",_xlpm.ch),0)>0, IFERROR(FIND("PY",_xlpm.ch),0)>0), _xlpm.chave, IF(_xlpm.ehTrator, MID(_xlpm.ch,4,5), MID(_xlpm.ch,4,4)), _xlpm.fonte, IF(LEN(_xlpm.chave)=5, UTIL!BV:BV, UTIL!BU:BU), _xlpm.modelo, TRIM(SUBSTITUTE(R11,CHAR(160),"")), _xlpm.nomeMod, IFERROR(_xlfn.XLOOKUP("*"&_xlpm.modelo&"*", UTIL!D:D, UTIL!B:B, "", 2), IFERROR(_xlfn.XLOOKUP("*"&_xlpm.modelo&"*", UTIL!E:E, UTIL!B:B, "", 2), "")), _xlpm.tipoMod, IF(_xlpm.nomeMod="", "", IFERROR(LEFT(_xlpm.nomeMod, FIND(" ", _xlpm.nomeMod)-1), _xlpm.nomeMod)), _xlpm.dimMod, IFERROR(_xlfn.XLOOKUP("*"&_xlpm.modelo&"*", UTIL!D:D, UTIL!K:K, "", 2), IFERROR(_xlfn.XLOOKUP("*"&_xlpm.modelo&"*", UTIL!E:E, UTIL!K:K, "", 2), "")), _xlpm.tipotxt_antigo, IF(_xlpm.ehTrator, "TRATOR", IFERROR(_xlfn.XLOOKUP(_xlpm.chave, _xlpm.fonte, UTIL!BS:BS, "", 0), IFERROR(_xlfn.XLOOKUP("*"&_xlpm.chave&"*", _xlpm.fonte, UTIL!BS:BS, "", 2), "Não encontrado"))), _xlpm.dimtxt_antigo, IFERROR(_xlfn.XLOOKUP(_xlpm.chave, _xlpm.fonte, UTIL!CB:CB, "", 0), IFERROR(_xlfn.XLOOKUP("*"&_xlpm.chave&"*", _xlpm.fonte, UTIL!CB:CB, "", 2), "Não encontrado")), _xlpm.tipotxt, IF(_xlpm.tipoMod<>"", _xlpm.tipoMod, _xlpm.tipotxt_antigo), _xlpm.dimtxt, IF(_xlpm.dimMod<>"", _xlpm.dimMod, _xlpm.dimtxt_antigo), _xlpm.deTxt, IF(L11="CLIENTE", O11, IF(LEFT(L11,4)="http", L11, "MACPONTA AGRO DE "&L11)), _xlpm.paraBase, IF(M11="CLIENTE", P11, M11), _xlpm.paraTxt, IF(LEFT(_xlpm.paraBase,4)="http", _xlpm.paraBase, "MACPONTA AGRO DE "&_xlpm.paraBase), _xlpm.nfParte, IF(LEN(TRIM(I11))=0, "", " -NF "&TRIM(I11)), "- " & _xlpm.tipotxt & ": *" & G11 & "*" & CHAR(13)&CHAR(10) & "- " & _xlpm.dimtxt & CHAR(13)&CHAR(10) & "- *Cliente*: " & J11 & _xlpm.nfParte & CHAR(13)&CHAR(10) & "- *Obs:* " & Q11 & CHAR(13)&CHAR(10) & CHAR(10) & "- *De*: " & _xlpm.deTxt & CHAR(13)&CHAR(10) & "- *Para*: " & _xlpm.paraTxt & CHAR(13)&CHAR(10) & "- *Ida e volta*: +/- " & TEXT(((D11*1.5)/1440),"h:mm") & "h | " & D11 & "km" )} -> - TRATOR: *1BM5060EAP4104558*_x000D_ - _x000D_ - *Cliente*: MANUTENÇÃO → CLIENTE -NF 45965_x000D_ - *Obs:* LUCIANO DE FREITAS - 43 99624-6946_x000D_ - *De*: https://maps.app.goo.gl/PXTmMqoYPtx48Gex6_x000D_ - *Para*: MACPONTA AGRO DE ARAPOTI_x000D_ - *Ida e volta*: +/- 4:37h | 185km
A12: CONCLUIDO | B12: PROPRIO DAF | C12: 0.052777778 | D12: 51 | E12: =IFERROR((D12*7),"?") -> 357 | F12: 0 | G12: 1BM7215CVR3000057 | H12: 45966 | I12: 45967 | J12: MANUTENÇÃO → CLIENTE | K12: marcelo.ferreira | L12: PONTA GROSSA | M12: CLIENTE | N12: DE LOJA PARA CLIENTE | O12: MPA | P12: https://maps.app.goo.gl/pQZUg9LPg5sgdyLs8 | Q12: GABRIEL - 42 -99972-7464 | R12: =IF( OR( IFERROR(FIND("BM",G12),0)>0, IFERROR(FIND("PY",G12),0)>0 ), MID(TRIM(SUBSTITUTE(SUBSTITUTE(G12,CHAR(160),""),CHAR(9),"")),4,5), MID(TRIM(SUBSTITUTE(SUBSTITUTE(G12,CHAR(160),""),CHAR(9),"")),4,4) ) -> 7215C | S12: {=_xlfn.LET( _xlpm.ch, TRIM(SUBSTITUTE(G12,CHAR(160),"")), _xlpm.ehTrator, OR(IFERROR(FIND("BM",_xlpm.ch),0)>0, IFERROR(FIND("PY",_xlpm.ch),0)>0), _xlpm.chave, IF(_xlpm.ehTrator, MID(_xlpm.ch,4,5), MID(_xlpm.ch,4,4)), _xlpm.fonte, IF(LEN(_xlpm.chave)=5, UTIL!BV:BV, UTIL!BU:BU), _xlpm.modelo, TRIM(SUBSTITUTE(R12,CHAR(160),"")), _xlpm.nomeMod, IFERROR(_xlfn.XLOOKUP("*"&_xlpm.modelo&"*", UTIL!D:D, UTIL!B:B, "", 2), IFERROR(_xlfn.XLOOKUP("*"&_xlpm.modelo&"*", UTIL!E:E, UTIL!B:B, "", 2), "")), _xlpm.tipoMod, IF(_xlpm.nomeMod="", "", IFERROR(LEFT(_xlpm.nomeMod, FIND(" ", _xlpm.nomeMod)-1), _xlpm.nomeMod)), _xlpm.dimMod, IFERROR(_xlfn.XLOOKUP("*"&_xlpm.modelo&"*", UTIL!D:D, UTIL!K:K, "", 2), IFERROR(_xlfn.XLOOKUP("*"&_xlpm.modelo&"*", UTIL!E:E, UTIL!K:K, "", 2), "")), _xlpm.tipotxt_antigo, IF(_xlpm.ehTrator, "TRATOR", IFERROR(_xlfn.XLOOKUP(_xlpm.chave, _xlpm.fonte, UTIL!BS:BS, "", 0), IFERROR(_xlfn.XLOOKUP("*"&_xlpm.chave&"*", _xlpm.fonte, UTIL!BS:BS, "", 2), "Não encontrado"))), _xlpm.dimtxt_antigo, IFERROR(_xlfn.XLOOKUP(_xlpm.chave, _xlpm.fonte, UTIL!CB:CB, "", 0), IFERROR(_xlfn.XLOOKUP("*"&_xlpm.chave&"*", _xlpm.fonte, UTIL!CB:CB, "", 2), "Não encontrado")), _xlpm.tipotxt, IF(_xlpm.tipoMod<>"", _xlpm.tipoMod, _xlpm.tipotxt_antigo), _xlpm.dimtxt, IF(_xlpm.dimMod<>"", _xlpm.dimMod, _xlpm.dimtxt_antigo), _xlpm.deTxt, IF(L12="CLIENTE", O12, IF(LEFT(L12,4)="http", L12, "MACPONTA AGRO DE "&L12)), _xlpm.paraBase, IF(M12="CLIENTE", P12, M12), _xlpm.paraTxt, IF(LEFT(_xlpm.paraBase,4)="http", _xlpm.paraBase, "MACPONTA AGRO DE "&_xlpm.paraBase), _xlpm.nfParte, IF(LEN(TRIM(I12))=0, "", " -NF "&TRIM(I12)), "- " & _xlpm.tipotxt & ": *" & G12 & "*" & CHAR(13)&CHAR(10) & "- " & _xlpm.dimtxt & CHAR(13)&CHAR(10) & "- *Cliente*: " & J12 & _xlpm.nfParte & CHAR(13)&CHAR(10) & "- *Obs:* " & Q12 & CHAR(13)&CHAR(10) & CHAR(10) & "- *De*: " & _xlpm.deTxt & CHAR(13)&CHAR(10) & "- *Para*: " & _xlpm.paraTxt & CHAR(13)&CHAR(10) & "- *Ida e volta*: +/- " & TEXT(((D12*1.5)/1440),"h:mm") & "h | " & D12 & "km" )} -> - TRATOR: *1BM7215CVR3000057*_x000D_ - _x000D_ - *Cliente*: MANUTENÇÃO → CLIENTE -NF 45967_x000D_ - *Obs:* GABRIEL - 42 -99972-7464_x000D_ - *De*: MACPONTA AGRO DE PONTA GROSSA_x000D_ - *Para*: https://maps.app.goo.gl/pQZUg9LPg5sgdyLs8_x000D_ - *Ida e volta*: +/- 1:16h | 51km
A13: CONCLUIDO | B13: PROPRIO VW | C13: 0.022916667 | D13: 22 | E13: =IFERROR((D13*7),"?") -> 154 | F13: 0 | G13: 1P06110DABA021136 | H13: 45966 | I13: 45967 | J13: MANUTENÇÃO → CLIENTE | K13: leonardo.ramos | L13: PONTA GROSSA | M13: CLIENTE | N13: DE LOJA PARA CLIENTE | O13: MPA | P13: https://maps.app.goo.gl/zzmzdRt4m8WXMVjg9 | Q13: JUNIOR +55 42 8866-3271 | R13: =IF( OR( IFERROR(FIND("BM",G13),0)>0, IFERROR(FIND("PY",G13),0)>0 ), MID(TRIM(SUBSTITUTE(SUBSTITUTE(G13,CHAR(160),""),CHAR(9),"")),4,5), MID(TRIM(SUBSTITUTE(SUBSTITUTE(G13,CHAR(160),""),CHAR(9),"")),4,4) ) -> 6110 | S13: {=_xlfn.LET( _xlpm.ch, TRIM(SUBSTITUTE(G13,CHAR(160),"")), _xlpm.ehTrator, OR(IFERROR(FIND("BM",_xlpm.ch),0)>0, IFERROR(FIND("PY",_xlpm.ch),0)>0), _xlpm.chave, IF(_xlpm.ehTrator, MID(_xlpm.ch,4,5), MID(_xlpm.ch,4,4)), _xlpm.fonte, IF(LEN(_xlpm.chave)=5, UTIL!BV:BV, UTIL!BU:BU), _xlpm.modelo, TRIM(SUBSTITUTE(R13,CHAR(160),"")), _xlpm.nomeMod, IFERROR(_xlfn.XLOOKUP("*"&_xlpm.modelo&"*", UTIL!D:D, UTIL!B:B, "", 2), IFERROR(_xlfn.XLOOKUP("*"&_xlpm.modelo&"*", UTIL!E:E, UTIL!B:B, "", 2), "")), _xlpm.tipoMod, IF(_xlpm.nomeMod="", "", IFERROR(LEFT(_xlpm.nomeMod, FIND(" ", _xlpm.nomeMod)-1), _xlpm.nomeMod)), _xlpm.dimMod, IFERROR(_xlfn.XLOOKUP("*"&_xlpm.modelo&"*", UTIL!D:D, UTIL!K:K, "", 2), IFERROR(_xlfn.XLOOKUP("*"&_xlpm.modelo&"*", UTIL!E:E, UTIL!K:K, "", 2), "")), _xlpm.tipotxt_antigo, IF(_xlpm.ehTrator, "TRATOR", IFERROR(_xlfn.XLOOKUP(_xlpm.chave, _xlpm.fonte, UTIL!BS:BS, "", 0), IFERROR(_xlfn.XLOOKUP("*"&_xlpm.chave&"*", _xlpm.fonte, UTIL!BS:BS, "", 2), "Não encontrado"))), _xlpm.dimtxt_antigo, IFERROR(_xlfn.XLOOKUP(_xlpm.chave, _xlpm.fonte, UTIL!CB:CB, "", 0), IFERROR(_xlfn.XLOOKUP("*"&_xlpm.chave&"*", _xlpm.fonte, UTIL!CB:CB, "", 2), "Não encontrado")), _xlpm.tipotxt, IF(_xlpm.tipoMod<>"", _xlpm.tipoMod, _xlpm.tipotxt_antigo), _xlpm.dimtxt, IF(_xlpm.dimMod<>"", _xlpm.dimMod, _xlpm.dimtxt_antigo), _xlpm.deTxt, IF(L13="CLIENTE", O13, IF(LEFT(L13,4)="http", L13, "MACPONTA AGRO DE "&L13)), _xlpm.paraBase, IF(M13="CLIENTE", P13, M13), _xlpm.paraTxt, IF(LEFT(_xlpm.paraBase,4)="http", _xlpm.paraBase, "MACPONTA AGRO DE "&_xlpm.paraBase), _xlpm.nfParte, IF(LEN(TRIM(I13))=0, "", " -NF "&TRIM(I13)), "- " & _xlpm.tipotxt & ": *" & G13 & "*" & CHAR(13)&CHAR(10) & "- " & _xlpm.dimtxt & CHAR(13)&CHAR(10) & "- *Cliente*: " & J13 & _xlpm.nfParte & CHAR(13)&CHAR(10) & "- *Obs:* " & Q13 & CHAR(13)&CHAR(10) & CHAR(10) & "- *De*: " & _xlpm.deTxt & CHAR(13)&CHAR(10) & "- *Para*: " & _xlpm.paraTxt & CHAR(13)&CHAR(10) & "- *Ida e volta*: +/- " & TEXT(((D13*1.5)/1440),"h:mm") & "h | " & D13 & "km" )} -> - : *1P06110DABA021136*_x000D_ - _x000D_ - *Cliente*: MANUTENÇÃO → CLIENTE -NF 45967_x000D_ - *Obs:* JUNIOR +55 42 8866-3271_x000D_ - *De*: MACPONTA AGRO DE PONTA GROSSA_x000D_ - *Para*: https://maps.app.goo.gl/zzmzdRt4m8WXMVjg9_x000D_ - *Ida e volta*: +/- 0:33h | 22km
... A20: CONCLUIDO | B20: PROPRIO DAF | C20: 0.18194444 | D20: 175 | E20: =IFERROR((D20*7),"?") -> 1225 | F20: 0 | G20: 1CQS680ATF0110209 | H20: 45968 | I20: 45969 | J20: DOUGLAS FANCHIN TAQUES FONSECA -NF278835 | K20: marcelo.ferreira | L20: PONTA GROSSA | M20: CLIENTE | N20: DE LOJA PARA CLIENTE | O20: MPA | P20: https://maps.app.goo.gl/GfTKV558G2iXHWmg8 | Q20: VALTINHO 42-99920-3056 | R20: =IF( OR( IFERROR(FIND("BM",G20),0)>0, IFERROR(FIND("PY",G20),0)>0 ), MID(TRIM(SUBSTITUTE(SUBSTITUTE(G20,CHAR(160),""),CHAR(9),"")),4,5), MID(TRIM(SUBSTITUTE(SUBSTITUTE(G20,CHAR(160),""),CHAR(9),"")),4,4) ) -> S680 | S20: {=_xlfn.LET( _xlpm.ch, TRIM(SUBSTITUTE(G20,CHAR(160),"")), _xlpm.ehTrator, OR(IFERROR(FIND("BM",_xlpm.ch),0)>0, IFERROR(FIND("PY",_xlpm.ch),0)>0), _xlpm.chave, IF(_xlpm.ehTrator, MID(_xlpm.ch,4,5), MID(_xlpm.ch,4,4)), _xlpm.fonte, IF(LEN(_xlpm.chave)=5, UTIL!BV:BV, UTIL!BU:BU), _xlpm.modelo, TRIM(SUBSTITUTE(R20,CHAR(160),"")), _xlpm.nomeMod, IFERROR(_xlfn.XLOOKUP("*"&_xlpm.modelo&"*", UTIL!D:D, UTIL!B:B, "", 2), IFERROR(_xlfn.XLOOKUP("*"&_xlpm.modelo&"*", UTIL!E:E, UTIL!B:B, "", 2), "")), _xlpm.tipoMod, IF(_xlpm.nomeMod="", "", IFERROR(LEFT(_xlpm.nomeMod, FIND(" ", _xlpm.nomeMod)-1), _xlpm.nomeMod)), _xlpm.dimMod, IFERROR(_xlfn.XLOOKUP("*"&_xlpm.modelo&"*", UTIL!D:D, UTIL!K:K, "", 2), IFERROR(_xlfn.XLOOKUP("*"&_xlpm.modelo&"*", UTIL!E:E, UTIL!K:K, "", 2), "")), _xlpm.tipotxt_antigo, IF(_xlpm.ehTrator, "TRATOR", IFERROR(_xlfn.XLOOKUP(_xlpm.chave, _xlpm.fonte, UTIL!BS:BS, "", 0), IFERROR(_xlfn.XLOOKUP("*"&_xlpm.chave&"*", _xlpm.fonte, UTIL!BS:BS, "", 2), "Não encontrado"))), _xlpm.dimtxt_antigo, IFERROR(_xlfn.XLOOKUP(_xlpm.chave, _xlpm.fonte, UTIL!CB:CB, "", 0), IFERROR(_xlfn.XLOOKUP("*"&_xlpm.chave&"*", _xlpm.fonte, UTIL!CB:CB, "", 2), "Não encontrado")), _xlpm.tipotxt, IF(_xlpm.tipoMod<>"", _xlpm.tipoMod, _xlpm.tipotxt_antigo), _xlpm.dimtxt, IF(_xlpm.dimMod<>"", _xlpm.dimMod, _xlpm.dimtxt_antigo), _xlpm.deTxt, IF(L20="CLIENTE", O20, IF(LEFT(L20,4)="http", L20, "MACPONTA AGRO DE "&L20)), _xlpm.paraBase, IF(M20="CLIENTE", P20, M20), _xlpm.paraTxt, IF(LEFT(_xlpm.paraBase,4)="http", _xlpm.paraBase, "MACPONTA AGRO DE "&_xlpm.paraBase), _xlpm.nfParte, IF(LEN(TRIM(I20))=0, "", " -NF "&TRIM(I20)), "- " & _xlpm.tipotxt & ": *" & G20 & "*" & CHAR(13)&CHAR(10) & "- " & _xlpm.dimtxt & CHAR(13)&CHAR(10) & "- *Cliente*: " & J20 & _xlpm.nfParte & CHAR(13)&CHAR(10) & "- *Obs:* " & Q20 & CHAR(13)&CHAR(10) & CHAR(10) & "- *De*: " & _xlpm.deTxt & CHAR(13)&CHAR(10) & "- *Para*: " & _xlpm.paraTxt & CHAR(13)&CHAR(10) & "- *Ida e volta*: +/- " & TEXT(((D20*1.5)/1440),"h:mm") & "h | " & D20 & "km" )} -> - COLHEITADEIRA: *1CQS680ATF0110209*_x000D_ - A:3,98 x C:12,10 x L:3,50-5,43 x P:21.921kg_x000D_ - *Cliente*: DOUGLAS FANCHIN TAQUES FONSECA -NF278835 -NF 45969_x000D_ - *Obs:* VALTINHO 42-99920-3056_x000D_ - *De*: MACPONTA AGRO DE PONTA GROSSA_x000D_ - *Para*: https://maps.app.goo.gl/GfTKV558G2iXHWmg8_x000D_ - *Ida e volta*: +/- 4:22h | 175km
A21: CONCLUIDO | B21: TERCEIRO MAZETTO | C21: 0.34375 | D21: 330 | E21: =IFERROR((D21*7),"?") -> 2310 | G21: 1BM6100JVSD602522 | H21: 45968 | I21: 45968 | J21: ADILSON KRASSOSKI -NF11620 | K21: euclides.junior | L21: GUARAPUAVA | M21: CLIENTE | N21: DE LOJA PARA CLIENTE | O21: MPA | P21: https://maps.app.goo.gl/nUnfbBeivgDPDFmy6 | Q21: Adilson | R21: =IF( OR( IFERROR(FIND("BM",G21),0)>0, IFERROR(FIND("PY",G21),0)>0 ), MID(TRIM(SUBSTITUTE(SUBSTITUTE(G21,CHAR(160),""),CHAR(9),"")),4,5), MID(TRIM(SUBSTITUTE(SUBSTITUTE(G21,CHAR(160),""),CHAR(9),"")),4,4) ) -> 6100J | S21: {=_xlfn.LET( _xlpm.ch, TRIM(SUBSTITUTE(G21,CHAR(160),"")), _xlpm.ehTrator, OR(IFERROR(FIND("BM",_xlpm.ch),0)>0, IFERROR(FIND("PY",_xlpm.ch),0)>0), _xlpm.chave, IF(_xlpm.ehTrator, MID(_xlpm.ch,4,5), MID(_xlpm.ch,4,4)), _xlpm.fonte, IF(LEN(_xlpm.chave)=5, UTIL!BV:BV, UTIL!BU:BU), _xlpm.modelo, TRIM(SUBSTITUTE(R21,CHAR(160),"")), _xlpm.nomeMod, IFERROR(_xlfn.XLOOKUP("*"&_xlpm.modelo&"*", UTIL!D:D, UTIL!B:B, "", 2), IFERROR(_xlfn.XLOOKUP("*"&_xlpm.modelo&"*", UTIL!E:E, UTIL!B:B, "", 2), "")), _xlpm.tipoMod, IF(_xlpm.nomeMod="", "", IFERROR(LEFT(_xlpm.nomeMod, FIND(" ", _xlpm.nomeMod)-1), _xlpm.nomeMod)), _xlpm.dimMod, IFERROR(_xlfn.XLOOKUP("*"&_xlpm.modelo&"*", UTIL!D:D, UTIL!K:K, "", 2), IFERROR(_xlfn.XLOOKUP("*"&_xlpm.modelo&"*", UTIL!E:E, UTIL!K:K, "", 2), "")), _xlpm.tipotxt_antigo, IF(_xlpm.ehTrator, "TRATOR", IFERROR(_xlfn.XLOOKUP(_xlpm.chave, _xlpm.fonte, UTIL!BS:BS, "", 0), IFERROR(_xlfn.XLOOKUP("*"&_xlpm.chave&"*", _xlpm.fonte, UTIL!BS:BS, "", 2), "Não encontrado"))), _xlpm.dimtxt_antigo, IFERROR(_xlfn.XLOOKUP(_xlpm.chave, _xlpm.fonte, UTIL!CB:CB, "", 0), IFERROR(_xlfn.XLOOKUP("*"&_xlpm.chave&"*", _xlpm.fonte, UTIL!CB:CB, "", 2), "Não encontrado")), _xlpm.tipotxt, IF(_xlpm.tipoMod<>"", _xlpm.tipoMod, _xlpm.tipotxt_antigo), _xlpm.dimtxt, IF(_xlpm.dimMod<>"", _xlpm.dimMod, _xlpm.dimtxt_antigo), _xlpm.deTxt, IF(L21="CLIENTE", O21, IF(LEFT(L21,4)="http", L21, "MACPONTA AGRO DE "&L21)), _xlpm.paraBase, IF(M21="CLIENTE", P21, M21), _xlpm.paraTxt, IF(LEFT(_xlpm.paraBase,4)="http", _xlpm.paraBase, "MACPONTA AGRO DE "&_xlpm.paraBase), _xlpm.nfParte, IF(LEN(TRIM(I21))=0, "", " -NF "&TRIM(I21)), "- " & _xlpm.tipotxt & ": *" & G21 & "*" & CHAR(13)&CHAR(10) & "- " & _xlpm.dimtxt & CHAR(13)&CHAR(10) & "- *Cliente*: " & J21 & _xlpm.nfParte & CHAR(13)&CHAR(10) & "- *Obs:* " & Q21 & CHAR(13)&CHAR(10) & CHAR(10) & "- *De*: " & _xlpm.deTxt & CHAR(13)&CHAR(10) & "- *Para*: " & _xlpm.paraTxt & CHAR(13)&CHAR(10) & "- *Ida e volta*: +/- " & TEXT(((D21*1.5)/1440),"h:mm") & "h | " & D21 & "km" )} -> - TRATOR: *1BM6100JVSD602522*_x000D_ - _x000D_ - *Cliente*: ADILSON KRASSOSKI -NF11620 -NF 45968_x000D_ - *Obs:* Adilson_x000D_ - *De*: MACPONTA AGRO DE GUARAPUAVA_x000D_ - *Para*: https://maps.app.goo.gl/nUnfbBeivgDPDFmy6_x000D_ - *Ida e volta*: +/- 8:15h | 330km
A22: CONCLUIDO | B22: PROPRIO DAF | C22: 0.33819444 | D22: 325 | E22: =IFERROR((D22*7),"?") -> 2275 | F22: 0 | G22: 9AGC1007EHS000187 | H22: 45972 | I22: 45972 | J22: TRANSF -NF000076891 | K22: marcio.jacovossi | L22: IRATI | M22: PRUDENTÓPOLIS | N22: DE LOJA PARA LOJA | O22: MPA | P22: MPA | Q22: N/A | R22: =IF( OR( IFERROR(FIND("BM",G22),0)>0, IFERROR(FIND("PY",G22),0)>0 ), MID(TRIM(SUBSTITUTE(SUBSTITUTE(G22,CHAR(160),""),CHAR(9),"")),4,5), MID(TRIM(SUBSTITUTE(SUBSTITUTE(G22,CHAR(160),""),CHAR(9),"")),4,4) ) -> C100 | S22: {=_xlfn.LET( _xlpm.ch, TRIM(SUBSTITUTE(G22,CHAR(160),"")), _xlpm.ehTrator, OR(IFERROR(FIND("BM",_xlpm.ch),0)>0, IFERROR(FIND("PY",_xlpm.ch),0)>0), _xlpm.chave, IF(_xlpm.ehTrator, MID(_xlpm.ch,4,5), MID(_xlpm.ch,4,4)), _xlpm.fonte, IF(LEN(_xlpm.chave)=5, UTIL!BV:BV, UTIL!BU:BU), _xlpm.modelo, TRIM(SUBSTITUTE(R22,CHAR(160),"")), _xlpm.nomeMod, IFERROR(_xlfn.XLOOKUP("*"&_xlpm.modelo&"*", UTIL!D:D, UTIL!B:B, "", 2), IFERROR(_xlfn.XLOOKUP("*"&_xlpm.modelo&"*", UTIL!E:E, UTIL!B:B, "", 2), "")), _xlpm.tipoMod, IF(_xlpm.nomeMod="", "", IFERROR(LEFT(_xlpm.nomeMod, FIND(" ", _xlpm.nomeMod)-1), _xlpm.nomeMod)), _xlpm.dimMod, IFERROR(_xlfn.XLOOKUP("*"&_xlpm.modelo&"*", UTIL!D:D, UTIL!K:K, "", 2), IFERROR(_xlfn.XLOOKUP("*"&_xlpm.modelo&"*", UTIL!E:E, UTIL!K:K, "", 2), "")), _xlpm.tipotxt_antigo, IF(_xlpm.ehTrator, "TRATOR", IFERROR(_xlfn.XLOOKUP(_xlpm.chave, _xlpm.fonte, UTIL!BS:BS, "", 0), IFERROR(_xlfn.XLOOKUP("*"&_xlpm.chave&"*", _xlpm.fonte, UTIL!BS:BS, "", 2), "Não encontrado"))), _xlpm.dimtxt_antigo, IFERROR(_xlfn.XLOOKUP(_xlpm.chave, _xlpm.fonte, UTIL!CB:CB, "", 0), IFERROR(_xlfn.XLOOKUP("*"&_xlpm.chave&"*", _xlpm.fonte, UTIL!CB:CB, "", 2), "Não encontrado")), _xlpm.tipotxt, IF(_xlpm.tipoMod<>"", _xlpm.tipoMod, _xlpm.tipotxt_antigo), _xlpm.dimtxt, IF(_xlpm.dimMod<>"", _xlpm.dimMod, _xlpm.dimtxt_antigo), _xlpm.deTxt, IF(L22="CLIENTE", O22, IF(LEFT(L22,4)="http", L22, "MACPONTA AGRO DE "&L22)), _xlpm.paraBase, IF(M22="CLIENTE", P22, M22), _xlpm.paraTxt, IF(LEFT(_xlpm.paraBase,4)="http", _xlpm.paraBase, "MACPONTA AGRO DE "&_xlpm.paraBase), _xlpm.nfParte, IF(LEN(TRIM(I22))=0, "", " -NF "&TRIM(I22)), "- " & _xlpm.tipotxt & ": *" & G22 & "*" & CHAR(13)&CHAR(10) & "- " & _xlpm.dimtxt & CHAR(13)&CHAR(10) & "- *Cliente*: " & J22 & _xlpm.nfParte & CHAR(13)&CHAR(10) & "- *Obs:* " & Q22 & CHAR(13)&CHAR(10) & CHAR(10) & "- *De*: " & _xlpm.deTxt & CHAR(13)&CHAR(10) & "- *Para*: " & _xlpm.paraTxt & CHAR(13)&CHAR(10) & "- *Ida e volta*: +/- " & TEXT(((D22*1.5)/1440),"h:mm") & "h | " & D22 & "km" )} -> - : *9AGC1007EHS000187*_x000D_ - _x000D_ - *Cliente*: TRANSF -NF000076891 -NF 45972_x000D_ - *Obs:* N/A_x000D_ - *De*: MACPONTA AGRO DE IRATI_x000D_ - *Para*: MACPONTA AGRO DE PRUDENTÓPOLIS_x000D_ - *Ida e volta*: +/- 8:07h | 325km
A23: CONCLUIDO | B23: PROPRIO DAF | C23: 0.33819444 | D23: 325 | E23: =IFERROR((D23*7),"?") -> 2275 | F23: 0 | G23: AAAP1112CGS000944 | H23: 45972 | I23: 45972 | J23: TRANSF -NF000076886 | K23: marcio.jacovossi | L23: IRATI | M23: PRUDENTÓPOLIS | N23: DE LOJA PARA LOJA | O23: MPA | P23: MPA | Q23: N/A | R23: =IF( OR( IFERROR(FIND("BM",G23),0)>0, IFERROR(FIND("PY",G23),0)>0 ), MID(TRIM(SUBSTITUTE(SUBSTITUTE(G23,CHAR(160),""),CHAR(9),"")),4,5), MID(TRIM(SUBSTITUTE(SUBSTITUTE(G23,CHAR(160),""),CHAR(9),"")),4,4) ) -> P111 | S23: {=_xlfn.LET( _xlpm.ch, TRIM(SUBSTITUTE(G23,CHAR(160),"")), _xlpm.ehTrator, OR(IFERROR(FIND("BM",_xlpm.ch),0)>0, IFERROR(FIND("PY",_xlpm.ch),0)>0), _xlpm.chave, IF(_xlpm.ehTrator, MID(_xlpm.ch,4,5), MID(_xlpm.ch,4,4)), _xlpm.fonte, IF(LEN(_xlpm.chave)=5, UTIL!BV:BV, UTIL!BU:BU), _xlpm.modelo, TRIM(SUBSTITUTE(R23,CHAR(160),"")), _xlpm.nomeMod, IFERROR(_xlfn.XLOOKUP("*"&_xlpm.modelo&"*", UTIL!D:D, UTIL!B:B, "", 2), IFERROR(_xlfn.XLOOKUP("*"&_xlpm.modelo&"*", UTIL!E:E, UTIL!B:B, "", 2), "")), _xlpm.tipoMod, IF(_xlpm.nomeMod="", "", IFERROR(LEFT(_xlpm.nomeMod, FIND(" ", _xlpm.nomeMod)-1), _xlpm.nomeMod)), _xlpm.dimMod, IFERROR(_xlfn.XLOOKUP("*"&_xlpm.modelo&"*", UTIL!D:D, UTIL!K:K, "", 2), IFERROR(_xlfn.XLOOKUP("*"&_xlpm.modelo&"*", UTIL!E:E, UTIL!K:K, "", 2), "")), _xlpm.tipotxt_antigo, IF(_xlpm.ehTrator, "TRATOR", IFERROR(_xlfn.XLOOKUP(_xlpm.chave, _xlpm.fonte, UTIL!BS:BS, "", 0), IFERROR(_xlfn.XLOOKUP("*"&_xlpm.chave&"*", _xlpm.fonte, UTIL!BS:BS, "", 2), "Não encontrado"))), _xlpm.dimtxt_antigo, IFERROR(_xlfn.XLOOKUP(_xlpm.chave, _xlpm.fonte, UTIL!CB:CB, "", 0), IFERROR(_xlfn.XLOOKUP("*"&_xlpm.chave&"*", _xlpm.fonte, UTIL!CB:CB, "", 2), "Não encontrado")), _xlpm.tipotxt, IF(_xlpm.tipoMod<>"", _xlpm.tipoMod, _xlpm.tipotxt_antigo), _xlpm.dimtxt, IF(_xlpm.dimMod<>"", _xlpm.dimMod, _xlpm.dimtxt_antigo), _xlpm.deTxt, IF(L23="CLIENTE", O23, IF(LEFT(L23,4)="http", L23, "MACPONTA AGRO DE "&L23)), _xlpm.paraBase, IF(M23="CLIENTE", P23, M23), _xlpm.paraTxt, IF(LEFT(_xlpm.paraBase,4)="http", _xlpm.paraBase, "MACPONTA AGRO DE "&_xlpm.paraBase), _xlpm.nfParte, IF(LEN(TRIM(I23))=0, "", " -NF "&TRIM(I23)), "- " & _xlpm.tipotxt & ": *" & G23 & "*" & CHAR(13)&CHAR(10) & "- " & _xlpm.dimtxt & CHAR(13)&CHAR(10) & "- *Cliente*: " & J23 & _xlpm.nfParte & CHAR(13)&CHAR(10) & "- *Obs:* " & Q23 & CHAR(13)&CHAR(10) & CHAR(10) & "- *De*: " & _xlpm.deTxt & CHAR(13)&CHAR(10) & "- *Para*: " & _xlpm.paraTxt & CHAR(13)&CHAR(10) & "- *Ida e volta*: +/- " & TEXT(((D23*1.5)/1440),"h:mm") & "h | " & D23 & "km" )} -> - : *AAAP1112CGS000944*_x000D_ - _x000D_ - *Cliente*: TRANSF -NF000076886 -NF 45972_x000D_ - *Obs:* N/A_x000D_ - *De*: MACPONTA AGRO DE IRATI_x000D_ - *Para*: MACPONTA AGRO DE PRUDENTÓPOLIS_x000D_ - *Ida e volta*: +/- 8:07h | 325km
A24: CONCLUIDO | B24: PROPRIO DAF | C24: 0.26527778 | D24: 255 | E24: =IFERROR((D24*7),"?") -> 1785 | F24: 0 | G24: 1BM6150JCSD642412 | H24: 45972 | I24: 45972 | J24: TRANSF -NF000076884 | K24: marcio.jacovossi | L24: IRATI | M24: PRUDENTÓPOLIS | N24: DE LOJA PARA LOJA | O24: MPA | P24: MPA | Q24: N/A | R24: =IF( OR( IFERROR(FIND("BM",G24),0)>0, IFERROR(FIND("PY",G24),0)>0 ), MID(TRIM(SUBSTITUTE(SUBSTITUTE(G24,CHAR(160),""),CHAR(9),"")),4,5), MID(TRIM(SUBSTITUTE(SUBSTITUTE(G24,CHAR(160),""),CHAR(9),"")),4,4) ) -> 6150J | S24: {=_xlfn.LET( _xlpm.ch, TRIM(SUBSTITUTE(G24,CHAR(160),"")), _xlpm.ehTrator, OR(IFERROR(FIND("BM",_xlpm.ch),0)>0, IFERROR(FIND("PY",_xlpm.ch),0)>0), _xlpm.chave, IF(_xlpm.ehTrator, MID(_xlpm.ch,4,5), MID(_xlpm.ch,4,4)), _xlpm.fonte, IF(LEN(_xlpm.chave)=5, UTIL!BV:BV, UTIL!BU:BU), _xlpm.modelo, TRIM(SUBSTITUTE(R24,CHAR(160),"")), _xlpm.nomeMod, IFERROR(_xlfn.XLOOKUP("*"&_xlpm.modelo&"*", UTIL!D:D, UTIL!B:B, "", 2), IFERROR(_xlfn.XLOOKUP("*"&_xlpm.modelo&"*", UTIL!E:E, UTIL!B:B, "", 2), "")), _xlpm.tipoMod, IF(_xlpm.nomeMod="", "", IFERROR(LEFT(_xlpm.nomeMod, FIND(" ", _xlpm.nomeMod)-1), _xlpm.nomeMod)), _xlpm.dimMod, IFERROR(_xlfn.XLOOKUP("*"&_xlpm.modelo&"*", UTIL!D:D, UTIL!K:K, "", 2), IFERROR(_xlfn.XLOOKUP("*"&_xlpm.modelo&"*", UTIL!E:E, UTIL!K:K, "", 2), "")), _xlpm.tipotxt_antigo, IF(_xlpm.ehTrator, "TRATOR", IFERROR(_xlfn.XLOOKUP(_xlpm.chave, _xlpm.fonte, UTIL!BS:BS, "", 0), IFERROR(_xlfn.XLOOKUP("*"&_xlpm.chave&"*", _xlpm.fonte, UTIL!BS:BS, "", 2), "Não encontrado"))), _xlpm.dimtxt_antigo, IFERROR(_xlfn.XLOOKUP(_xlpm.chave, _xlpm.fonte, UTIL!CB:CB, "", 0), IFERROR(_xlfn.XLOOKUP("*"&_xlpm.chave&"*", _xlpm.fonte, UTIL!CB:CB, "", 2), "Não encontrado")), _xlpm.tipotxt, IF(_xlpm.tipoMod<>"", _xlpm.tipoMod, _xlpm.tipotxt_antigo), _xlpm.dimtxt, IF(_xlpm.dimMod<>"", _xlpm.dimMod, _xlpm.dimtxt_antigo), _xlpm.deTxt, IF(L24="CLIENTE", O24, IF(LEFT(L24,4)="http", L24, "MACPONTA AGRO DE "&L24)), _xlpm.paraBase, IF(M24="CLIENTE", P24, M24), _xlpm.paraTxt, IF(LEFT(_xlpm.paraBase,4)="http", _xlpm.paraBase, "MACPONTA AGRO DE "&_xlpm.paraBase), _xlpm.nfParte, IF(LEN(TRIM(I24))=0, "", " -NF "&TRIM(I24)), "- " & _xlpm.tipotxt & ": *" & G24 & "*" & CHAR(13)&CHAR(10) & "- " & _xlpm.dimtxt & CHAR(13)&CHAR(10) & "- *Cliente*: " & J24 & _xlpm.nfParte & CHAR(13)&CHAR(10) & "- *Obs:* " & Q24 & CHAR(13)&CHAR(10) & CHAR(10) & "- *De*: " & _xlpm.deTxt & CHAR(13)&CHAR(10) & "- *Para*: " & _xlpm.paraTxt & CHAR(13)&CHAR(10) & "- *Ida e volta*: +/- " & TEXT(((D24*1.5)/1440),"h:mm") & "h | " & D24 & "km" )} -> - TRATOR: *1BM6150JCSD642412*_x000D_ - _x000D_ - *Cliente*: TRANSF -NF000076884 -NF 45972_x000D_ - *Obs:* N/A_x000D_ - *De*: MACPONTA AGRO DE IRATI_x000D_ - *Para*: MACPONTA AGRO DE PRUDENTÓPOLIS_x000D_ - *Ida e volta*: +/- 6:22h | 255km
A25: CONCLUIDO | B25: PROPRIO DAF | C25: 0.26527778 | D25: 255 | E25: =IFERROR((D25*7),"?") -> 1785 | F25: 0 | G25: 1BM5078EHS4200616 | H25: 45972 | I25: 45972 | J25: TRANSF -NF000076884 | K25: marcio.jacovossi | L25: IRATI | M25: PRUDENTÓPOLIS | N25: DE LOJA PARA LOJA | O25: MPA | P25: MPA | Q25: N/A | R25: =IF( OR( IFERROR(FIND("BM",G25),0)>0, IFERROR(FIND("PY",G25),0)>0 ), MID(TRIM(SUBSTITUTE(SUBSTITUTE(G25,CHAR(160),""),CHAR(9),"")),4,5), MID(TRIM(SUBSTITUTE(SUBSTITUTE(G25,CHAR(160),""),CHAR(9),"")),4,4) ) -> 5078E | S25: {=_xlfn.LET( _xlpm.ch, TRIM(SUBSTITUTE(G25,CHAR(160),"")), _xlpm.ehTrator, OR(IFERROR(FIND("BM",_xlpm.ch),0)>0, IFERROR(FIND("PY",_xlpm.ch),0)>0), _xlpm.chave, IF(_xlpm.ehTrator, MID(_xlpm.ch,4,5), MID(_xlpm.ch,4,4)), _xlpm.fonte, IF(LEN(_xlpm.chave)=5, UTIL!BV:BV, UTIL!BU:BU), _xlpm.modelo, TRIM(SUBSTITUTE(R25,CHAR(160),"")), _xlpm.nomeMod, IFERROR(_xlfn.XLOOKUP("*"&_xlpm.modelo&"*", UTIL!D:D, UTIL!B:B, "", 2), IFERROR(_xlfn.XLOOKUP("*"&_xlpm.modelo&"*", UTIL!E:E, UTIL!B:B, "", 2), "")), _xlpm.tipoMod, IF(_xlpm.nomeMod="", "", IFERROR(LEFT(_xlpm.nomeMod, FIND(" ", _xlpm.nomeMod)-1), _xlpm.nomeMod)), _xlpm.dimMod, IFERROR(_xlfn.XLOOKUP("*"&_xlpm.modelo&"*", UTIL!D:D, UTIL!K:K, "", 2), IFERROR(_xlfn.XLOOKUP("*"&_xlpm.modelo&"*", UTIL!E:E, UTIL!K:K, "", 2), "")), _xlpm.tipotxt_antigo, IF(_xlpm.ehTrator, "TRATOR", IFERROR(_xlfn.XLOOKUP(_xlpm.chave, _xlpm.fonte, UTIL!BS:BS, "", 0), IFERROR(_xlfn.XLOOKUP("*"&_xlpm.chave&"*", _xlpm.fonte, UTIL!BS:BS, "", 2), "Não encontrado"))), _xlpm.dimtxt_antigo, IFERROR(_xlfn.XLOOKUP(_xlpm.chave, _xlpm.fonte, UTIL!CB:CB, "", 0), IFERROR(_xlfn.XLOOKUP("*"&_xlpm.chave&"*", _xlpm.fonte, UTIL!CB:CB, "", 2), "Não encontrado")), _xlpm.tipotxt, IF(_xlpm.tipoMod<>"", _xlpm.tipoMod, _xlpm.tipotxt_antigo), _xlpm.dimtxt, IF(_xlpm.dimMod<>"", _xlpm.dimMod, _xlpm.dimtxt_antigo), _xlpm.deTxt, IF(L25="CLIENTE", O25, IF(LEFT(L25,4)="http", L25, "MACPONTA AGRO DE "&L25)), _xlpm.paraBase, IF(M25="CLIENTE", P25, M25), _xlpm.paraTxt, IF(LEFT(_xlpm.paraBase,4)="http", _xlpm.paraBase, "MACPONTA AGRO DE "&_xlpm.paraBase), _xlpm.nfParte, IF(LEN(TRIM(I25))=0, "", " -NF "&TRIM(I25)), "- " & _xlpm.tipotxt & ": *" & G25 & "*" & CHAR(13)&CHAR(10) & "- " & _xlpm.dimtxt & CHAR(13)&CHAR(10) & "- *Cliente*: " & J25 & _xlpm.nfParte & CHAR(13)&CHAR(10) & "- *Obs:* " & Q25 & CHAR(13)&CHAR(10) & CHAR(10) & "- *De*: " & _xlpm.deTxt & CHAR(13)&CHAR(10) & "- *Para*: " & _xlpm.paraTxt & CHAR(13)&CHAR(10) & "- *Ida e volta*: +/- " & TEXT(((D25*1.5)/1440),"h:mm") & "h | " & D25 & "km" )} -> - TRATOR: *1BM5078EHS4200616*_x000D_ - _x000D_ - *Cliente*: TRANSF -NF000076884 -NF 45972_x000D_ - *Obs:* N/A_x000D_ - *De*: MACPONTA AGRO DE IRATI_x000D_ - *Para*: MACPONTA AGRO DE PRUDENTÓPOLIS_x000D_ - *Ida e volta*: +/- 6:22h | 255km
A26: CONCLUIDO | B26: TERCEIRO MAZETTO | C26: 0.08125 | D26: 78 | E26: =IFERROR((D26*7),"?") -> 546 | G26: 1BM6100JESD602123 | H26: 45972 | I26: 45972 | J26: OSWALDO R BARBOSA -NF107698 | K26: euclides.junior | L26: PRUDENTÓPOLIS | M26: CLIENTE | N26: DE LOJA PARA CLIENTE | O26: MPA | P26: https://maps.app.goo.gl/3mYP9KzrASogJS3w9 | Q26: Oswaldo | R26: =IF( OR( IFERROR(FIND("BM",G26),0)>0, IFERROR(FIND("PY",G26),0)>0 ), MID(TRIM(SUBSTITUTE(SUBSTITUTE(G26,CHAR(160),""),CHAR(9),"")),4,5), MID(TRIM(SUBSTITUTE(SUBSTITUTE(G26,CHAR(160),""),CHAR(9),"")),4,4) ) -> 6100J | S26: {=_xlfn.LET( _xlpm.ch, TRIM(SUBSTITUTE(G26,CHAR(160),"")), _xlpm.ehTrator, OR(IFERROR(FIND("BM",_xlpm.ch),0)>0, IFERROR(FIND("PY",_xlpm.ch),0)>0), _xlpm.chave, IF(_xlpm.ehTrator, MID(_xlpm.ch,4,5), MID(_xlpm.ch,4,4)), _xlpm.fonte, IF(LEN(_xlpm.chave)=5, UTIL!BV:BV, UTIL!BU:BU), _xlpm.modelo, TRIM(SUBSTITUTE(R26,CHAR(160),"")), _xlpm.nomeMod, IFERROR(_xlfn.XLOOKUP("*"&_xlpm.modelo&"*", UTIL!D:D, UTIL!B:B, "", 2), IFERROR(_xlfn.XLOOKUP("*"&_xlpm.modelo&"*", UTIL!E:E, UTIL!B:B, "", 2), "")), _xlpm.tipoMod, IF(_xlpm.nomeMod="", "", IFERROR(LEFT(_xlpm.nomeMod, FIND(" ", _xlpm.nomeMod)-1), _xlpm.nomeMod)), _xlpm.dimMod, IFERROR(_xlfn.XLOOKUP("*"&_xlpm.modelo&"*", UTIL!D:D, UTIL!K:K, "", 2), IFERROR(_xlfn.XLOOKUP("*"&_xlpm.modelo&"*", UTIL!E:E, UTIL!K:K, "", 2), "")), _xlpm.tipotxt_antigo, IF(_xlpm.ehTrator, "TRATOR", IFERROR(_xlfn.XLOOKUP(_xlpm.chave, _xlpm.fonte, UTIL!BS:BS, "", 0), IFERROR(_xlfn.XLOOKUP("*"&_xlpm.chave&"*", _xlpm.fonte, UTIL!BS:BS, "", 2), "Não encontrado"))), _xlpm.dimtxt_antigo, IFERROR(_xlfn.XLOOKUP(_xlpm.chave, _xlpm.fonte, UTIL!CB:CB, "", 0), IFERROR(_xlfn.XLOOKUP("*"&_xlpm.chave&"*", _xlpm.fonte, UTIL!CB:CB, "", 2), "Não encontrado")), _xlpm.tipotxt, IF(_xlpm.tipoMod<>"", _xlpm.tipoMod, _xlpm.tipotxt_antigo), _xlpm.dimtxt, IF(_xlpm.dimMod<>"", _xlpm.dimMod, _xlpm.dimtxt_antigo), _xlpm.deTxt, IF(L26="CLIENTE", O26, IF(LEFT(L26,4)="http", L26, "MACPONTA AGRO DE "&L26)), _xlpm.paraBase, IF(M26="CLIENTE", P26, M26), _xlpm.paraTxt, IF(LEFT(_xlpm.paraBase,4)="http", _xlpm.paraBase, "MACPONTA AGRO DE "&_xlpm.paraBase), _xlpm.nfParte, IF(LEN(TRIM(I26))=0, "", " -NF "&TRIM(I26)), "- " & _xlpm.tipotxt & ": *" & G26 & "*" & CHAR(13)&CHAR(10) & "- " & _xlpm.dimtxt & CHAR(13)&CHAR(10) & "- *Cliente*: " & J26 & _xlpm.nfParte & CHAR(13)&CHAR(10) & "- *Obs:* " & Q26 & CHAR(13)&CHAR(10) & CHAR(10) & "- *De*: " & _xlpm.deTxt & CHAR(13)&CHAR(10) & "- *Para*: " & _xlpm.paraTxt & CHAR(13)&CHAR(10) & "- *Ida e volta*: +/- " & TEXT(((D26*1.5)/1440),"h:mm") & "h | " & D26 & "km" )} -> - TRATOR: *1BM6100JESD602123*_x000D_ - _x000D_ - *Cliente*: OSWALDO R BARBOSA -NF107698 -NF 45972_x000D_ - *Obs:* Oswaldo_x000D_ - *De*: MACPONTA AGRO DE PRUDENTÓPOLIS_x000D_ - *Para*: https://maps.app.goo.gl/3mYP9KzrASogJS3w9_x000D_ - *Ida e volta*: +/- 1:57h | 78km
A27: CONCLUIDO (D) | B27: PROPRIO DAF | C27: 0.52083333 | D27: 500 | E27: =IFERROR((D27*7),"?") -> 3500 | F27: 0 | G27: 1CQS550APS0160136 | H27: 45972 | I27: 45971 | J27: DOUGLAS FONSECA -NF 107225 | K27: marcelo.ferreira | L27: GUARAPUAVA | M27: CLIENTE | N27: DE LOJA PARA DEMONSTRAÇÃO | O27: MPA | P27: https://maps.app.goo.gl/xyQpe8BG44WqsG1v9 | Q27: N/A | R27: =IF( OR( IFERROR(FIND("BM",G27),0)>0, IFERROR(FIND("PY",G27),0)>0 ), MID(TRIM(SUBSTITUTE(SUBSTITUTE(G27,CHAR(160),""),CHAR(9),"")),4,5), MID(TRIM(SUBSTITUTE(SUBSTITUTE(G27,CHAR(160),""),CHAR(9),"")),4,4) ) -> S550 | S27: {=_xlfn.LET( _xlpm.ch, TRIM(SUBSTITUTE(G27,CHAR(160),"")), _xlpm.ehTrator, OR(IFERROR(FIND("BM",_xlpm.ch),0)>0, IFERROR(FIND("PY",_xlpm.ch),0)>0), _xlpm.chave, IF(_xlpm.ehTrator, MID(_xlpm.ch,4,5), MID(_xlpm.ch,4,4)), _xlpm.fonte, IF(LEN(_xlpm.chave)=5, UTIL!BV:BV, UTIL!BU:BU), _xlpm.modelo, TRIM(SUBSTITUTE(R27,CHAR(160),"")), _xlpm.nomeMod, IFERROR(_xlfn.XLOOKUP("*"&_xlpm.modelo&"*", UTIL!D:D, UTIL!B:B, "", 2), IFERROR(_xlfn.XLOOKUP("*"&_xlpm.modelo&"*", UTIL!E:E, UTIL!B:B, "", 2), "")), _xlpm.tipoMod, IF(_xlpm.nomeMod="", "", IFERROR(LEFT(_xlpm.nomeMod, FIND(" ", _xlpm.nomeMod)-1), _xlpm.nomeMod)), _xlpm.dimMod, IFERROR(_xlfn.XLOOKUP("*"&_xlpm.modelo&"*", UTIL!D:D, UTIL!K:K, "", 2), IFERROR(_xlfn.XLOOKUP("*"&_xlpm.modelo&"*", UTIL!E:E, UTIL!K:K, "", 2), "")), _xlpm.tipotxt_antigo, IF(_xlpm.ehTrator, "TRATOR", IFERROR(_xlfn.XLOOKUP(_xlpm.chave, _xlpm.fonte, UTIL!BS:BS, "", 0), IFERROR(_xlfn.XLOOKUP("*"&_xlpm.chave&"*", _xlpm.fonte, UTIL!BS:BS, "", 2), "Não encontrado"))), _xlpm.dimtxt_antigo, IFERROR(_xlfn.XLOOKUP(_xlpm.chave, _xlpm.fonte, UTIL!CB:CB, "", 0), IFERROR(_xlfn.XLOOKUP("*"&_xlpm.chave&"*", _xlpm.fonte, UTIL!CB:CB, "", 2), "Não encontrado")), _xlpm.tipotxt, IF(_xlpm.tipoMod<>"", _xlpm.tipoMod, _xlpm.tipotxt_antigo), _xlpm.dimtxt, IF(_xlpm.dimMod<>"", _xlpm.dimMod, _xlpm.dimtxt_antigo), _xlpm.deTxt, IF(L27="CLIENTE", O27, IF(LEFT(L27,4)="http", L27, "MACPONTA AGRO DE "&L27)), _xlpm.paraBase, IF(M27="CLIENTE", P27, M27), _xlpm.paraTxt, IF(LEFT(_xlpm.paraBase,4)="http", _xlpm.paraBase, "MACPONTA AGRO DE "&_xlpm.paraBase), _xlpm.nfParte, IF(LEN(TRIM(I27))=0, "", " -NF "&TRIM(I27)), "- " & _xlpm.tipotxt & ": *" & G27 & "*" & CHAR(13)&CHAR(10) & "- " & _xlpm.dimtxt & CHAR(13)&CHAR(10) & "- *Cliente*: " & J27 & _xlpm.nfParte & CHAR(13)&CHAR(10) & "- *Obs:* " & Q27 & CHAR(13)&CHAR(10) & CHAR(10) & "- *De*: " & _xlpm.deTxt & CHAR(13)&CHAR(10) & "- *Para*: " & _xlpm.paraTxt & CHAR(13)&CHAR(10) & "- *Ida e volta*: +/- " & TEXT(((D27*1.5)/1440),"h:mm") & "h | " & D27 & "km" )} -> - COLHEITADEIRA: *1CQS550APS0160136*_x000D_ - A:3,80 x C:10,00 x L:3,70-4,20 x P:15.938kg_x000D_ - *Cliente*: DOUGLAS FONSECA -NF 107225 -NF 45971_x000D_ - *Obs:* N/A_x000D_ - *De*: MACPONTA AGRO DE GUARAPUAVA_x000D_ - *Para*: https://maps.app.goo.gl/xyQpe8BG44WqsG1v9_x000D_ - *Ida e volta*: +/- 12:30h | 500km
A28: CONCLUIDO (D) | B28: PROPRIO DAF | C28: 0.52083333 | D28: 500 | E28: =IFERROR((D28*7),"?") -> 3500 | F28: 0 | G28: 1CQRD30AVS0160245 | H28: 45972 | I28: 45971 | J28: DOUGLAS FONSECA -NF 107225 | K28: marcelo.ferreira | L28: GUARAPUAVA | M28: CLIENTE | N28: DE LOJA PARA DEMONSTRAÇÃO | O28: MPA | P28: https://maps.app.goo.gl/xyQpe8BG44WqsG1v9 | Q28: N/A | R28: =IF( OR( IFERROR(FIND("BM",G28),0)>0, IFERROR(FIND("PY",G28),0)>0 ), MID(TRIM(SUBSTITUTE(SUBSTITUTE(G28,CHAR(160),""),CHAR(9),"")),4,5), MID(TRIM(SUBSTITUTE(SUBSTITUTE(G28,CHAR(160),""),CHAR(9),"")),4,4) ) -> RD30 | S28: {=_xlfn.LET( _xlpm.ch, TRIM(SUBSTITUTE(G28,CHAR(160),"")), _xlpm.ehTrator, OR(IFERROR(FIND("BM",_xlpm.ch),0)>0, IFERROR(FIND("PY",_xlpm.ch),0)>0), _xlpm.chave, IF(_xlpm.ehTrator, MID(_xlpm.ch,4,5), MID(_xlpm.ch,4,4)), _xlpm.fonte, IF(LEN(_xlpm.chave)=5, UTIL!BV:BV, UTIL!BU:BU), _xlpm.modelo, TRIM(SUBSTITUTE(R28,CHAR(160),"")), _xlpm.nomeMod, IFERROR(_xlfn.XLOOKUP("*"&_xlpm.modelo&"*", UTIL!D:D, UTIL!B:B, "", 2), IFERROR(_xlfn.XLOOKUP("*"&_xlpm.modelo&"*", UTIL!E:E, UTIL!B:B, "", 2), "")), _xlpm.tipoMod, IF(_xlpm.nomeMod="", "", IFERROR(LEFT(_xlpm.nomeMod, FIND(" ", _xlpm.nomeMod)-1), _xlpm.nomeMod)), _xlpm.dimMod, IFERROR(_xlfn.XLOOKUP("*"&_xlpm.modelo&"*", UTIL!D:D, UTIL!K:K, "", 2), IFERROR(_xlfn.XLOOKUP("*"&_xlpm.modelo&"*", UTIL!E:E, UTIL!K:K, "", 2), "")), _xlpm.tipotxt_antigo, IF(_xlpm.ehTrator, "TRATOR", IFERROR(_xlfn.XLOOKUP(_xlpm.chave, _xlpm.fonte, UTIL!BS:BS, "", 0), IFERROR(_xlfn.XLOOKUP("*"&_xlpm.chave&"*", _xlpm.fonte, UTIL!BS:BS, "", 2), "Não encontrado"))), _xlpm.dimtxt_antigo, IFERROR(_xlfn.XLOOKUP(_xlpm.chave, _xlpm.fonte, UTIL!CB:CB, "", 0), IFERROR(_xlfn.XLOOKUP("*"&_xlpm.chave&"*", _xlpm.fonte, UTIL!CB:CB, "", 2), "Não encontrado")), _xlpm.tipotxt, IF(_xlpm.tipoMod<>"", _xlpm.tipoMod, _xlpm.tipotxt_antigo), _xlpm.dimtxt, IF(_xlpm.dimMod<>"", _xlpm.dimMod, _xlpm.dimtxt_antigo), _xlpm.deTxt, IF(L28="CLIENTE", O28, IF(LEFT(L28,4)="http", L28, "MACPONTA AGRO DE "&L28)), _xlpm.paraBase, IF(M28="CLIENTE", P28, M28), _xlpm.paraTxt, IF(LEFT(_xlpm.paraBase,4)="http", _xlpm.paraBase, "MACPONTA AGRO DE "&_xlpm.paraBase), _xlpm.nfParte, IF(LEN(TRIM(I28))=0, "", " -NF "&TRIM(I28)), "- " & _xlpm.tipotxt & ": *" & G28 & "*" & CHAR(13)&CHAR(10) & "- " & _xlpm.dimtxt & CHAR(13)&CHAR(10) & "- *Cliente*: " & J28 & _xlpm.nfParte & CHAR(13)&CHAR(10) & "- *Obs:* " & Q28 & CHAR(13)&CHAR(10) & CHAR(10) & "- *De*: " & _xlpm.deTxt & CHAR(13)&CHAR(10) & "- *Para*: " & _xlpm.paraTxt & CHAR(13)&CHAR(10) & "- *Ida e volta*: +/- " & TEXT(((D28*1.5)/1440),"h:mm") & "h | " & D28 & "km" )} -> - PLATAFORMA: *1CQRD30AVS0160245*_x000D_ - A:1,60 x C:9,14 x L:2,20-2,20 x P:4.200kg_x000D_ - *Cliente*: DOUGLAS FONSECA -NF 107225 -NF 45971_x000D_ - *Obs:* N/A_x000D_ - *De*: MACPONTA AGRO DE GUARAPUAVA_x000D_ - *Para*: https://maps.app.goo.gl/xyQpe8BG44WqsG1v9_x000D_ - *Ida e volta*: +/- 12:30h | 500km
A29: PROGRAMADO | B29: PROPRIO DAF | C29: 0.10694444 | D29: 103 | E29: =IFERROR((D29*7),"?") -> 721 | F29: 0 | G29: 1BM5080EVS6204375 | H29: 45974 | J29: CARLA BORKOSKI -NF278340 | K29: marcos.ribas | L29: PONTA GROSSA | M29: CLIENTE | N29: DE LOJA PARA CLIENTE | O29: MPA | P29: https://maps.app.goo.gl/pz4jP4cRzqhcm3mP6 | Q29: GERALDO - GABRIEL - AVISAR CLEBER PARA ACOMPANHAR | R29: =IF( OR( IFERROR(FIND("BM",G29),0)>0, IFERROR(FIND("PY",G29),0)>0 ), MID(TRIM(SUBSTITUTE(SUBSTITUTE(G29,CHAR(160),""),CHAR(9),"")),4,5), MID(TRIM(SUBSTITUTE(SUBSTITUTE(G29,CHAR(160),""),CHAR(9),"")),4,4) ) -> 5080E | S29: {=_xlfn.LET( _xlpm.ch, TRIM(SUBSTITUTE(G29,CHAR(160),"")), _xlpm.ehTrator, OR(IFERROR(FIND("BM",_xlpm.ch),0)>0, IFERROR(FIND("PY",_xlpm.ch),0)>0), _xlpm.chave, IF(_xlpm.ehTrator, MID(_xlpm.ch,4,5), MID(_xlpm.ch,4,4)), _xlpm.fonte, IF(LEN(_xlpm.chave)=5, UTIL!BV:BV, UTIL!BU:BU), _xlpm.modelo, TRIM(SUBSTITUTE(R29,CHAR(160),"")), _xlpm.nomeMod, IFERROR(_xlfn.XLOOKUP("*"&_xlpm.modelo&"*", UTIL!D:D, UTIL!B:B, "", 2), IFERROR(_xlfn.XLOOKUP("*"&_xlpm.modelo&"*", UTIL!E:E, UTIL!B:B, "", 2), "")), _xlpm.tipoMod, IF(_xlpm.nomeMod="", "", IFERROR(LEFT(_xlpm.nomeMod, FIND(" ", _xlpm.nomeMod)-1), _xlpm.nomeMod)), _xlpm.dimMod, IFERROR(_xlfn.XLOOKUP("*"&_xlpm.modelo&"*", UTIL!D:D, UTIL!K:K, "", 2), IFERROR(_xlfn.XLOOKUP("*"&_xlpm.modelo&"*", UTIL!E:E, UTIL!K:K, "", 2), "")), _xlpm.tipotxt_antigo, IF(_xlpm.ehTrator, "TRATOR", IFERROR(_xlfn.XLOOKUP(_xlpm.chave, _xlpm.fonte, UTIL!BS:BS, "", 0), IFERROR(_xlfn.XLOOKUP("*"&_xlpm.chave&"*", _xlpm.fonte, UTIL!BS:BS, "", 2), "Não encontrado"))), _xlpm.dimtxt_antigo, IFERROR(_xlfn.XLOOKUP(_xlpm.chave, _xlpm.fonte, UTIL!CB:CB, "", 0), IFERROR(_xlfn.XLOOKUP("*"&_xlpm.chave&"*", _xlpm.fonte, UTIL!CB:CB, "", 2), "Não encontrado")), _xlpm.tipotxt, IF(_xlpm.tipoMod<>"", _xlpm.tipoMod, _xlpm.tipotxt_antigo), _xlpm.dimtxt, IF(_xlpm.dimMod<>"", _xlpm.dimMod, _xlpm.dimtxt_antigo), _xlpm.deTxt, IF(L29="CLIENTE", O29, IF(LEFT(L29,4)="http", L29, "MACPONTA AGRO DE "&L29)), _xlpm.paraBase, IF(M29="CLIENTE", P29, M29), _xlpm.paraTxt, IF(LEFT(_xlpm.paraBase,4)="http", _xlpm.paraBase, "MACPONTA AGRO DE "&_xlpm.paraBase), _xlpm.nfParte, IF(LEN(TRIM(I29))=0, "", " -NF "&TRIM(I29)), "- " & _xlpm.tipotxt & ": *" & G29 & "*" & CHAR(13)&CHAR(10) & "- " & _xlpm.dimtxt & CHAR(13)&CHAR(10) & "- *Cliente*: " & J29 & _xlpm.nfParte & CHAR(13)&CHAR(10) & "- *Obs:* " & Q29 & CHAR(13)&CHAR(10) & CHAR(10) & "- *De*: " & _xlpm.deTxt & CHAR(13)&CHAR(10) & "- *Para*: " & _xlpm.paraTxt & CHAR(13)&CHAR(10) & "- *Ida e volta*: +/- " & TEXT(((D29*1.5)/1440),"h:mm") & "h | " & D29 & "km" )} -> - TRATOR: *1BM5080EVS6204375*_x000D_ - _x000D_ - *Cliente*: CARLA BORKOSKI -NF278340_x000D_ - *Obs:* GERALDO - GABRIEL - AVISAR CLEBER PARA ACOMPANHAR_x000D_ - *De*: MACPONTA AGRO DE PONTA GROSSA_x000D_ - *Para*: https://maps.app.goo.gl/pz4jP4cRzqhcm3mP6_x000D_ - *Ida e volta*: +/- 2:34h | 103km
A30: PROGRAMADO | B30: PROPRIO DAF | C30: 0.10694444 | D30: 103 | E30: =IFERROR((D30*7),"?") -> 721 | F30: 0 | G30: 1BM5080EVS6204327 | H30: 45974 | J30: MARIA BORKOSKI -NF278379 | K30: marcos.ribas | L30: PONTA GROSSA | M30: CLIENTE | N30: DE LOJA PARA CLIENTE | O30: MPA | P30: https://maps.app.goo.gl/pz4jP4cRzqhcm3mP6 | Q30: GERALDO - GABRIEL - AVISAR CLEBER PARA ACOMPANHAR | R30: =IF( OR( IFERROR(FIND("BM",G30),0)>0, IFERROR(FIND("PY",G30),0)>0 ), MID(TRIM(SUBSTITUTE(SUBSTITUTE(G30,CHAR(160),""),CHAR(9),"")),4,5), MID(TRIM(SUBSTITUTE(SUBSTITUTE(G30,CHAR(160),""),CHAR(9),"")),4,4) ) -> 5080E | S30: {=_xlfn.LET( _xlpm.ch, TRIM(SUBSTITUTE(G30,CHAR(160),"")), _xlpm.ehTrator, OR(IFERROR(FIND("BM",_xlpm.ch),0)>0, IFERROR(FIND("PY",_xlpm.ch),0)>0), _xlpm.chave, IF(_xlpm.ehTrator, MID(_xlpm.ch,4,5), MID(_xlpm.ch,4,4)), _xlpm.fonte, IF(LEN(_xlpm.chave)=5, UTIL!BV:BV, UTIL!BU:BU), _xlpm.modelo, TRIM(SUBSTITUTE(R30,CHAR(160),"")), _xlpm.nomeMod, IFERROR(_xlfn.XLOOKUP("*"&_xlpm.modelo&"*", UTIL!D:D, UTIL!B:B, "", 2), IFERROR(_xlfn.XLOOKUP("*"&_xlpm.modelo&"*", UTIL!E:E, UTIL!B:B, "", 2), "")), _xlpm.tipoMod, IF(_xlpm.nomeMod="", "", IFERROR(LEFT(_xlpm.nomeMod, FIND(" ", _xlpm.nomeMod)-1), _xlpm.nomeMod)), _xlpm.dimMod, IFERROR(_xlfn.XLOOKUP("*"&_xlpm.modelo&"*", UTIL!D:D, UTIL!K:K, "", 2), IFERROR(_xlfn.XLOOKUP("*"&_xlpm.modelo&"*", UTIL!E:E, UTIL!K:K, "", 2), "")), _xlpm.tipotxt_antigo, IF(_xlpm.ehTrator, "TRATOR", IFERROR(_xlfn.XLOOKUP(_xlpm.chave, _xlpm.fonte, UTIL!BS:BS, "", 0), IFERROR(_xlfn.XLOOKUP("*"&_xlpm.chave&"*", _xlpm.fonte, UTIL!BS:BS, "", 2), "Não encontrado"))), _xlpm.dimtxt_antigo, IFERROR(_xlfn.XLOOKUP(_xlpm.chave, _xlpm.fonte, UTIL!CB:CB, "", 0), IFERROR(_xlfn.XLOOKUP("*"&_xlpm.chave&"*", _xlpm.fonte, UTIL!CB:CB, "", 2), "Não encontrado")), _xlpm.tipotxt, IF(_xlpm.tipoMod<>"", _xlpm.tipoMod, _xlpm.tipotxt_antigo), _xlpm.dimtxt, IF(_xlpm.dimMod<>"", _xlpm.dimMod, _xlpm.dimtxt_antigo), _xlpm.deTxt, IF(L30="CLIENTE", O30, IF(LEFT(L30,4)="http", L30, "MACPONTA AGRO DE "&L30)), _xlpm.paraBase, IF(M30="CLIENTE", P30, M30), _xlpm.paraTxt, IF(LEFT(_xlpm.paraBase,4)="http", _xlpm.paraBase, "MACPONTA AGRO DE "&_xlpm.paraBase), _xlpm.nfParte, IF(LEN(TRIM(I30))=0, "", " -NF "&TRIM(I30)), "- " & _xlpm.tipotxt & ": *" & G30 & "*" & CHAR(13)&CHAR(10) & "- " & _xlpm.dimtxt & CHAR(13)&CHAR(10) & "- *Cliente*: " & J30 & _xlpm.nfParte & CHAR(13)&CHAR(10) & "- *Obs:* " & Q30 & CHAR(13)&CHAR(10) & CHAR(10) & "- *De*: " & _xlpm.deTxt & CHAR(13)&CHAR(10) & "- *Para*: " & _xlpm.paraTxt & CHAR(13)&CHAR(10) & "- *Ida e volta*: +/- " & TEXT(((D30*1.5)/1440),"h:mm") & "h | " & D30 & "km" )} -> - TRATOR: *1BM5080EVS6204327*_x000D_ - _x000D_ - *Cliente*: MARIA BORKOSKI -NF278379_x000D_ - *Obs:* GERALDO - GABRIEL - AVISAR CLEBER PARA ACOMPANHAR_x000D_ - *De*: MACPONTA AGRO DE PONTA GROSSA_x000D_ - *Para*: https://maps.app.goo.gl/pz4jP4cRzqhcm3mP6_x000D_ - *Ida e volta*: +/- 2:34h | 103km
A31: PROGRAMADO | B31: PROPRIO VW | C31: 0.075 | D31: 72 | E31: =IFERROR((D31*7),"?") -> 504 | F31: 0 | G31: 1BM5080ECN4109659 | H31: 45974 | J31: CLIENTE → MANUTENÇÃO | K31: daisy.kakol | L31: CLIENTE | M31: IRATI | N31: DE CLIENTE PARA LOJA | O31: https://maps.app.goo.gl/fhc785TjS54Vtjgc8 | P31: MPA | Q31: OFICINA | R31: =IF( OR( IFERROR(FIND("BM",G31),0)>0, IFERROR(FIND("PY",G31),0)>0 ), MID(TRIM(SUBSTITUTE(SUBSTITUTE(G31,CHAR(160),""),CHAR(9),"")),4,5), MID(TRIM(SUBSTITUTE(SUBSTITUTE(G31,CHAR(160),""),CHAR(9),"")),4,4) ) -> 5080E | S31: {=_xlfn.LET( _xlpm.ch, TRIM(SUBSTITUTE(G31,CHAR(160),"")), _xlpm.ehTrator, OR(IFERROR(FIND("BM",_xlpm.ch),0)>0, IFERROR(FIND("PY",_xlpm.ch),0)>0), _xlpm.chave, IF(_xlpm.ehTrator, MID(_xlpm.ch,4,5), MID(_xlpm.ch,4,4)), _xlpm.fonte, IF(LEN(_xlpm.chave)=5, UTIL!BV:BV, UTIL!BU:BU), _xlpm.modelo, TRIM(SUBSTITUTE(R31,CHAR(160),"")), _xlpm.nomeMod, IFERROR(_xlfn.XLOOKUP("*"&_xlpm.modelo&"*", UTIL!D:D, UTIL!B:B, "", 2), IFERROR(_xlfn.XLOOKUP("*"&_xlpm.modelo&"*", UTIL!E:E, UTIL!B:B, "", 2), "")), _xlpm.tipoMod, IF(_xlpm.nomeMod="", "", IFERROR(LEFT(_xlpm.nomeMod, FIND(" ", _xlpm.nomeMod)-1), _xlpm.nomeMod)), _xlpm.dimMod, IFERROR(_xlfn.XLOOKUP("*"&_xlpm.modelo&"*", UTIL!D:D, UTIL!K:K, "", 2), IFERROR(_xlfn.XLOOKUP("*"&_xlpm.modelo&"*", UTIL!E:E, UTIL!K:K, "", 2), "")), _xlpm.tipotxt_antigo, IF(_xlpm.ehTrator, "TRATOR", IFERROR(_xlfn.XLOOKUP(_xlpm.chave, _xlpm.fonte, UTIL!BS:BS, "", 0), IFERROR(_xlfn.XLOOKUP("*"&_xlpm.chave&"*", _xlpm.fonte, UTIL!BS:BS, "", 2), "Não encontrado"))), _xlpm.dimtxt_antigo, IFERROR(_xlfn.XLOOKUP(_xlpm.chave, _xlpm.fonte, UTIL!CB:CB, "", 0), IFERROR(_xlfn.XLOOKUP("*"&_xlpm.chave&"*", _xlpm.fonte, UTIL!CB:CB, "", 2), "Não encontrado")), _xlpm.tipotxt, IF(_xlpm.tipoMod<>"", _xlpm.tipoMod, _xlpm.tipotxt_antigo), _xlpm.dimtxt, IF(_xlpm.dimMod<>"", _xlpm.dimMod, _xlpm.dimtxt_antigo), _xlpm.deTxt, IF(L31="CLIENTE", O31, IF(LEFT(L31,4)="http", L31, "MACPONTA AGRO DE "&L31)), _xlpm.paraBase, IF(M31="CLIENTE", P31, M31), _xlpm.paraTxt, IF(LEFT(_xlpm.paraBase,4)="http", _xlpm.paraBase, "MACPONTA AGRO DE "&_xlpm.paraBase), _xlpm.nfParte, IF(LEN(TRIM(I31))=0, "", " -NF "&TRIM(I31)), "- " & _xlpm.tipotxt & ": *" & G31 & "*" & CHAR(13)&CHAR(10) & "- " & _xlpm.dimtxt & CHAR(13)&CHAR(10) & "- *Cliente*: " & J31 & _xlpm.nfParte & CHAR(13)&CHAR(10) & "- *Obs:* " & Q31 & CHAR(13)&CHAR(10) & CHAR(10) & "- *De*: " & _xlpm.deTxt & CHAR(13)&CHAR(10) & "- *Para*: " & _xlpm.paraTxt & CHAR(13)&CHAR(10) & "- *Ida e volta*: +/- " & TEXT(((D31*1.5)/1440),"h:mm") & "h | " & D31 & "km" )} -> - TRATOR: *1BM5080ECN4109659*_x000D_ - _x000D_ - *Cliente*: CLIENTE → MANUTENÇÃO_x000D_ - *Obs:* OFICINA_x000D_ - *De*: https://maps.app.goo.gl/fhc785TjS54Vtjgc8_x000D_ - *Para*: MACPONTA AGRO DE IRATI_x000D_ - *Ida e volta*: +/- 1:48h | 72km
A32: PROGRAMADO | B32: PROPRIO VW | C32: 0.11944444 | D32: 115 | E32: =IFERROR((D32*7),"?") -> 805 | F32: 0 | G32: 1BM5080EEP4112594 | H32: 45974 | J32: MANUTENÇÃO → CLIENTE | K32: daisy.kakol | L32: IRATI | M32: CLIENTE | N32: DE LOJA PARA CLIENTE | O32: MPA | P32: https://maps.app.goo.gl/u6RQ92AcKr5YZVN5A | Q32: JOSE VALCIR | R32: =IF( OR( IFERROR(FIND("BM",G32),0)>0, IFERROR(FIND("PY",G32),0)>0 ), MID(TRIM(SUBSTITUTE(SUBSTITUTE(G32,CHAR(160),""),CHAR(9),"")),4,5), MID(TRIM(SUBSTITUTE(SUBSTITUTE(G32,CHAR(160),""),CHAR(9),"")),4,4) ) -> 5080E | S32: {=_xlfn.LET( _xlpm.ch, TRIM(SUBSTITUTE(G32,CHAR(160),"")), _xlpm.ehTrator, OR(IFERROR(FIND("BM",_xlpm.ch),0)>0, IFERROR(FIND("PY",_xlpm.ch),0)>0), _xlpm.chave, IF(_xlpm.ehTrator, MID(_xlpm.ch,4,5), MID(_xlpm.ch,4,4)), _xlpm.fonte, IF(LEN(_xlpm.chave)=5, UTIL!BV:BV, UTIL!BU:BU), _xlpm.modelo, TRIM(SUBSTITUTE(R32,CHAR(160),"")), _xlpm.nomeMod, IFERROR(_xlfn.XLOOKUP("*"&_xlpm.modelo&"*", UTIL!D:D, UTIL!B:B, "", 2), IFERROR(_xlfn.XLOOKUP("*"&_xlpm.modelo&"*", UTIL!E:E, UTIL!B:B, "", 2), "")), _xlpm.tipoMod, IF(_xlpm.nomeMod="", "", IFERROR(LEFT(_xlpm.nomeMod, FIND(" ", _xlpm.nomeMod)-1), _xlpm.nomeMod)), _xlpm.dimMod, IFERROR(_xlfn.XLOOKUP("*"&_xlpm.modelo&"*", UTIL!D:D, UTIL!K:K, "", 2), IFERROR(_xlfn.XLOOKUP("*"&_xlpm.modelo&"*", UTIL!E:E, UTIL!K:K, "", 2), "")), _xlpm.tipotxt_antigo, IF(_xlpm.ehTrator, "TRATOR", IFERROR(_xlfn.XLOOKUP(_xlpm.chave, _xlpm.fonte, UTIL!BS:BS, "", 0), IFERROR(_xlfn.XLOOKUP("*"&_xlpm.chave&"*", _xlpm.fonte, UTIL!BS:BS, "", 2), "Não encontrado"))), _xlpm.dimtxt_antigo, IFERROR(_xlfn.XLOOKUP(_xlpm.chave, _xlpm.fonte, UTIL!CB:CB, "", 0), IFERROR(_xlfn.XLOOKUP("*"&_xlpm.chave&"*", _xlpm.fonte, UTIL!CB:CB, "", 2), "Não encontrado")), _xlpm.tipotxt, IF(_xlpm.tipoMod<>"", _xlpm.tipoMod, _xlpm.tipotxt_antigo), _xlpm.dimtxt, IF(_xlpm.dimMod<>"", _xlpm.dimMod, _xlpm.dimtxt_antigo), _xlpm.deTxt, IF(L32="CLIENTE", O32, IF(LEFT(L32,4)="http", L32, "MACPONTA AGRO DE "&L32)), _xlpm.paraBase, IF(M32="CLIENTE", P32, M32), _xlpm.paraTxt, IF(LEFT(_xlpm.paraBase,4)="http", _xlpm.paraBase, "MACPONTA AGRO DE "&_xlpm.paraBase), _xlpm.nfParte, IF(LEN(TRIM(I32))=0, "", " -NF "&TRIM(I32)), "- " & _xlpm.tipotxt & ": *" & G32 & "*" & CHAR(13)&CHAR(10) & "- " & _xlpm.dimtxt & CHAR(13)&CHAR(10) & "- *Cliente*: " & J32 & _xlpm.nfParte & CHAR(13)&CHAR(10) & "- *Obs:* " & Q32 & CHAR(13)&CHAR(10) & CHAR(10) & "- *De*: " & _xlpm.deTxt & CHAR(13)&CHAR(10) & "- *Para*: " & _xlpm.paraTxt & CHAR(13)&CHAR(10) & "- *Ida e volta*: +/- " & TEXT(((D32*1.5)/1440),"h:mm") & "h | " & D32 & "km" )} -> - TRATOR: *1BM5080EEP4112594*_x000D_ - _x000D_ - *Cliente*: MANUTENÇÃO → CLIENTE_x000D_ - *Obs:* JOSE VALCIR_x000D_ - *De*: MACPONTA AGRO DE IRATI_x000D_ - *Para*: https://maps.app.goo.gl/u6RQ92AcKr5YZVN5A_x000D_ - *Ida e volta*: +/- 2:52h | 115km
A33: PROGRAMADO | B33: TERCEIRO COLOMBO | C33: 0.76319444 | D33: 733 | E33: =IFERROR((D33*7),"?") -> 5131 | F33: 9600 | G33: 1NW4030MES0250870 | H33: 45975 | J33: VIKTOR LEH -NF107863 - AET ESP+ESCOLTA | K33: euclides.junior | L33: GUARAPUAVA | M33: CLIENTE | N33: DE LOJA PARA CLIENTE | O33: MPA | P33: https://maps.app.goo.gl/CR8ypB1Pd9ZCuWzE6 | Q33: Viktor | R33: =IF( OR( IFERROR(FIND("BM",G33),0)>0, IFERROR(FIND("PY",G33),0)>0 ), MID(TRIM(SUBSTITUTE(SUBSTITUTE(G33,CHAR(160),""),CHAR(9),"")),4,5), MID(TRIM(SUBSTITUTE(SUBSTITUTE(G33,CHAR(160),""),CHAR(9),"")),4,4) ) -> 4030 | S33: {=_xlfn.LET( _xlpm.ch, TRIM(SUBSTITUTE(G33,CHAR(160),"")), _xlpm.ehTrator, OR(IFERROR(FIND("BM",_xlpm.ch),0)>0, IFERROR(FIND("PY",_xlpm.ch),0)>0), _xlpm.chave, IF(_xlpm.ehTrator, MID(_xlpm.ch,4,5), MID(_xlpm.ch,4,4)), _xlpm.fonte, IF(LEN(_xlpm.chave)=5, UTIL!BV:BV, UTIL!BU:BU), _xlpm.modelo, TRIM(SUBSTITUTE(R33,CHAR(160),"")), _xlpm.nomeMod, IFERROR(_xlfn.XLOOKUP("*"&_xlpm.modelo&"*", UTIL!D:D, UTIL!B:B, "", 2), IFERROR(_xlfn.XLOOKUP("*"&_xlpm.modelo&"*", UTIL!E:E, UTIL!B:B, "", 2), "")), _xlpm.tipoMod, IF(_xlpm.nomeMod="", "", IFERROR(LEFT(_xlpm.nomeMod, FIND(" ", _xlpm.nomeMod)-1), _xlpm.nomeMod)), _xlpm.dimMod, IFERROR(_xlfn.XLOOKUP("*"&_xlpm.modelo&"*", UTIL!D:D, UTIL!K:K, "", 2), IFERROR(_xlfn.XLOOKUP("*"&_xlpm.modelo&"*", UTIL!E:E, UTIL!K:K, "", 2), "")), _xlpm.tipotxt_antigo, IF(_xlpm.ehTrator, "TRATOR", IFERROR(_xlfn.XLOOKUP(_xlpm.chave, _xlpm.fonte, UTIL!BS:BS, "", 0), IFERROR(_xlfn.XLOOKUP("*"&_xlpm.chave&"*", _xlpm.fonte, UTIL!BS:BS, "", 2), "Não encontrado"))), _xlpm.dimtxt_antigo, IFERROR(_xlfn.XLOOKUP(_xlpm.chave, _xlpm.fonte, UTIL!CB:CB, "", 0), IFERROR(_xlfn.XLOOKUP("*"&_xlpm.chave&"*", _xlpm.fonte, UTIL!CB:CB, "", 2), "Não encontrado")), _xlpm.tipotxt, IF(_xlpm.tipoMod<>"", _xlpm.tipoMod, _xlpm.tipotxt_antigo), _xlpm.dimtxt, IF(_xlpm.dimMod<>"", _xlpm.dimMod, _xlpm.dimtxt_antigo), _xlpm.deTxt, IF(L33="CLIENTE", O33, IF(LEFT(L33,4)="http", L33, "MACPONTA AGRO DE "&L33)), _xlpm.paraBase, IF(M33="CLIENTE", P33, M33), _xlpm.paraTxt, IF(LEFT(_xlpm.paraBase,4)="http", _xlpm.paraBase, "MACPONTA AGRO DE "&_xlpm.paraBase), _xlpm.nfParte, IF(LEN(TRIM(I33))=0, "", " -NF "&TRIM(I33)), "- " & _xlpm.tipotxt & ": *" & G33 & "*" & CHAR(13)&CHAR(10) & "- " & _xlpm.dimtxt & CHAR(13)&CHAR(10) & "- *Cliente*: " & J33 & _xlpm.nfParte & CHAR(13)&CHAR(10) & "- *Obs:* " & Q33 & CHAR(13)&CHAR(10) & CHAR(10) & "- *De*: " & _xlpm.deTxt & CHAR(13)&CHAR(10) & "- *Para*: " & _xlpm.paraTxt & CHAR(13)&CHAR(10) & "- *Ida e volta*: +/- " & TEXT(((D33*1.5)/1440),"h:mm") & "h | " & D33 & "km" )} -> - PULVERIZADOR: *1NW4030MES0250870*_x000D_ - A:3,35 x C:7,50 x L:3,12-3,94 x P:10.000kg_x000D_ - *Cliente*: VIKTOR LEH -NF107863 - AET ESP+ESCOLTA_x000D_ - *Obs:* Viktor _x000D_ - *De*: MACPONTA AGRO DE GUARAPUAVA_x000D_ - *Para*: https://maps.app.goo.gl/CR8ypB1Pd9ZCuWzE6_x000D_ - *Ida e volta*: +/- 18:19h | 733km
A34: PROGRAMADO (D) | B34: PROPRIO DAF | C34: 0.15625 | D34: 150 | E34: =IFERROR((D34*7),"?") -> 1050 | F34: 0 | G34: 1CQS550AER0155105 | H34: 45978 | J34: MARCELO RIBEIRO NARDI -NF278794 | K34: marcos.ribas | L34: PONTA GROSSA | M34: CLIENTE | N34: DE LOJA PARA CLIENTE | O34: MPA | P34: https://maps.app.goo.gl/2DJawZBMR4yqycss9 | Q34: DANILO - MARCELO | R34: =IF( OR( IFERROR(FIND("BM",G34),0)>0, IFERROR(FIND("PY",G34),0)>0 ), MID(TRIM(SUBSTITUTE(SUBSTITUTE(G34,CHAR(160),""),CHAR(9),"")),4,5), MID(TRIM(SUBSTITUTE(SUBSTITUTE(G34,CHAR(160),""),CHAR(9),"")),4,4) ) -> S550 | S34: {=_xlfn.LET( _xlpm.ch, TRIM(SUBSTITUTE(G34,CHAR(160),"")), _xlpm.ehTrator, OR(IFERROR(FIND("BM",_xlpm.ch),0)>0, IFERROR(FIND("PY",_xlpm.ch),0)>0), _xlpm.chave, IF(_xlpm.ehTrator, MID(_xlpm.ch,4,5), MID(_xlpm.ch,4,4)), _xlpm.fonte, IF(LEN(_xlpm.chave)=5, UTIL!BV:BV, UTIL!BU:BU), _xlpm.modelo, TRIM(SUBSTITUTE(R34,CHAR(160),"")), _xlpm.nomeMod, IFERROR(_xlfn.XLOOKUP("*"&_xlpm.modelo&"*", UTIL!D:D, UTIL!B:B, "", 2), IFERROR(_xlfn.XLOOKUP("*"&_xlpm.modelo&"*", UTIL!E:E, UTIL!B:B, "", 2), "")), _xlpm.tipoMod, IF(_xlpm.nomeMod="", "", IFERROR(LEFT(_xlpm.nomeMod, FIND(" ", _xlpm.nomeMod)-1), _xlpm.nomeMod)), _xlpm.dimMod, IFERROR(_xlfn.XLOOKUP("*"&_xlpm.modelo&"*", UTIL!D:D, UTIL!K:K, "", 2), IFERROR(_xlfn.XLOOKUP("*"&_xlpm.modelo&"*", UTIL!E:E, UTIL!K:K, "", 2), "")), _xlpm.tipotxt_antigo, IF(_xlpm.ehTrator, "TRATOR", IFERROR(_xlfn.XLOOKUP(_xlpm.chave, _xlpm.fonte, UTIL!BS:BS, "", 0), IFERROR(_xlfn.XLOOKUP("*"&_xlpm.chave&"*", _xlpm.fonte, UTIL!BS:BS, "", 2), "Não encontrado"))), _xlpm.dimtxt_antigo, IFERROR(_xlfn.XLOOKUP(_xlpm.chave, _xlpm.fonte, UTIL!CB:CB, "", 0), IFERROR(_xlfn.XLOOKUP("*"&_xlpm.chave&"*", _xlpm.fonte, UTIL!CB:CB, "", 2), "Não encontrado")), _xlpm.tipotxt, IF(_xlpm.tipoMod<>"", _xlpm.tipoMod, _xlpm.tipotxt_antigo), _xlpm.dimtxt, IF(_xlpm.dimMod<>"", _xlpm.dimMod, _xlpm.dimtxt_antigo), _xlpm.deTxt, IF(L34="CLIENTE", O34, IF(LEFT(L34,4)="http", L34, "MACPONTA AGRO DE "&L34)), _xlpm.paraBase, IF(M34="CLIENTE", P34, M34), _xlpm.paraTxt, IF(LEFT(_xlpm.paraBase,4)="http", _xlpm.paraBase, "MACPONTA AGRO DE "&_xlpm.paraBase), _xlpm.nfParte, IF(LEN(TRIM(I34))=0, "", " -NF "&TRIM(I34)), "- " & _xlpm.tipotxt & ": *" & G34 & "*" & CHAR(13)&CHAR(10) & "- " & _xlpm.dimtxt & CHAR(13)&CHAR(10) & "- *Cliente*: " & J34 & _xlpm.nfParte & CHAR(13)&CHAR(10) & "- *Obs:* " & Q34 & CHAR(13)&CHAR(10) & CHAR(10) & "- *De*: " & _xlpm.deTxt & CHAR(13)&CHAR(10) & "- *Para*: " & _xlpm.paraTxt & CHAR(13)&CHAR(10) & "- *Ida e volta*: +/- " & TEXT(((D34*1.5)/1440),"h:mm") & "h | " & D34 & "km" )} -> - COLHEITADEIRA: *1CQS550AER0155105*_x000D_ - A:3,80 x C:10,00 x L:3,70-4,20 x P:15.938kg_x000D_ - *Cliente*: MARCELO RIBEIRO NARDI -NF278794_x000D_ - *Obs:* DANILO - MARCELO _x000D_ - *De*: MACPONTA AGRO DE PONTA GROSSA_x000D_ - *Para*: https://maps.app.goo.gl/2DJawZBMR4yqycss9_x000D_ - *Ida e volta*: +/- 3:45h | 150km
A35: PROGRAMADO (D) | B35: PROPRIO DAF | C35: 0.15625 | D35: 150 | E35: =IFERROR((D35*7),"?") -> 1050 | F35: 0 | G35: 1CQ0630AHR0155127 | H35: 45978 | J35: MARCELO RIBEIRO NARDI -NF278794 | K35: marcos.ribas | L35: PONTA GROSSA | M35: CLIENTE | N35: DE LOJA PARA CLIENTE | O35: MPA | P35: https://maps.app.goo.gl/2DJawZBMR4yqycss9 | Q35: DANILO - MARCELO | R35: =IF( OR( IFERROR(FIND("BM",G35),0)>0, IFERROR(FIND("PY",G35),0)>0 ), MID(TRIM(SUBSTITUTE(SUBSTITUTE(G35,CHAR(160),""),CHAR(9),"")),4,5), MID(TRIM(SUBSTITUTE(SUBSTITUTE(G35,CHAR(160),""),CHAR(9),"")),4,4) ) -> 0630 | S35: {=_xlfn.LET( _xlpm.ch, TRIM(SUBSTITUTE(G35,CHAR(160),"")), _xlpm.ehTrator, OR(IFERROR(FIND("BM",_xlpm.ch),0)>0, IFERROR(FIND("PY",_xlpm.ch),0)>0), _xlpm.chave, IF(_xlpm.ehTrator, MID(_xlpm.ch,4,5), MID(_xlpm.ch,4,4)), _xlpm.fonte, IF(LEN(_xlpm.chave)=5, UTIL!BV:BV, UTIL!BU:BU), _xlpm.modelo, TRIM(SUBSTITUTE(R35,CHAR(160),"")), _xlpm.nomeMod, IFERROR(_xlfn.XLOOKUP("*"&_xlpm.modelo&"*", UTIL!D:D, UTIL!B:B, "", 2), IFERROR(_xlfn.XLOOKUP("*"&_xlpm.modelo&"*", UTIL!E:E, UTIL!B:B, "", 2), "")), _xlpm.tipoMod, IF(_xlpm.nomeMod="", "", IFERROR(LEFT(_xlpm.nomeMod, FIND(" ", _xlpm.nomeMod)-1), _xlpm.nomeMod)), _xlpm.dimMod, IFERROR(_xlfn.XLOOKUP("*"&_xlpm.modelo&"*", UTIL!D:D, UTIL!K:K, "", 2), IFERROR(_xlfn.XLOOKUP("*"&_xlpm.modelo&"*", UTIL!E:E, UTIL!K:K, "", 2), "")), _xlpm.tipotxt_antigo, IF(_xlpm.ehTrator, "TRATOR", IFERROR(_xlfn.XLOOKUP(_xlpm.chave, _xlpm.fonte, UTIL!BS:BS, "", 0), IFERROR(_xlfn.XLOOKUP("*"&_xlpm.chave&"*", _xlpm.fonte, UTIL!BS:BS, "", 2), "Não encontrado"))), _xlpm.dimtxt_antigo, IFERROR(_xlfn.XLOOKUP(_xlpm.chave, _xlpm.fonte, UTIL!CB:CB, "", 0), IFERROR(_xlfn.XLOOKUP("*"&_xlpm.chave&"*", _xlpm.fonte, UTIL!CB:CB, "", 2), "Não encontrado")), _xlpm.tipotxt, IF(_xlpm.tipoMod<>"", _xlpm.tipoMod, _xlpm.tipotxt_antigo), _xlpm.dimtxt, IF(_xlpm.dimMod<>"", _xlpm.dimMod, _xlpm.dimtxt_antigo), _xlpm.deTxt, IF(L35="CLIENTE", O35, IF(LEFT(L35,4)="http", L35, "MACPONTA AGRO DE "&L35)), _xlpm.paraBase, IF(M35="CLIENTE", P35, M35), _xlpm.paraTxt, IF(LEFT(_xlpm.paraBase,4)="http", _xlpm.paraBase, "MACPONTA AGRO DE "&_xlpm.paraBase), _xlpm.nfParte, IF(LEN(TRIM(I35))=0, "", " -NF "&TRIM(I35)), "- " & _xlpm.tipotxt & ": *" & G35 & "*" & CHAR(13)&CHAR(10) & "- " & _xlpm.dimtxt & CHAR(13)&CHAR(10) & "- *Cliente*: " & J35 & _xlpm.nfParte & CHAR(13)&CHAR(10) & "- *Obs:* " & Q35 & CHAR(13)&CHAR(10) & CHAR(10) & "- *De*: " & _xlpm.deTxt & CHAR(13)&CHAR(10) & "- *Para*: " & _xlpm.paraTxt & CHAR(13)&CHAR(10) & "- *Ida e volta*: +/- " & TEXT(((D35*1.5)/1440),"h:mm") & "h | " & D35 & "km" )} -> - PLATAFORMA: *1CQ0630AHR0155127*_x000D_ - A:1,60 x C:9,14 x L:1,80-1,80 x P:2.871kg_x000D_ - *Cliente*: MARCELO RIBEIRO NARDI -NF278794_x000D_ - *Obs:* DANILO - MARCELO _x000D_ - *De*: MACPONTA AGRO DE PONTA GROSSA_x000D_ - *Para*: https://maps.app.goo.gl/2DJawZBMR4yqycss9_x000D_ - *Ida e volta*: +/- 3:45h | 150km
A36: SUSPENSO | B36: PROPRIO DAF | C36: 0.14583333 | D36: 140 | E36: =IFERROR((D36*7),"?") -> 980 | F36: 0 | G36: 1CQS440AES0155172 | H36: 45978 | J36: MARCELO RIBEIRO DE NARDI -NF | K36: marcos.ribas | L36: PONTA GROSSA | M36: CLIENTE | N36: DE LOJA PARA CLIENTE | O36: MPA | P36: https://maps.app.goo.gl/a7As7SRaDnZSRB6c6 | Q36: DANILO - AVISAR ROITEMAN PARA ACOMPANHAR | R36: =IF( OR( IFERROR(FIND("BM",G36),0)>0, IFERROR(FIND("PY",G36),0)>0 ), MID(TRIM(SUBSTITUTE(SUBSTITUTE(G36,CHAR(160),""),CHAR(9),"")),4,5), MID(TRIM(SUBSTITUTE(SUBSTITUTE(G36,CHAR(160),""),CHAR(9),"")),4,4) ) -> S440 | S36: {=_xlfn.LET( _xlpm.ch, TRIM(SUBSTITUTE(G36,CHAR(160),"")), _xlpm.ehTrator, OR(IFERROR(FIND("BM",_xlpm.ch),0)>0, IFERROR(FIND("PY",_xlpm.ch),0)>0), _xlpm.chave, IF(_xlpm.ehTrator, MID(_xlpm.ch,4,5), MID(_xlpm.ch,4,4)), _xlpm.fonte, IF(LEN(_xlpm.chave)=5, UTIL!BV:BV, UTIL!BU:BU), _xlpm.modelo, TRIM(SUBSTITUTE(R36,CHAR(160),"")), _xlpm.nomeMod, IFERROR(_xlfn.XLOOKUP("*"&_xlpm.modelo&"*", UTIL!D:D, UTIL!B:B, "", 2), IFERROR(_xlfn.XLOOKUP("*"&_xlpm.modelo&"*", UTIL!E:E, UTIL!B:B, "", 2), "")), _xlpm.tipoMod, IF(_xlpm.nomeMod="", "", IFERROR(LEFT(_xlpm.nomeMod, FIND(" ", _xlpm.nomeMod)-1), _xlpm.nomeMod)), _xlpm.dimMod, IFERROR(_xlfn.XLOOKUP("*"&_xlpm.modelo&"*", UTIL!D:D, UTIL!K:K, "", 2), IFERROR(_xlfn.XLOOKUP("*"&_xlpm.modelo&"*", UTIL!E:E, UTIL!K:K, "", 2), "")), _xlpm.tipotxt_antigo, IF(_xlpm.ehTrator, "TRATOR", IFERROR(_xlfn.XLOOKUP(_xlpm.chave, _xlpm.fonte, UTIL!BS:BS, "", 0), IFERROR(_xlfn.XLOOKUP("*"&_xlpm.chave&"*", _xlpm.fonte, UTIL!BS:BS, "", 2), "Não encontrado"))), _xlpm.dimtxt_antigo, IFERROR(_xlfn.XLOOKUP(_xlpm.chave, _xlpm.fonte, UTIL!CB:CB, "", 0), IFERROR(_xlfn.XLOOKUP("*"&_xlpm.chave&"*", _xlpm.fonte, UTIL!CB:CB, "", 2), "Não encontrado")), _xlpm.tipotxt, IF(_xlpm.tipoMod<>"", _xlpm.tipoMod, _xlpm.tipotxt_antigo), _xlpm.dimtxt, IF(_xlpm.dimMod<>"", _xlpm.dimMod, _xlpm.dimtxt_antigo), _xlpm.deTxt, IF(L36="CLIENTE", O36, IF(LEFT(L36,4)="http", L36, "MACPONTA AGRO DE "&L36)), _xlpm.paraBase, IF(M36="CLIENTE", P36, M36), _xlpm.paraTxt, IF(LEFT(_xlpm.paraBase,4)="http", _xlpm.paraBase, "MACPONTA AGRO DE "&_xlpm.paraBase), _xlpm.nfParte, IF(LEN(TRIM(I36))=0, "", " -NF "&TRIM(I36)), "- " & _xlpm.tipotxt & ": *" & G36 & "*" & CHAR(13)&CHAR(10) & "- " & _xlpm.dimtxt & CHAR(13)&CHAR(10) & "- *Cliente*: " & J36 & _xlpm.nfParte & CHAR(13)&CHAR(10) & "- *Obs:* " & Q36 & CHAR(13)&CHAR(10) & CHAR(10) & "- *De*: " & _xlpm.deTxt & CHAR(13)&CHAR(10) & "- *Para*: " & _xlpm.paraTxt & CHAR(13)&CHAR(10) & "- *Ida e volta*: +/- " & TEXT(((D36*1.5)/1440),"h:mm") & "h | " & D36 & "km" )} -> - COLHEITADEIRA: *1CQS440AES0155172*_x000D_ - A:4,10 x C:7,70 x L:3,40-4,10 x P:11.800kg_x000D_ - *Cliente*: MARCELO RIBEIRO DE NARDI -NF_x000D_ - *Obs:* DANILO - AVISAR ROITEMAN PARA ACOMPANHAR_x000D_ - *De*: MACPONTA AGRO DE PONTA GROSSA_x000D_ - *Para*: https://maps.app.goo.gl/a7As7SRaDnZSRB6c6_x000D_ - *Ida e volta*: +/- 3:30h | 140km
A37: SUSPENSO | B37: PROPRIO DAF | C37: 0.14583333 | D37: 140 | E37: =IFERROR((D37*7),"?") -> 980 | F37: 0 | G37: 1CQFA25AES0160153 | H37: 45978 | J37: MARCELO RIBEIRO DE NARDI -NF | K37: marcos.ribas | L37: PONTA GROSSA | M37: CLIENTE | N37: DE LOJA PARA CLIENTE | O37: MPA | P37: https://maps.app.goo.gl/a7As7SRaDnZSRB6c6 | Q37: DANILO - AVISAR ROITEMAN PARA ACOMPANHAR | R37: =IF( OR( IFERROR(FIND("BM",G37),0)>0, IFERROR(FIND("PY",G37),0)>0 ), MID(TRIM(SUBSTITUTE(SUBSTITUTE(G37,CHAR(160),""),CHAR(9),"")),4,5), MID(TRIM(SUBSTITUTE(SUBSTITUTE(G37,CHAR(160),""),CHAR(9),"")),4,4) ) -> FA25 | S37: {=_xlfn.LET( _xlpm.ch, TRIM(SUBSTITUTE(G37,CHAR(160),"")), _xlpm.ehTrator, OR(IFERROR(FIND("BM",_xlpm.ch),0)>0, IFERROR(FIND("PY",_xlpm.ch),0)>0), _xlpm.chave, IF(_xlpm.ehTrator, MID(_xlpm.ch,4,5), MID(_xlpm.ch,4,4)), _xlpm.fonte, IF(LEN(_xlpm.chave)=5, UTIL!BV:BV, UTIL!BU:BU), _xlpm.modelo, TRIM(SUBSTITUTE(R37,CHAR(160),"")), _xlpm.nomeMod, IFERROR(_xlfn.XLOOKUP("*"&_xlpm.modelo&"*", UTIL!D:D, UTIL!B:B, "", 2), IFERROR(_xlfn.XLOOKUP("*"&_xlpm.modelo&"*", UTIL!E:E, UTIL!B:B, "", 2), "")), _xlpm.tipoMod, IF(_xlpm.nomeMod="", "", IFERROR(LEFT(_xlpm.nomeMod, FIND(" ", _xlpm.nomeMod)-1), _xlpm.nomeMod)), _xlpm.dimMod, IFERROR(_xlfn.XLOOKUP("*"&_xlpm.modelo&"*", UTIL!D:D, UTIL!K:K, "", 2), IFERROR(_xlfn.XLOOKUP("*"&_xlpm.modelo&"*", UTIL!E:E, UTIL!K:K, "", 2), "")), _xlpm.tipotxt_antigo, IF(_xlpm.ehTrator, "TRATOR", IFERROR(_xlfn.XLOOKUP(_xlpm.chave, _xlpm.fonte, UTIL!BS:BS, "", 0), IFERROR(_xlfn.XLOOKUP("*"&_xlpm.chave&"*", _xlpm.fonte, UTIL!BS:BS, "", 2), "Não encontrado"))), _xlpm.dimtxt_antigo, IFERROR(_xlfn.XLOOKUP(_xlpm.chave, _xlpm.fonte, UTIL!CB:CB, "", 0), IFERROR(_xlfn.XLOOKUP("*"&_xlpm.chave&"*", _xlpm.fonte, UTIL!CB:CB, "", 2), "Não encontrado")), _xlpm.tipotxt, IF(_xlpm.tipoMod<>"", _xlpm.tipoMod, _xlpm.tipotxt_antigo), _xlpm.dimtxt, IF(_xlpm.dimMod<>"", _xlpm.dimMod, _xlpm.dimtxt_antigo), _xlpm.deTxt, IF(L37="CLIENTE", O37, IF(LEFT(L37,4)="http", L37, "MACPONTA AGRO DE "&L37)), _xlpm.paraBase, IF(M37="CLIENTE", P37, M37), _xlpm.paraTxt, IF(LEFT(_xlpm.paraBase,4)="http", _xlpm.paraBase, "MACPONTA AGRO DE "&_xlpm.paraBase), _xlpm.nfParte, IF(LEN(TRIM(I37))=0, "", " -NF "&TRIM(I37)), "- " & _xlpm.tipotxt & ": *" & G37 & "*" & CHAR(13)&CHAR(10) & "- " & _xlpm.dimtxt & CHAR(13)&CHAR(10) & "- *Cliente*: " & J37 & _xlpm.nfParte & CHAR(13)&CHAR(10) & "- *Obs:* " & Q37 & CHAR(13)&CHAR(10) & CHAR(10) & "- *De*: " & _xlpm.deTxt & CHAR(13)&CHAR(10) & "- *Para*: " & _xlpm.paraTxt & CHAR(13)&CHAR(10) & "- *Ida e volta*: +/- " & TEXT(((D37*1.5)/1440),"h:mm") & "h | " & D37 & "km" )} -> - PLATAFORMA: *1CQFA25AES0160153*_x000D_ - A:1,60 x C:7,60 x L:1,80-1,80 x P:2.100kg_x000D_ - *Cliente*: MARCELO RIBEIRO DE NARDI -NF_x000D_ - *Obs:* DANILO - AVISAR ROITEMAN PARA ACOMPANHAR_x000D_ - *De*: MACPONTA AGRO DE PONTA GROSSA_x000D_ - *Para*: https://maps.app.goo.gl/a7As7SRaDnZSRB6c6_x000D_ - *Ida e volta*: +/- 3:30h | 140km
A38: PROGRAMADO (D) | B38: PROPRIO DAF | C38: 0.058333333 | D38: 56 | E38: =IFERROR((D38*7),"?") -> 392 | F38: 0 | G38: 1BM7230CKS3002086 | H38: 45980 | J38: DEMO GOLF CLUBE -NF ? 16h | K38: carolina.quadros | L38: PONTA GROSSA | M38: CLIENTE | N38: DE LOJA PARA DEMONSTRAÇÃO | O38: MPA | P38: https://maps.app.goo.gl/nPrR72QZAjPCStGf7 | Q38: Silvana +55 42 9955-7892 (Golf Clube) | R38: =IF( OR( IFERROR(FIND("BM",G38),0)>0, IFERROR(FIND("PY",G38),0)>0 ), MID(TRIM(SUBSTITUTE(SUBSTITUTE(G38,CHAR(160),""),CHAR(9),"")),4,5), MID(TRIM(SUBSTITUTE(SUBSTITUTE(G38,CHAR(160),""),CHAR(9),"")),4,4) ) -> 7230C | S38: {=_xlfn.LET( _xlpm.ch, TRIM(SUBSTITUTE(G38,CHAR(160),"")), _xlpm.ehTrator, OR(IFERROR(FIND("BM",_xlpm.ch),0)>0, IFERROR(FIND("PY",_xlpm.ch),0)>0), _xlpm.chave, IF(_xlpm.ehTrator, MID(_xlpm.ch,4,5), MID(_xlpm.ch,4,4)), _xlpm.fonte, IF(LEN(_xlpm.chave)=5, UTIL!BV:BV, UTIL!BU:BU), _xlpm.modelo, TRIM(SUBSTITUTE(R38,CHAR(160),"")), _xlpm.nomeMod, IFERROR(_xlfn.XLOOKUP("*"&_xlpm.modelo&"*", UTIL!D:D, UTIL!B:B, "", 2), IFERROR(_xlfn.XLOOKUP("*"&_xlpm.modelo&"*", UTIL!E:E, UTIL!B:B, "", 2), "")), _xlpm.tipoMod, IF(_xlpm.nomeMod="", "", IFERROR(LEFT(_xlpm.nomeMod, FIND(" ", _xlpm.nomeMod)-1), _xlpm.nomeMod)), _xlpm.dimMod, IFERROR(_xlfn.XLOOKUP("*"&_xlpm.modelo&"*", UTIL!D:D, UTIL!K:K, "", 2), IFERROR(_xlfn.XLOOKUP("*"&_xlpm.modelo&"*", UTIL!E:E, UTIL!K:K, "", 2), "")), _xlpm.tipotxt_antigo, IF(_xlpm.ehTrator, "TRATOR", IFERROR(_xlfn.XLOOKUP(_xlpm.chave, _xlpm.fonte, UTIL!BS:BS, "", 0), IFERROR(_xlfn.XLOOKUP("*"&_xlpm.chave&"*", _xlpm.fonte, UTIL!BS:BS, "", 2), "Não encontrado"))), _xlpm.dimtxt_antigo, IFERROR(_xlfn.XLOOKUP(_xlpm.chave, _xlpm.fonte, UTIL!CB:CB, "", 0), IFERROR(_xlfn.XLOOKUP("*"&_xlpm.chave&"*", _xlpm.fonte, UTIL!CB:CB, "", 2), "Não encontrado")), _xlpm.tipotxt, IF(_xlpm.tipoMod<>"", _xlpm.tipoMod, _xlpm.tipotxt_antigo), _xlpm.dimtxt, IF(_xlpm.dimMod<>"", _xlpm.dimMod, _xlpm.dimtxt_antigo), _xlpm.deTxt, IF(L38="CLIENTE", O38, IF(LEFT(L38,4)="http", L38, "MACPONTA AGRO DE "&L38)), _xlpm.paraBase, IF(M38="CLIENTE", P38, M38), _xlpm.paraTxt, IF(LEFT(_xlpm.paraBase,4)="http", _xlpm.paraBase, "MACPONTA AGRO DE "&_xlpm.paraBase), _xlpm.nfParte, IF(LEN(TRIM(I38))=0, "", " -NF "&TRIM(I38)), "- " & _xlpm.tipotxt & ": *" & G38 & "*" & CHAR(13)&CHAR(10) & "- " & _xlpm.dimtxt & CHAR(13)&CHAR(10) & "- *Cliente*: " & J38 & _xlpm.nfParte & CHAR(13)&CHAR(10) & "- *Obs:* " & Q38 & CHAR(13)&CHAR(10) & CHAR(10) & "- *De*: " & _xlpm.deTxt & CHAR(13)&CHAR(10) & "- *Para*: " & _xlpm.paraTxt & CHAR(13)&CHAR(10) & "- *Ida e volta*: +/- " & TEXT(((D38*1.5)/1440),"h:mm") & "h | " & D38 & "km" )} -> - TRATOR: *1BM7230CKS3002086*_x000D_ - _x000D_ - *Cliente*: DEMO GOLF CLUBE -NF ? 16h_x000D_ - *Obs:* Silvana +55 42 9955-7892 (Golf Clube)_x000D_ - *De*: MACPONTA AGRO DE PONTA GROSSA_x000D_ - *Para*: https://maps.app.goo.gl/nPrR72QZAjPCStGf7_x000D_ - *Ida e volta*: +/- 1:24h | 56km
A39: PROGRAMADO (D) | B39: PROPRIO VW | C39: 0.058333333 | D39: 56 | E39: =IFERROR((D39*7),"?") -> 392 | F39: 0 | G39: 1BM7215CJSH000128 | H39: 45980 | J39: DEMO GOLF CLUBE -NF ? 16h | K39: carolina.quadros | L39: PONTA GROSSA | M39: CLIENTE | N39: DE LOJA PARA DEMONSTRAÇÃO | O39: MPA | P39: https://maps.app.goo.gl/nPrR72QZAjPCStGf7 | Q39: Silvana +55 42 9955-7892 (Golf Clube) | R39: =IF( OR( IFERROR(FIND("BM",G39),0)>0, IFERROR(FIND("PY",G39),0)>0 ), MID(TRIM(SUBSTITUTE(SUBSTITUTE(G39,CHAR(160),""),CHAR(9),"")),4,5), MID(TRIM(SUBSTITUTE(SUBSTITUTE(G39,CHAR(160),""),CHAR(9),"")),4,4) ) -> 7215C | S39: {=_xlfn.LET( _xlpm.ch, TRIM(SUBSTITUTE(G39,CHAR(160),"")), _xlpm.ehTrator, OR(IFERROR(FIND("BM",_xlpm.ch),0)>0, IFERROR(FIND("PY",_xlpm.ch),0)>0), _xlpm.chave, IF(_xlpm.ehTrator, MID(_xlpm.ch,4,5), MID(_xlpm.ch,4,4)), _xlpm.fonte, IF(LEN(_xlpm.chave)=5, UTIL!BV:BV, UTIL!BU:BU), _xlpm.modelo, TRIM(SUBSTITUTE(R39,CHAR(160),"")), _xlpm.nomeMod, IFERROR(_xlfn.XLOOKUP("*"&_xlpm.modelo&"*", UTIL!D:D, UTIL!B:B, "", 2), IFERROR(_xlfn.XLOOKUP("*"&_xlpm.modelo&"*", UTIL!E:E, UTIL!B:B, "", 2), "")), _xlpm.tipoMod, IF(_xlpm.nomeMod="", "", IFERROR(LEFT(_xlpm.nomeMod, FIND(" ", _xlpm.nomeMod)-1), _xlpm.nomeMod)), _xlpm.dimMod, IFERROR(_xlfn.XLOOKUP("*"&_xlpm.modelo&"*", UTIL!D:D, UTIL!K:K, "", 2), IFERROR(_xlfn.XLOOKUP("*"&_xlpm.modelo&"*", UTIL!E:E, UTIL!K:K, "", 2), "")), _xlpm.tipotxt_antigo, IF(_xlpm.ehTrator, "TRATOR", IFERROR(_xlfn.XLOOKUP(_xlpm.chave, _xlpm.fonte, UTIL!BS:BS, "", 0), IFERROR(_xlfn.XLOOKUP("*"&_xlpm.chave&"*", _xlpm.fonte, UTIL!BS:BS, "", 2), "Não encontrado"))), _xlpm.dimtxt_antigo, IFERROR(_xlfn.XLOOKUP(_xlpm.chave, _xlpm.fonte, UTIL!CB:CB, "", 0), IFERROR(_xlfn.XLOOKUP("*"&_xlpm.chave&"*", _xlpm.fonte, UTIL!CB:CB, "", 2), "Não encontrado")), _xlpm.tipotxt, IF(_xlpm.tipoMod<>"", _xlpm.tipoMod, _xlpm.tipotxt_antigo), _xlpm.dimtxt, IF(_xlpm.dimMod<>"", _xlpm.dimMod, _xlpm.dimtxt_antigo), _xlpm.deTxt, IF(L39="CLIENTE", O39, IF(LEFT(L39,4)="http", L39, "MACPONTA AGRO DE "&L39)), _xlpm.paraBase, IF(M39="CLIENTE", P39, M39), _xlpm.paraTxt, IF(LEFT(_xlpm.paraBase,4)="http", _xlpm.paraBase, "MACPONTA AGRO DE "&_xlpm.paraBase), _xlpm.nfParte, IF(LEN(TRIM(I39))=0, "", " -NF "&TRIM(I39)), "- " & _xlpm.tipotxt & ": *" & G39 & "*" & CHAR(13)&CHAR(10) & "- " & _xlpm.dimtxt & CHAR(13)&CHAR(10) & "- *Cliente*: " & J39 & _xlpm.nfParte & CHAR(13)&CHAR(10) & "- *Obs:* " & Q39 & CHAR(13)&CHAR(10) & CHAR(10) & "- *De*: " & _xlpm.deTxt & CHAR(13)&CHAR(10) & "- *Para*: " & _xlpm.paraTxt & CHAR(13)&CHAR(10) & "- *Ida e volta*: +/- " & TEXT(((D39*1.5)/1440),"h:mm") & "h | " & D39 & "km" )} -> - TRATOR: *1BM7215CJSH000128*_x000D_ - _x000D_ - *Cliente*: DEMO GOLF CLUBE -NF ? 16h_x000D_ - *Obs:* Silvana +55 42 9955-7892 (Golf Clube)_x000D_ - *De*: MACPONTA AGRO DE PONTA GROSSA_x000D_ - *Para*: https://maps.app.goo.gl/nPrR72QZAjPCStGf7_x000D_ - *Ida e volta*: +/- 1:24h | 56km
A40: PROGRAMADO (D) | B40: PROPRIO DAF | C40: =IFERROR((D40*1.5)/1440, "?") -> 0.058333333 | D40: 56 | E40: =IFERROR((D40*7),"?") -> 392 | F40: 0 | G40: 1BM7230CKS3002086 | H40: 45985 | J40: DEMO GOLF CLUBE -NF ? volta | K40: carolina.quadros | L40: PONTA GROSSA | M40: CLIENTE | N40: DE LOJA PARA DEMONSTRAÇÃO | O40: MPA | P40: https://maps.app.goo.gl/nPrR72QZAjPCStGf7 | Q40: Silvana +55 42 9955-7892 (Golf Clube) | R40: =IF( OR( IFERROR(FIND("BM",G40),0)>0, IFERROR(FIND("PY",G40),0)>0 ), MID(TRIM(SUBSTITUTE(SUBSTITUTE(G40,CHAR(160),""),CHAR(9),"")),4,5), MID(TRIM(SUBSTITUTE(SUBSTITUTE(G40,CHAR(160),""),CHAR(9),"")),4,4) ) -> 7230C | S40: {=_xlfn.LET( _xlpm.ch, TRIM(SUBSTITUTE(G40,CHAR(160),"")), _xlpm.ehTrator, OR(IFERROR(FIND("BM",_xlpm.ch),0)>0, IFERROR(FIND("PY",_xlpm.ch),0)>0), _xlpm.chave, IF(_xlpm.ehTrator, MID(_xlpm.ch,4,5), MID(_xlpm.ch,4,4)), _xlpm.fonte, IF(LEN(_xlpm.chave)=5, UTIL!BV:BV, UTIL!BU:BU), _xlpm.modelo, TRIM(SUBSTITUTE(R40,CHAR(160),"")), _xlpm.nomeMod, IFERROR(_xlfn.XLOOKUP("*"&_xlpm.modelo&"*", UTIL!D:D, UTIL!B:B, "", 2), IFERROR(_xlfn.XLOOKUP("*"&_xlpm.modelo&"*", UTIL!E:E, UTIL!B:B, "", 2), "")), _xlpm.tipoMod, IF(_xlpm.nomeMod="", "", IFERROR(LEFT(_xlpm.nomeMod, FIND(" ", _xlpm.nomeMod)-1), _xlpm.nomeMod)), _xlpm.dimMod, IFERROR(_xlfn.XLOOKUP("*"&_xlpm.modelo&"*", UTIL!D:D, UTIL!K:K, "", 2), IFERROR(_xlfn.XLOOKUP("*"&_xlpm.modelo&"*", UTIL!E:E, UTIL!K:K, "", 2), "")), _xlpm.tipotxt_antigo, IF(_xlpm.ehTrator, "TRATOR", IFERROR(_xlfn.XLOOKUP(_xlpm.chave, _xlpm.fonte, UTIL!BS:BS, "", 0), IFERROR(_xlfn.XLOOKUP("*"&_xlpm.chave&"*", _xlpm.fonte, UTIL!BS:BS, "", 2), "Não encontrado"))), _xlpm.dimtxt_antigo, IFERROR(_xlfn.XLOOKUP(_xlpm.chave, _xlpm.fonte, UTIL!CB:CB, "", 0), IFERROR(_xlfn.XLOOKUP("*"&_xlpm.chave&"*", _xlpm.fonte, UTIL!CB:CB, "", 2), "Não encontrado")), _xlpm.tipotxt, IF(_xlpm.tipoMod<>"", _xlpm.tipoMod, _xlpm.tipotxt_antigo), _xlpm.dimtxt, IF(_xlpm.dimMod<>"", _xlpm.dimMod, _xlpm.dimtxt_antigo), _xlpm.deTxt, IF(L40="CLIENTE", O40, IF(LEFT(L40,4)="http", L40, "MACPONTA AGRO DE "&L40)), _xlpm.paraBase, IF(M40="CLIENTE", P40, M40), _xlpm.paraTxt, IF(LEFT(_xlpm.paraBase,4)="http", _xlpm.paraBase, "MACPONTA AGRO DE "&_xlpm.paraBase), _xlpm.nfParte, IF(LEN(TRIM(I40))=0, "", " -NF "&TRIM(I40)), "- " & _xlpm.tipotxt & ": *" & G40 & "*" & CHAR(13)&CHAR(10) & "- " & _xlpm.dimtxt & CHAR(13)&CHAR(10) & "- *Cliente*: " & J40 & _xlpm.nfParte & CHAR(13)&CHAR(10) & "- *Obs:* " & Q40 & CHAR(13)&CHAR(10) & CHAR(10) & "- *De*: " & _xlpm.deTxt & CHAR(13)&CHAR(10) & "- *Para*: " & _xlpm.paraTxt & CHAR(13)&CHAR(10) & "- *Ida e volta*: +/- " & TEXT(((D40*1.5)/1440),"h:mm") & "h | " & D40 & "km" )} -> - TRATOR: *1BM7230CKS3002086*_x000D_ - _x000D_ - *Cliente*: DEMO GOLF CLUBE -NF ? volta_x000D_ - *Obs:* Silvana +55 42 9955-7892 (Golf Clube)_x000D_ - *De*: MACPONTA AGRO DE PONTA GROSSA_x000D_ - *Para*: https://maps.app.goo.gl/nPrR72QZAjPCStGf7_x000D_ - *Ida e volta*: +/- 1:24h | 56km
A41: PROGRAMADO (D) | B41: PROPRIO VW | C41: 0.058333333 | D41: 56 | E41: =IFERROR((D41*7),"?") -> 392 | F41: 0 | G41: 1BM7215CJSH000128 | H41: 45985 | J41: DEMO GOLF CLUBE -NF ? volta | K41: carolina.quadros | L41: PONTA GROSSA | M41: CLIENTE | N41: DE LOJA PARA DEMONSTRAÇÃO | O41: MPA | P41: https://maps.app.goo.gl/nPrR72QZAjPCStGf7 | Q41: Silvana +55 42 9955-7892 (Golf Clube) | R41: =IF( OR( IFERROR(FIND("BM",G41),0)>0, IFERROR(FIND("PY",G41),0)>0 ), MID(TRIM(SUBSTITUTE(SUBSTITUTE(G41,CHAR(160),""),CHAR(9),"")),4,5), MID(TRIM(SUBSTITUTE(SUBSTITUTE(G41,CHAR(160),""),CHAR(9),"")),4,4) ) -> 7215C | S41: {=_xlfn.LET( _xlpm.ch, TRIM(SUBSTITUTE(G41,CHAR(160),"")), _xlpm.ehTrator, OR(IFERROR(FIND("BM",_xlpm.ch),0)>0, IFERROR(FIND("PY",_xlpm.ch),0)>0), _xlpm.chave, IF(_xlpm.ehTrator, MID(_xlpm.ch,4,5), MID(_xlpm.ch,4,4)), _xlpm.fonte, IF(LEN(_xlpm.chave)=5, UTIL!BV:BV, UTIL!BU:BU), _xlpm.modelo, TRIM(SUBSTITUTE(R41,CHAR(160),"")), _xlpm.nomeMod, IFERROR(_xlfn.XLOOKUP("*"&_xlpm.modelo&"*", UTIL!D:D, UTIL!B:B, "", 2), IFERROR(_xlfn.XLOOKUP("*"&_xlpm.modelo&"*", UTIL!E:E, UTIL!B:B, "", 2), "")), _xlpm.tipoMod, IF(_xlpm.nomeMod="", "", IFERROR(LEFT(_xlpm.nomeMod, FIND(" ", _xlpm.nomeMod)-1), _xlpm.nomeMod)), _xlpm.dimMod, IFERROR(_xlfn.XLOOKUP("*"&_xlpm.modelo&"*", UTIL!D:D, UTIL!K:K, "", 2), IFERROR(_xlfn.XLOOKUP("*"&_xlpm.modelo&"*", UTIL!E:E, UTIL!K:K, "", 2), "")), _xlpm.tipotxt_antigo, IF(_xlpm.ehTrator, "TRATOR", IFERROR(_xlfn.XLOOKUP(_xlpm.chave, _xlpm.fonte, UTIL!BS:BS, "", 0), IFERROR(_xlfn.XLOOKUP("*"&_xlpm.chave&"*", _xlpm.fonte, UTIL!BS:BS, "", 2), "Não encontrado"))), _xlpm.dimtxt_antigo, IFERROR(_xlfn.XLOOKUP(_xlpm.chave, _xlpm.fonte, UTIL!CB:CB, "", 0), IFERROR(_xlfn.XLOOKUP("*"&_xlpm.chave&"*", _xlpm.fonte, UTIL!CB:CB, "", 2), "Não encontrado")), _xlpm.tipotxt, IF(_xlpm.tipoMod<>"", _xlpm.tipoMod, _xlpm.tipotxt_antigo), _xlpm.dimtxt, IF(_xlpm.dimMod<>"", _xlpm.dimMod, _xlpm.dimtxt_antigo), _xlpm.deTxt, IF(L41="CLIENTE", O41, IF(LEFT(L41,4)="http", L41, "MACPONTA AGRO DE "&L41)), _xlpm.paraBase, IF(M41="CLIENTE", P41, M41), _xlpm.paraTxt, IF(LEFT(_xlpm.paraBase,4)="http", _xlpm.paraBase, "MACPONTA AGRO DE "&_xlpm.paraBase), _xlpm.nfParte, IF(LEN(TRIM(I41))=0, "", " -NF "&TRIM(I41)), "- " & _xlpm.tipotxt & ": *" & G41 & "*" & CHAR(13)&CHAR(10) & "- " & _xlpm.dimtxt & CHAR(13)&CHAR(10) & "- *Cliente*: " & J41 & _xlpm.nfParte & CHAR(13)&CHAR(10) & "- *Obs:* " & Q41 & CHAR(13)&CHAR(10) & CHAR(10) & "- *De*: " & _xlpm.deTxt & CHAR(13)&CHAR(10) & "- *Para*: " & _xlpm.paraTxt & CHAR(13)&CHAR(10) & "- *Ida e volta*: +/- " & TEXT(((D41*1.5)/1440),"h:mm") & "h | " & D41 & "km" )} -> - TRATOR: *1BM7215CJSH000128*_x000D_ - _x000D_ - *Cliente*: DEMO GOLF CLUBE -NF ? volta_x000D_ - *Obs:* Silvana +55 42 9955-7892 (Golf Clube)_x000D_ - *De*: MACPONTA AGRO DE PONTA GROSSA_x000D_ - *Para*: https://maps.app.goo.gl/nPrR72QZAjPCStGf7_x000D_ - *Ida e volta*: +/- 1:24h | 56km
A43: RECEBIDO
A44: PROGRAMADO
A45: EM ROTA
A46: RECEBIDO (D)
A47: PROGRAMADO (D)

Sheet FRETE PEÇAS
A1: STATUS | B1: SOLICITANTE | C1: DATA DA COLETA | D1: ENTREGAR ATÉ | E1: MOTOBOY OU DEDICADO? | F1: ESCOLHA O MOTOBOY | G1: VALOR DO SERVIÇO | H1: QUEM IRÁ PAGAR? | I1: DESCRIÇÃO | J1: PC PARA LOJA | K1: ENVIAR PC PARA | L1: DIMENSÕES | M1: LOC COLETA | N1: LOC ENTREGA | O1: SUGESTÃO TRANSP
A2: CONCLUIDO
A3: REGISTRADO

Sheet VW DAF
A1: ITEM | B1: CAMINHÃO VW | C1: CAMINHÃO DAF
A2: Placa | B2: ATV6639 | C2: SDY9A72
A3: Modelo | B3: VW 24.320 CLC 6x2 | C3: DAF CF FAC 410 | E3: REFORMULAR
A4: Ano Fabricação | B4: 2010 | C4: 2022
A5: Cor | B5: Branca | C5: Branca
A6: Combustível | B6: Diesel | C6: Diesel
A7: Tipo | B7: Caminhão Carga / Prancha | C7: Caminhão Carga / Prancha (com Mec. Operac. e Estendida)
A8: Potência (CV) | B8: 320 | C8: 410
A9: CMT (t) | B9: 45 | C9: 45
A10: PBTC (t) | B10: 23 | C10: 29
A11: Comprimento (m) | B11: 128 | C11: 140
A12: Altura (cm) | B12: 495 | C12: 495
A13: Largura (cm) | B13: 32 | C13: 32
A14: Velocidade Máx. (km/h) | B14: 60 | C14: 60
A15: Acessório | B15: CAR/REBOQUE/C. ABERTA | C15: CARGA REBOQUE
A16: Valor Aquisição (Caminhão) | B16: 252400 | C16: 895000
A17: Valor Aquisição (Acessório) | B17: 67300 | C17: 120000
A18: Valor Total | B18: 319700 | C18: 1015000
B20: ATV6639 | C20: SDY9A72
B21: 00317009680 | C21: 01326905837
B22: 00.702.079/0001-00 | C22: 00.702.079/0001-00
C24: SDZ9C31
C25: 01328419948
C26: 00.702.079/0001-00
A28: SIDER – DER/PR → https://sider.der.pr.gov.br
A29: DPRF - Departamento de Polícia Rodoviária Federal → https://www.prf.gov.br/
A30: DNIT - Departamento Nacional de infraestrutura de Transportes → http://www.dnit.gov.br/
A31: IPVA - Em caso de dúvidas consulte → www.fazenda.pr.gov.br
A32: Seguro DPVAT → www.dpvatsegurodotransito.com.br
A34: Sistema | B34: Login | C34: ACESSO
A35: DNIT (Federais) | B35: 11307 | C35: 11307
A36: SIDER/PR (Estaduais - PR) | B36: 00702079000100 | C36: 6hyod
A37: AET - Requerimento de AET | B37: 00702079000100 | C37: MPA@2025
A38: Multa Detran | B38: DAF | C38: 116200 - NIC0998654 - SDY9A72 - 00702079000100
A39: CRLV-e e IPVA | B39: Site do Detran
A41: LUIZ MAURO PEDROSO DA SILVA; CPF 021.745.239-65; Reg. 02659067776
A42: DIOGO DUARTE FERREIRA; CPF 068.744.709-73; Registro 04308191052
A44: ITEM | B44: CAMINHÃO VW | C44: CAMINHÃO DAF
A45: RENAVAM | B45: 00317009680 | C45: 01326905837 / Reboque: 01328419948
A46: Chassi | B46: - | C46: 98PACM410NB124999
A47: CRLV (último) | B47: - | C47: 44931
A48: IPVA Pago (último) | B48: 44931 | C48: 44931
A49: IPVA 2025 (R$) | B49: 152362 | C49: 476464
A50: Licenciamento | B50: - | C50: 7.58
A51: Seguro | B51: - | C51: 6821.34
A52: AET Validade | B52: 10/03/2025 a 07/06/2025 | C52: 03/03/2025 a 20/05/2025
A53: Situação Documental | B53: OK (AET e IPVA pagos) | C53: OK (AET e IPVA pagos)
A54: Custos Fixos (mensal)
A55: Custos Variáveis (mensal)
A56: Custo Total (mensal)
A57: KM Mês
A58: Valor por KM

Sheet PEDIDO COMPRA
A1: TIPO | B1: FILIAL | C1: DATA | D1: PDIDO | E1: CÓD | F1: FORNECEDOR | G1: VALOR | H1: STATUS PC | I1: Nº NOTA | J1: LANÇADA | K1: OBSERVAÇÕES | L1: SALVAR COMO
A2: Frete Peças | B2: ARAPOTI | C2: 45964 | D2: 047186 | E2: 027525938 | F2: ESC TRANSPORTES | G2: 1100 | H2: Aprovado | I2: 2967 | J2: 45965 | K2: FRETE DE PEÇAS - ESC | L2: =TEXT($C2,"dd.mm") & " -Ped " & D2 & " -" & F2 & " -R$" & G2 & IF(LEN(TRIM(I2))=0, "", " -NF " & TRIM(I2)) -> 03.11 -Ped 047186 -ESC TRANSPORTES -R$1100 -NF 2967
A3: Frete Peças | B3: IRATI | C3: 45964 | D3: 047187 | E3: 027525938 | F3: ESC TRANSPORTES | G3: 550 | H3: Aprovado | I3: 2965 | J3: 45965 | K3: FRETE DE PEÇAS - ESC | L3: =TEXT($C3,"dd.mm") & " -Ped " & D3 & " -" & F3 & " -R$" & G3 & IF(LEN(TRIM(I3))=0, "", " -NF " & TRIM(I3)) -> 03.11 -Ped 047187 -ESC TRANSPORTES -R$550 -NF 2965
A4: Frete Peças | B4: PG | C4: 45964 | D4: 047188 | E4: 027525938 | F4: ESC TRANSPORTES | G4: 600 | H4: Aprovado | I4: 2964 | J4: 45965 | K4: FRETE DE PEÇAS - ESC | L4: =TEXT($C4,"dd.mm") & " -Ped " & D4 & " -" & F4 & " -R$" & G4 & IF(LEN(TRIM(I4))=0, "", " -NF " & TRIM(I4)) -> 03.11 -Ped 047188 -ESC TRANSPORTES -R$600 -NF 2964
A5: Frete Peças | B5: PRUDE | C5: 45964 | D5: 047189 | E5: 027525938 | F5: ESC TRANSPORTES | G5: 550 | H5: Aprovado | I5: 2963 | J5: 45965 | K5: FRETE DE PEÇAS - ESC | L5: =TEXT($C5,"dd.mm") & " -Ped " & D5 & " -" & F5 & " -R$" & G5 & IF(LEN(TRIM(I5))=0, "", " -NF " & TRIM(I5)) -> 03.11 -Ped 047189 -ESC TRANSPORTES -R$550 -NF 2963
A6: Frete Peças | B6: CASTRO | C6: 45964 | D6: 047190 | E6: 027525938 | F6: ESC TRANSPORTES | G6: 850 | H6: Aprovado | I6: 2962 | J6: 45965 | K6: FRETE DE PEÇAS - ESC | L6: =TEXT($C6,"dd.mm") & " -Ped " & D6 & " -" & F6 & " -R$" & G6 & IF(LEN(TRIM(I6))=0, "", " -NF " & TRIM(I6)) -> 03.11 -Ped 047190 -ESC TRANSPORTES -R$850 -NF 2962
A7: Frete Peças | B7: GRPVA | C7: 45964 | D7: 047192 | E7: 027525938 | F7: ESC TRANSPORTES | G7: 1100 | H7: Aprovado | I7: 2969 | J7: 45965 | K7: FRETE DE PEÇAS - ESC | L7: =TEXT($C7,"dd.mm") & " -Ped " & D7 & " -" & F7 & " -R$" & G7 & IF(LEN(TRIM(I7))=0, "", " -NF " & TRIM(I7)) -> 03.11 -Ped 047192 -ESC TRANSPORTES -R$1100 -NF 2969
A8: Frete Peças | B8: TIBAGI | C8: 45964 | D8: 047193 | E8: 027525938 | F8: ESC TRANSPORTES | G8: 830 | H8: Aprovado | I8: 2968 | J8: 45965 | K8: FRETE DE PEÇAS - ESC | L8: =TEXT($C8,"dd.mm") & " -Ped " & D8 & " -" & F8 & " -R$" & G8 & IF(LEN(TRIM(I8))=0, "", " -NF " & TRIM(I8)) -> 03.11 -Ped 047193 -ESC TRANSPORTES -R$830 -NF 2968
A9: Frete Peças | B9: TIBAGI | C9: 45964 | D9: 047258 | E9: 061196032 | F9: ANDREIA R. COURIER | G9: 200 | H9: Aprovado | I9: 48 | J9: 45966 | L9: =TEXT($C9,"dd.mm") & " -Ped " & D9 & " -" & F9 & " -R$" & G9 & IF(LEN(TRIM(I9))=0, "", " -NF " & TRIM(I9)) -> 03.11 -Ped 047258 -ANDREIA R. COURIER -R$200 -NF 48
A10: Frete Peças | B10: TIBAGI | C10: 45964 | D10: 047247 | E10: 049138592 | F10: DELTA MOTOS COURIER | G10: 1210 | H10: Aprovado | I10: 247 | J10: 45967 | K10: MOTOBOY X CLIENTE: ENTREGAS DO MÊS DE OUTUBRO | L10: =TEXT($C10,"dd.mm") & " -Ped " & D10 & " -" & F10 & " -R$" & G10 & IF(LEN(TRIM(I10))=0, "", " -NF " & TRIM(I10)) -> 03.11 -Ped 047247 -DELTA MOTOS COURIER -R$1210 -NF 247
A11: Frete Peças | B11: GRPVA | C11: 45964 | D11: 047246 | E11: 049138592 | F11: DELTA MOTOS COURIER | G11: 550 | H11: Aprovado | I11: 246 | J11: 45968 | L11: =TEXT($C11,"dd.mm") & " -Ped " & D11 & " -" & F11 & " -R$" & G11 & IF(LEN(TRIM(I11))=0, "", " -NF " & TRIM(I11)) -> 03.11 -Ped 047246 -DELTA MOTOS COURIER -R$550 -NF 246
A12: Frete Peças | B12: IRATI | C12: 45964 | D12: 047233 | E12: 049138592 | F12: DELTA MOTOS COURIER | G12: 180 | H12: Aprovado | I12: 245 | J12: 45969 | K12: FRETE DE PEÇAS MOTOBOY X CLIENTE | L12: =TEXT($C12,"dd.mm") & " -Ped " & D12 & " -" & F12 & " -R$" & G12 & IF(LEN(TRIM(I12))=0, "", " -NF " & TRIM(I12)) -> 03.11 -Ped 047233 -DELTA MOTOS COURIER -R$180 -NF 245
A13: Frete Peças | B13: ARAPOTI | C13: 45964 | D13: 047243 | E13: 049138592 | F13: DELTA MOTOS COURIER | G13: 990 | H13: Aprovado | I13: 244 | J13: 45970 | L13: =TEXT($C13,"dd.mm") & " -Ped " & D13 & " -" & F13 & " -R$" & G13 & IF(LEN(TRIM(I13))=0, "", " -NF " & TRIM(I13)) -> 03.11 -Ped 047243 -DELTA MOTOS COURIER -R$990 -NF 244
A14: Frete Peças | B14: PRUDE | C14: 45964 | D14: 047244 | E14: 049138592 | F14: DELTA MOTOS COURIER | G14: 245 | H14: Aprovado | I14: 243 | J14: 45971 | L14: =TEXT($C14,"dd.mm") & " -Ped " & D14 & " -" & F14 & " -R$" & G14 & IF(LEN(TRIM(I14))=0, "", " -NF " & TRIM(I14)) -> 03.11 -Ped 047244 -DELTA MOTOS COURIER -R$245 -NF 243
A15: Frete Peças | B15: PG | C15: 45964 | D15: 047249 | E15: 049138592 | F15: DELTA MOTOS COURIER | G15: 8245 | H15: Aprovado | I15: 242 | J15: 45972 | L15: =TEXT($C15,"dd.mm") & " -Ped " & D15 & " -" & F15 & " -R$" & G15 & IF(LEN(TRIM(I15))=0, "", " -NF " & TRIM(I15)) -> 03.11 -Ped 047249 -DELTA MOTOS COURIER -R$8245 -NF 242
A16: Frete Peças | B16: TIBAGI | C16: 45964 | D16: 047267 | E16: 061196032 | F16: ANDREIA R. COURIER | G16: 200 | H16: Aprovado | I16: FIN | J16: 45972 | L16: =TEXT($C16,"dd.mm") & " -Ped " & D16 & " -" & F16 & " -R$" & G16 & IF(LEN(TRIM(I16))=0, "", " -NF " & TRIM(I16)) -> 03.11 -Ped 047267 -ANDREIA R. COURIER -R$200 -NF FIN
A17: Manutenção VW | B17: PG | C17: 45965 | D17: 047178 | E17: 004892707 | F17: DNIT | G17: 87.62 | H17: Aprovado | I17: BOLETO | J17: 45965 | K17: BOLETO DNIT - AET TRIMESTRAL VW (120006) | L17: =TEXT($C17,"dd.mm") & " -Ped " & D17 & " -" & F17 & " -R$" & G17 & IF(LEN(TRIM(I17))=0, "", " -NF " & TRIM(I17)) -> 04.11 -Ped 047178 -DNIT -R$87,62 -NF BOLETO
A18: Frete Peças | B18: PRUDE | C18: 45965 | D18: 047199 | E18: 034154225 | F18: JOHN ELVIS COURIER | G18: 150 | H18: Aprovado | I18: 420 | J18: 45967 | K18: FRETE DE PEÇAS P/ CLIENTE | L18: =TEXT($C18,"dd.mm") & " -Ped " & D18 & " -" & F18 & " -R$" & G18 & IF(LEN(TRIM(I18))=0, "", " -NF " & TRIM(I18)) -> 04.11 -Ped 047199 -JOHN ELVIS COURIER -R$150 -NF 420
A19: Frete Máq. Trator | B19: IRATI | C19: 45965 | D19: 047269 | E19: 032878844 | F19: STOSKI TRANSPORTES | G19: 910 | H19: Aprovado | I19: 177 | J19: 45967 | K19: ENTREGA TRATOR 6135M - LAURO MIGUEL STRONA | L19: =TEXT($C19,"dd.mm") & " -Ped " & D19 & " -" & F19 & " -R$" & G19 & IF(LEN(TRIM(I19))=0, "", " -NF " & TRIM(I19)) -> 04.11 -Ped 047269 -STOSKI TRANSPORTES -R$910 -NF 177
A20: Frete Máq. Trator | B20: ARAPOTI | C20: 45965 | D20: 047315 | E20: 006914002 | F20: TRANSCAPITINGA FRET | G20: 1295 | H20: Aprovado | I20: 186 | J20: 45968 | K20: TRANSPORTE DE TRATOR DE JAPIRA PARA ARAPOTI | L20: =TEXT($C20,"dd.mm") & " -Ped " & D20 & " -" & F20 & " -R$" & G20 & IF(LEN(TRIM(I20))=0, "", " -NF " & TRIM(I20)) -> 04.11 -Ped 047315 -TRANSCAPITINGA FRET -R$1295 -NF 186
A21: Frete Peças | B21: TIBAGI | C21: 45965 | D21: 047437 | E21: 061196032 | F21: ANDREIA R. COURIER | G21: 80 | H21: Aprovado | I21: 51 | J21: 45971 | L21: =TEXT($C21,"dd.mm") & " -Ped " & D21 & " -" & F21 & " -R$" & G21 & IF(LEN(TRIM(I21))=0, "", " -NF " & TRIM(I21)) -> 04.11 -Ped 047437 -ANDREIA R. COURIER -R$80 -NF 51
A22: Manutenção DAF | B22: PG | C22: 45966 | D22: 047117 | E22: 078206513 | F22: DETRAN PR | G22: 156.18 | H22: Aprovado | I22: BOLETO | J22: 45964 | K22: Reboque: sem ABS correto | L22: =TEXT($C22,"dd.mm") & " -Ped " & D22 & " -" & F22 & " -R$" & G22 & IF(LEN(TRIM(I22))=0, "", " -NF " & TRIM(I22)) -> 05.11 -Ped 047117 -DETRAN PR -R$156,18 -NF BOLETO
A23: Manutenção DAF | B23: PG | C23: 45966 | D23: 047117 | E23: 078206513 | F23: DETRAN PR | G23: 94.61 | H23: Aprovado | I23: BOLETO | J23: 45964 | K23: Reboque: Licenciamento 2025 | L23: =TEXT($C23,"dd.mm") & " -Ped " & D23 & " -" & F23 & " -R$" & G23 & IF(LEN(TRIM(I23))=0, "", " -NF " & TRIM(I23)) -> 05.11 -Ped 047117 -DETRAN PR -R$94,61 -NF BOLETO
A24: Frete Peças | B24: GRPVA | C24: 45966 | D24: 047268 | E24: 051496564 | F24: MARCOS D COURIER | G24: 180 | H24: Aprovado | I24: 409 | J24: 45967 | K24: MOTOBOY: orçamento 79186 | L24: =TEXT($C24,"dd.mm") & " -Ped " & D24 & " -" & F24 & " -R$" & G24 & IF(LEN(TRIM(I24))=0, "", " -NF " & TRIM(I24)) -> 05.11 -Ped 047268 -MARCOS D COURIER -R$180 -NF 409
A25: Frete Peças | B25: CASTRO | C25: 45966 | D25: 047267 | E25: 051496564 | F25: MARCOS D COURIER | G25: 520 | H25: Aprovado | I25: 408 | J25: 45967 | K25: MOTOBOY: TRANSF ENTRE LOJAS GRPVA X CASTRO | L25: =TEXT($C25,"dd.mm") & " -Ped " & D25 & " -" & F25 & " -R$" & G25 & IF(LEN(TRIM(I25))=0, "", " -NF " & TRIM(I25)) -> 05.11 -Ped 047267 -MARCOS D COURIER -R$520 -NF 408
A26: Frete Peças | B26: PG | C26: 45966 | D26: 047348 | E26: 080227796 | F26: PRINCESA DOS CAMPOS | G26: 371.14 | H26: Aprovado | I26: 336939 | J26: 45967 | K26: CTE - KLABIN TB | L26: =TEXT($C26,"dd.mm") & " -Ped " & D26 & " -" & F26 & " -R$" & G26 & IF(LEN(TRIM(I26))=0, "", " -NF " & TRIM(I26)) -> 05.11 -Ped 047348 -PRINCESA DOS CAMPOS -R$371,14 -NF 336939
A27: Frete Peças | B27: PG | C27: 45966 | D27: 047348 | E27: 080227796 | F27: PRINCESA DOS CAMPOS | G27: 529.48 | H27: Aprovado | I27: 348407 | J27: 45967 | K27: CTE - KLABIN TB | L27: =TEXT($C27,"dd.mm") & " -Ped " & D27 & " -" & F27 & " -R$" & G27 & IF(LEN(TRIM(I27))=0, "", " -NF " & TRIM(I27)) -> 05.11 -Ped 047348 -PRINCESA DOS CAMPOS -R$529,48 -NF 348407
A28: Frete Máq. Trator | B28: ARAPOTI | C28: 45966 | D28: 047315 | E28: 006914002 | F28: TRANSCAPITINGA FRET | G28: 975 | H28: Aprovado | I28: 186 | J28: 45968 | K28: TRANSPORTE DE TRATOR PARA SIQUEIRA CAMPOS VEREDIANA | L28: =TEXT($C28,"dd.mm") & " -Ped " & D28 & " -" & F28 & " -R$" & G28 & IF(LEN(TRIM(I28))=0, "", " -NF " & TRIM(I28)) -> 05.11 -Ped 047315 -TRANSCAPITINGA FRET -R$975 -NF 186
A29: Frete Peças | B29: CASTRO | C29: 45967 | D29: 047349 | E29: 012772524 | F29: UNIBOY COURIER | G29: 1860 | H29: Aprovado | I29: 3300 | J29: 45968 | K29: MOTOBOY | L29: =TEXT($C29,"dd.mm") & " -Ped " & D29 & " -" & F29 & " -R$" & G29 & IF(LEN(TRIM(I29))=0, "", " -NF " & TRIM(I29)) -> 06.11 -Ped 047349 -UNIBOY COURIER -R$1860 -NF 3300
A30: Manutenção VW | B30: PG | C30: 45968 | D30: 047383 | E30: 010273940 | F30: SERIE4 - MT | G30: 2780 | H30: Aprovado | I30: 2708 | J30: 45972 | K30: peças: correia, polia lisa, polia virabrequim, tensionador -vw | L30: =TEXT($C30,"dd.mm") & " -Ped " & D30 & " -" & F30 & " -R$" & G30 & IF(LEN(TRIM(I30))=0, "", " -NF " & TRIM(I30)) -> 07.11 -Ped 047383 -SERIE4 - MT -R$2780 -NF 2708
A31: Manutenção VW | B31: PG | C31: 45968 | D31: 047383 | E31: 010273940 | F31: SERIE4 - MT | G31: 840 | H31: Aprovado | I31: 2374 | J31: 45972 | K31: serviço de manutenção e troca -vw | L31: =TEXT($C31,"dd.mm") & " -Ped " & D31 & " -" & F31 & " -R$" & G31 & IF(LEN(TRIM(I31))=0, "", " -NF " & TRIM(I31)) -> 07.11 -Ped 047383 -SERIE4 - MT -R$840 -NF 2374
A32: Manutenção VW | B32: PG | C32: 45971 | D32: 047116 | E32: 076669324 | F32: DER - AET VEICULOS | G32: 133.13 | H32: Aprovado | I32: BOLETO | J32: 45964 | K32: 33 - D.A. - GRU - Multas de Radares; velocidade: acima de 20% | L32: =TEXT($C32,"dd.mm") & " -Ped " & D32 & " -" & F32 & " -R$" & G32 & IF(LEN(TRIM(I32))=0, "", " -NF " & TRIM(I32)) -> 10.11 -Ped 047116 -DER - AET VEICULOS -R$133,13 -NF BOLETO
A33: Manutenção VW | B33: PG | C33: 45989 | D33: 047117 | E33: 078206513 | F33: DETRAN PR | G33: 140.67 | H33: Aprovado | I33: BOLETO | J33: 45964 | K33: Velocidade: acima de 20% (multa de 2024) | L33: =TEXT($C33,"dd.mm") & " -Ped " & D33 & " -" & F33 & " -R$" & G33 & IF(LEN(TRIM(I33))=0, "", " -NF " & TRIM(I33)) -> 28.11 -Ped 047117 -DETRAN PR -R$140,67 -NF BOLETO
A34: Manutenção VW | B34: PG | C34: 45989 | D34: 047117 | E34: 078206513 | F34: DETRAN PR | G34: 275.78 | H34: Aprovado | I34: BOLETO | J34: 45964 | K34: Velocidade: acima de 20% (multa de 2024) | L34: =TEXT($C34,"dd.mm") & " -Ped " & D34 & " -" & F34 & " -R$" & G34 & IF(LEN(TRIM(I34))=0, "", " -NF " & TRIM(I34)) -> 28.11 -Ped 047117 -DETRAN PR -R$275,78 -NF BOLETO
A35: Munck | B35: ARAPOTI | C35: 45962 | D35: 047315 | E35: 006914002 | F35: TRANSCAPITINGA FRET | G35: 1000 | H35: Aprovado | K35: UTILIZAÇÃO DE MUNCK PARA CARREGAR E DESCARREGAR NA LOJA | L35: =TEXT($C35,"dd.mm") & " -Ped " & D35 & " -" & F35 & " -R$" & G35 & IF(LEN(TRIM(I35))=0, "", " -NF " & TRIM(I35)) -> 01.11 -Ped 047315 -TRANSCAPITINGA FRET -R$1000
A36: Frete Peças | B36: PRUDE | C36: 45965 | D36: 047263 | E36: 031370636 | F36: JORGE LUIZ 2 COURIER | G36: 700 | H36: Aprovado | L36: =TEXT($C36,"dd.mm") & " -Ped " & D36 & " -" & F36 & " -R$" & G36 & IF(LEN(TRIM(I36))=0, "", " -NF " & TRIM(I36)) -> 04.11 -Ped 047263 -JORGE LUIZ 2 COURIER -R$700
A37: Frete Peças | B37: GRPVA | C37: 45965 | D37: 047525 | E37: 051496564 | F37: MARCOS D COURIER | G37: 400 | H37: Aprovado | K37: Levar peça na Propriedade do cliente | L37: =TEXT($C37,"dd.mm") & " -Ped " & D37 & " -" & F37 & " -R$" & G37 & IF(LEN(TRIM(I37))=0, "", " -NF " & TRIM(I37)) -> 04.11 -Ped 047525 -MARCOS D COURIER -R$400
A38: Frete Peças | B38: IRATI | C38: 45966 | D38: 047328 | E38: 031370636 | F38: JORGE LUIZ 2 COURIER | G38: 180 | H38: Aprovado | K38: entrega de peça cliente Paulo Roberto Soczek Dzierwa | L38: =TEXT($C38,"dd.mm") & " -Ped " & D38 & " -" & F38 & " -R$" & G38 & IF(LEN(TRIM(I38))=0, "", " -NF " & TRIM(I38)) -> 05.11 -Ped 047328 -JORGE LUIZ 2 COURIER -R$180
A39: Manutenção VW | B39: PG | C39: 45967 | D39: 047553 | E39: 050435638 | F39: ANDREANI - MT | G39: 500 | H39: Aguardando | K39: Diagnóstico e testes via aparelho - VW | L39: =TEXT($C39,"dd.mm") & " -Ped " & D39 & " -" & F39 & " -R$" & G39 & IF(LEN(TRIM(I39))=0, "", " -NF " & TRIM(I39)) -> 06.11 -Ped 047553 -ANDREANI - MT -R$500
A40: Manutenção VW | B40: PG | C40: 45967 | D40: 047553 | E40: 050435638 | F40: ANDREANI - MT | G40: 397 | H40: Aguardando | K40: Conector e sensor de rotação e tomada - VW | L40: =TEXT($C40,"dd.mm") & " -Ped " & D40 & " -" & F40 & " -R$" & G40 & IF(LEN(TRIM(I40))=0, "", " -NF " & TRIM(I40)) -> 06.11 -Ped 047553 -ANDREANI - MT -R$397
A41: Frete Peças | B41: GRPVA | C41: 45968 | D41: 047527 | E41: 051496564 | F41: MARCOS D COURIER | G41: 420 | H41: Aprovado | K41: Peça de GRPVA para PG | L41: =TEXT($C41,"dd.mm") & " -Ped " & D41 & " -" & F41 & " -R$" & G41 & IF(LEN(TRIM(I41))=0, "", " -NF " & TRIM(I41)) -> 07.11 -Ped 047527 -MARCOS D COURIER -R$420
A42: Frete Peças | B42: PRUDE | C42: 45971 | D42: 047550 | E42: 031370636 | F42: JORGE LUIZ 2 COURIER | G42: 700 | H42: Aguardando | L42: =TEXT($C42,"dd.mm") & " -Ped " & D42 & " -" & F42 & " -R$" & G42 & IF(LEN(TRIM(I42))=0, "", " -NF " & TRIM(I42)) -> 10.11 -Ped 047550 -JORGE LUIZ 2 COURIER -R$700
A43: Frete Peças | B43: GRPVA | C43: 45971 | D43: 047525 | E43: 051496564 | F43: MARCOS D COURIER | G43: 250 | H43: Aprovado | K43: 1. levar peças para Bituruna Pr Cliente Jean Carlos de Bastiane | L43: =TEXT($C43,"dd.mm") & " -Ped " & D43 & " -" & F43 & " -R$" & G43 & IF(LEN(TRIM(I43))=0, "", " -NF " & TRIM(I43)) -> 10.11 -Ped 047525 -MARCOS D COURIER -R$250
L44: =TEXT($C44,"dd.mm") & " -Ped " & D44 & " -" & F44 & " -R$" & G44 & IF(LEN(TRIM(I44))=0, "", " -NF " & TRIM(I44)) -> 00.01 -Ped - -R$
L45: =TEXT($C45,"dd.mm") & " -Ped " & D45 & " -" & F45 & " -R$" & G45 & IF(LEN(TRIM(I45))=0, "", " -NF " & TRIM(I45)) -> 00.01 -Ped - -R$
L46: =TEXT($C46,"dd.mm") & " -Ped " & D46 & " -" & F46 & " -R$" & G46 & IF(LEN(TRIM(I46))=0, "", " -NF " & TRIM(I46)) -> 00.01 -Ped - -R$
L47: =TEXT($C47,"dd.mm") & " -Ped " & D47 & " -" & F47 & " -R$" & G47 & IF(LEN(TRIM(I47))=0, "", " -NF " & TRIM(I47)) -> 00.01 -Ped - -R$

Sheet UTIL
A1: N | B1: NOME | C1: SIG | D1: CHA | E1: MOD | F1: A | G1: C | H1: L MIN | I1: L MAX | J1: PESO | K1: SOLICITAÇÕES | L1: DIMENSÕES | N1: CÓD | O1: CNPJ/CPF | P1: Razao Social | Q1: N Fantasia | R1: Home-Page | S1: FORNECEDORES | U1: 1 | V1: MacPonta AGRO – 00.702.079/0001-00 | W1: 010101 | Y1: CÓD | Z1: PRODUTO
A2: 1 | B2: TRATOR 3000 | C2: TR | D2: 3036 | E2: 3036EN | F2: 2.28 | G2: 3.1 | H2: 1 | I2: 1.57 | J2: 1200 | K2: ="A:"&TEXT(F2,"0,00")&" x C:"&TEXT(G2,"0,00")&" x L:"&TEXT(H2,"0,00")&"-"&TEXT(I2,"0,00")&" x P:"&TEXT(J2,"0.00")&"kg" -> A:2,28 x C:3,10 x L:1,00-1,57 x P:1.200kg | N2: ="0"&LEFT(TEXT(SUBSTITUTE(SUBSTITUTE(SUBSTITUTE(O2,".",""),"/",""),"-",""),"00000000000000"),8) -> 000428307 | O2: 428307001917 | P2: EXPRESSO SAO MIGUEL LTDA | Q2: EXPRESSO SAO MIGUEL | R2: LOG - ASSIS SP | V2: Ponta Grossa PR– Av. Sen. Flávio Carvalho Guimarães, 2100 - Boa Vista, 84072-190 | Y2: MC_016 | Z2: Frete Máquinas
A3: 1 | B3: TRATOR 5000 | C3: TR | D3: 5060 | E3: 5060E | F3: 2.6 | G3: 4.08 | H3: 1.45 | I3: 2 | J3: 5100 | K3: ="A:"&TEXT(F3,"0,00")&" x C:"&TEXT(G3,"0,00")&" x L:"&TEXT(H3,"0,00")&"-"&TEXT(I3,"0,00")&" x P:"&TEXT(J3,"0.00")&"kg" -> A:2,60 x C:4,08 x L:1,45-2,00 x P:5.100kg | N3: ="0"&LEFT(TEXT(SUBSTITUTE(SUBSTITUTE(SUBSTITUTE(O3,".",""),"/",""),"-",""),"00000000000000"),8) -> 056953013 | O3: 56953013000130 | P3: NNJOTRANS TRANSPORTES LTDA | Q3: CARGADEDICADA TRANS | R3: LOG - CURITIBA PR | U3: 2 | V3: MacPonta AGRO – 00.702.079/0002-83 | W3: 010102 | Y3: MC_017 | Z3: Frete Peças
A4: 1 | B4: TRATOR 5000 | C4: TR | D4: 5060 | E4: 5060EN | F4: 2.38 | G4: 4.08 | H4: 1.44 | I4: 1.88 | J4: 2710 | K4: ="A:"&TEXT(F4,"0,00")&" x C:"&TEXT(G4,"0,00")&" x L:"&TEXT(H4,"0,00")&"-"&TEXT(I4,"0,00")&" x P:"&TEXT(J4,"0.00")&"kg" -> A:2,38 x C:4,08 x L:1,44-1,88 x P:2.710kg | N4: ="0"&LEFT(TEXT(SUBSTITUTE(SUBSTITUTE(SUBSTITUTE(O4,".",""),"/",""),"-",""),"00000000000000"),8) -> 060968275 | O4: 60968275000145 | P4: 60.968.275 MAYCON JOSE CAMARGO DE OLIVEIRA | Q4: MAYCON TRANSPORTES | R4: LOG - CARAMBEI PR | V4: Castro PR–Av. Pref. Ronie Cardoso, 800 - Jardim das Araucarias, 84174-105 | Y4: MC_019 | Z4: Compra de Peças para Manutenção
A5: 1 | B5: TRATOR 5000 | C5: TR | D5: 5060 | E5: 5080EN | F5: 2.38 | G5: 4.08 | H5: 1.44 | I5: 1.88 | J5: 2710 | K5: ="A:"&TEXT(F5,"0,00")&" x C:"&TEXT(G5,"0,00")&" x L:"&TEXT(H5,"0,00")&"-"&TEXT(I5,"0,00")&" x P:"&TEXT(J5,"0.00")&"kg" -> A:2,38 x C:4,08 x L:1,44-1,88 x P:2.710kg | N5: ="0"&LEFT(TEXT(SUBSTITUTE(SUBSTITUTE(SUBSTITUTE(O5,".",""),"/",""),"-",""),"00000000000000"),8) -> 000428307 | O5: 428307001240 | P5: EXPRESSO SAO MIGUEL | Q5: EXPRESSO SAO MIGUEL | R5: LOG - ALTA FLORESTA DOESTE RO | U5: 3 | V5: MacPonta AGRO –00.702.079/0003-64 | W5: 010103 | Y5: SV_019 | Z5: Serviço de Manutenção
A6: 1 | B6: TRATOR 5000 | C6: TR | D6: 5070 | E6: 5070E | F6: 2.6 | G6: 4.08 | H6: 1.45 | I6: 2 | J6: 5100 | K6: ="A:"&TEXT(F6,"0,00")&" x C:"&TEXT(G6,"0,00")&" x L:"&TEXT(H6,"0,00")&"-"&TEXT(I6,"0,00")&" x P:"&TEXT(J6,"0.00")&"kg" -> A:2,60 x C:4,08 x L:1,45-2,00 x P:5.100kg | N6: ="0"&LEFT(TEXT(SUBSTITUTE(SUBSTITUTE(SUBSTITUTE(O6,".",""),"/",""),"-",""),"00000000000000"),8) -> 000428307 | O6: 428307001321 | P6: EXPRESSO SAO MIGUEL | Q6: EXPRESSO SAO MIGUEL | R6: LOG - ALTA FLORESTA DOESTE RO | V6: Irati PR– Rua Eduardo Van Der Larrs, S/N, Km 237 - Nhapindazal, 84500-536 | Y6: SV_046_0010 | Z6: Serviço de Munck | AA6: 511010601026
A7: 1 | B7: TRATOR 5000 | C7: TR | D7: 5078 | E7: 5078E | F7: 2.77 | G7: 4.17 | H7: 1.45 | I7: 2 | J7: 5100 | K7: ="A:"&TEXT(F7,"0,00")&" x C:"&TEXT(G7,"0,00")&" x L:"&TEXT(H7,"0,00")&"-"&TEXT(I7,"0,00")&" x P:"&TEXT(J7,"0.00")&"kg" -> A:2,77 x C:4,17 x L:1,45-2,00 x P:5.100kg | N7: ="0"&LEFT(TEXT(SUBSTITUTE(SUBSTITUTE(SUBSTITUTE(O7,".",""),"/",""),"-",""),"00000000000000"),8) -> 000428307 | O7: 428307000279 | P7: EXPRESSO SAO MIGUEL | Q7: EXPRESSO SAO MIGUEL | R7: LOG - SÃO LEOPOLDO RS | U7: 4 | V7: MacPonta AGRO – 00.702.079/0004-45 | W7: 010104 | Y7: SV_046 | Z7: Serviço de Terceiro (em geral)
A8: 1 | B8: TRATOR 5000 | C8: TR | D8: 5080 | E8: 5080E | F8: 2.6 | G8: 4.08 | H8: 1.45 | I8: 2 | J8: 5100 | K8: ="A:"&TEXT(F8,"0,00")&" x C:"&TEXT(G8,"0,00")&" x L:"&TEXT(H8,"0,00")&"-"&TEXT(I8,"0,00")&" x P:"&TEXT(J8,"0.00")&"kg" -> A:2,60 x C:4,08 x L:1,45-2,00 x P:5.100kg | N8: ="0"&LEFT(TEXT(SUBSTITUTE(SUBSTITUTE(SUBSTITUTE(O8,".",""),"/",""),"-",""),"00000000000000"),8) -> 000428307 | O8: 428307000864 | P8: EXPRESSO SAO MIGUEL LTDA | Q8: EXPRESSO SAO MIGUEL | R8: LOG - BLUMENAU SC | V8: Arapoti PR– PR-092, 231, 84990-000 | Y8: CÓD | Z8: CENTRO DE CUSTO
A9: 1 | B9: TRATOR 5000 | C9: TR | D9: 5090 | E9: 5090E | F9: 2.77 | G9: 4.17 | H9: 1.45 | I9: 2 | J9: 5100 | K9: ="A:"&TEXT(F9,"0,00")&" x C:"&TEXT(G9,"0,00")&" x L:"&TEXT(H9,"0,00")&"-"&TEXT(I9,"0,00")&" x P:"&TEXT(J9,"0.00")&"kg" -> A:2,77 x C:4,17 x L:1,45-2,00 x P:5.100kg | N9: ="0"&LEFT(TEXT(SUBSTITUTE(SUBSTITUTE(SUBSTITUTE(O9,".",""),"/",""),"-",""),"00000000000000"),8) -> 000428307 | O9: 428307000600 | P9: EXPRESSO SAO MIGUEL LTDA | Q9: EXPRESSO SAO MIGUEL | R9: LOG - CAXIAS DO SUL RS | U9: 5 | V9: MacPonta AGRO – 00.702.079/0005-26 | W9: 010105 | Y9: 101001 | Z9: Novos – Frete Máquinas e Manutenção
A10: 1 | B10: TRATOR 6000 | C10: TR | D10: 6100 | E10: 6100J | F10: 2.72 | G10: 4.56 | H10: 2.5 | I10: 3.3 | J10: 5600 | K10: ="A:"&TEXT(F10,"0,00")&" x C:"&TEXT(G10,"0,00")&" x L:"&TEXT(H10,"0,00")&"-"&TEXT(I10,"0,00")&" x P:"&TEXT(J10,"0.00")&"kg" -> A:2,72 x C:4,56 x L:2,50-3,30 x P:5.600kg | N10: ="0"&LEFT(TEXT(SUBSTITUTE(SUBSTITUTE(SUBSTITUTE(O10,".",""),"/",""),"-",""),"00000000000000"),8) -> 000428307 | O10: 428307000198 | P10: EXPRESSO SAO MIGUEL LTDA | Q10: EXPRESSO SAO MIGUEL | R10: LOG - CHAPECO SC | V10: Guarapuava PR– Rodovia BR 277, Km 347 - Jardim das Americas, 85031-350 | Y10: 105001 | Z10: Peças Estoque – Frete Peças
A11: 1 | B11: TRATOR 6000 | C11: TR | D11: 6115 | E11: 6115J | F11: 2.72 | G11: 4.56 | H11: 2.6 | I11: 3.3 | J11: 6300 | K11: ="A:"&TEXT(F11,"0,00")&" x C:"&TEXT(G11,"0,00")&" x L:"&TEXT(H11,"0,00")&"-"&TEXT(I11,"0,00")&" x P:"&TEXT(J11,"0.00")&"kg" -> A:2,72 x C:4,56 x L:2,60-3,30 x P:6.300kg | N11: ="0"&LEFT(TEXT(SUBSTITUTE(SUBSTITUTE(SUBSTITUTE(O11,".",""),"/",""),"-",""),"00000000000000"),8) -> 000428307 | O11: 428307001674 | P11: EXPRESSO SAO MIGUEL LTDA | Q11: EXPRESSO SAO MIGUEL | R11: LOG - MARINGA PR | U11: 6 | V11: MacPonta AGRO – 00.702.079/0006-07 | W11: 010106 | Y11: 105003 | Z11: Peças Comercial – Frete (Novos, CTE; entre lojas ou para clientes, motoboy e etc)
A12: 1 | B12: TRATOR 6000 | C12: TR | D12: 6125 | E12: 6125J | F12: 2.72 | G12: 4.56 | H12: 2.7 | I12: 3.35 | J12: 6800 | K12: ="A:"&TEXT(F12,"0,00")&" x C:"&TEXT(G12,"0,00")&" x L:"&TEXT(H12,"0,00")&"-"&TEXT(I12,"0,00")&" x P:"&TEXT(J12,"0.00")&"kg" -> A:2,72 x C:4,56 x L:2,70-3,35 x P:6.800kg | N12: ="0"&LEFT(TEXT(SUBSTITUTE(SUBSTITUTE(SUBSTITUTE(O12,".",""),"/",""),"-",""),"00000000000000"),8) -> 000428307 | O12: 428307000350 | P12: EXPRESSO SAO MIGUEL LTDA | Q12: EXPRESSO SAO MIGUEL | R12: LOG - PORTO ALEGRE RS | V12: Prudentópolis PR– Rua 12 de Outubro, 21 - Vila Iguaçu, 84400-000 | Y12: 110002 | Z12: Serviços – Frete Peças, Serviço de Munck
A13: 1 | B13: TRATOR 6000 | C13: TR | D13: 6135 | E13: 6135J | F13: 2.74 | G13: 4.92 | H13: 2.87 | I13: 3.45 | J13: 7200 | K13: ="A:"&TEXT(F13,"0,00")&" x C:"&TEXT(G13,"0,00")&" x L:"&TEXT(H13,"0,00")&"-"&TEXT(I13,"0,00")&" x P:"&TEXT(J13,"0.00")&"kg" -> A:2,74 x C:4,92 x L:2,87-3,45 x P:7.200kg | N13: ="0"&LEFT(TEXT(SUBSTITUTE(SUBSTITUTE(SUBSTITUTE(O13,".",""),"/",""),"-",""),"00000000000000"),8) -> 000428307 | O13: 428307000430 | P13: EXPRESSO SAO MIGUEL LTDA | Q13: EXPRESSO SAO MIGUEL | R13: LOG - REALEZA MG | U13: 7 | V13: MacPonta AGRO – 00.702.079/0007-98 | W13: 010107 | Y13: 101003 | Z13: Usados – Frete Máquinas, Serviço de Munck e Serviço de Terceiros
A14: 1 | B14: TRATOR 6000 | C14: TR | D14: 6135 | E14: 6135M | F14: 2.28 | G14: 4.56 | H14: 2.87 | I14: 3.45 | J14: 7500 | K14: ="A:"&TEXT(F14,"0,00")&" x C:"&TEXT(G14,"0,00")&" x L:"&TEXT(H14,"0,00")&"-"&TEXT(I14,"0,00")&" x P:"&TEXT(J14,"0.00")&"kg" -> A:2,28 x C:4,56 x L:2,87-3,45 x P:7.500kg | N14: ="0"&LEFT(TEXT(SUBSTITUTE(SUBSTITUTE(SUBSTITUTE(O14,".",""),"/",""),"-",""),"00000000000000"),8) -> 000428307 | O14: 428307000783 | P14: EXPRESSO SAO MIGUEL LTDA | Q14: EXPRESSO SAO MIGUEL | R14: LOG - SÃO CRISTOVÃO DO SUL SC | V14: Quedas do Iguaçu PR– Av. Ipê, 1495 - Centro, 85460-000 | Y14: 115004 | Z14: quando for assunto relacionado a AP agricultura de precisão, dpto.
A15: 1 | B15: TRATOR 6000 | C15: TR | D15: 6150 | E15: 6150J | F15: 2.86 | G15: 4.96 | H15: 2.7 | I15: 3.3 | J15: 7800 | K15: ="A:"&TEXT(F15,"0,00")&" x C:"&TEXT(G15,"0,00")&" x L:"&TEXT(H15,"0,00")&"-"&TEXT(I15,"0,00")&" x P:"&TEXT(J15,"0.00")&"kg" -> A:2,86 x C:4,96 x L:2,70-3,30 x P:7.800kg | N15: ="0"&LEFT(TEXT(SUBSTITUTE(SUBSTITUTE(SUBSTITUTE(O15,".",""),"/",""),"-",""),"00000000000000"),8) -> 000428307 | O15: 428307000511 | P15: EXPRESSO SAO MIGUEL LTDA | Q15: EXPRESSO SAO MIGUEL | R15: LOG - SARANDI RS | U15: 8 | V15: MacPonta AGRO – 00.702.079/0008-79 | W15: 010108 | Y15: 120007 | Z15: FACILITIES quando for algo a manutenção de prédio ou reparações de predio.
A16: 1 | B16: TRATOR 6000 | C16: TR | D16: 6150 | E16: 6150M | F16: 2.93 | G16: 4.65 | H16: 2.7 | I16: 3.3 | J16: 8500 | K16: ="A:"&TEXT(F16,"0,00")&" x C:"&TEXT(G16,"0,00")&" x L:"&TEXT(H16,"0,00")&"-"&TEXT(I16,"0,00")&" x P:"&TEXT(J16,"0.00")&"kg" -> A:2,93 x C:4,65 x L:2,70-3,30 x P:8.500kg | N16: ="0"&LEFT(TEXT(SUBSTITUTE(SUBSTITUTE(SUBSTITUTE(O16,".",""),"/",""),"-",""),"00000000000000"),8) -> 000428307 | O16: 428307001160 | P16: EXPRESSO SAO MIGUEL S/A | Q16: EXPRESSO SAO MIGUEL | R16: LOG - PALHOÇA SC | V16: Tibagi PR– Av. Manoel das Dores, 891 - Centro, 84300-000 | Y16: 120006 | Z16: AET, DNIT, DER - CC DE OPERAÇÕES (GERAL)
A17: 1 | B17: TRATOR 6000 | C17: TR | D17: 6170 | E17: 6170J | F17: 2.93 | G17: 5.42 | H17: 2.74 | I17: 3.4 | J17: 8500 | K17: ="A:"&TEXT(F17,"0,00")&" x C:"&TEXT(G17,"0,00")&" x L:"&TEXT(H17,"0,00")&"-"&TEXT(I17,"0,00")&" x P:"&TEXT(J17,"0.00")&"kg" -> A:2,93 x C:5,42 x L:2,74-3,40 x P:8.500kg | N17: ="0"&LEFT(TEXT(SUBSTITUTE(SUBSTITUTE(SUBSTITUTE(O17,".",""),"/",""),"-",""),"00000000000000"),8) -> 000428307 | O17: 428307001089 | P17: EXPRESSO SAO MIGUEL SA | Q17: EXPRESSO SAO MIGUEL | R17: LOG - JOINVILLE SC | W17: RATEIO | Y17: ÁREA | Z17: GRUPO APROVAÇÃO
A18: 1 | B18: TRATOR 6000 | C18: TR | D18: 6170 | E18: 6170M | F18: 3.3 | G18: 5.24 | H18: 2.74 | I18: 3.4 | J18: 9550 | K18: ="A:"&TEXT(F18,"0,00")&" x C:"&TEXT(G18,"0,00")&" x L:"&TEXT(H18,"0,00")&"-"&TEXT(I18,"0,00")&" x P:"&TEXT(J18,"0.00")&"kg" -> A:3,30 x C:5,24 x L:2,74-3,40 x P:9.550kg | N18: ="0"&LEFT(TEXT(SUBSTITUTE(SUBSTITUTE(SUBSTITUTE(O18,".",""),"/",""),"-",""),"00000000000000"),8) -> 082332735 | O18: 82332735000500 | P18: DUNAPETROL C.D.P CONT 7 | Q18: POSTO SHELL FRANQUIA | R18: LOG - PONTA GROSSA PR | W18: 511010301003 | Y18: Logística | Z18: 000016 | AA18: 000001
A19: 1 | B19: TRATOR 6000 | C19: TR | D19: 6190 | E19: 6190J | F19: 2.98 | G19: 5.42 | H19: 2.95 | I19: 3.6 | J19: 9800 | K19: ="A:"&TEXT(F19,"0,00")&" x C:"&TEXT(G19,"0,00")&" x L:"&TEXT(H19,"0,00")&"-"&TEXT(I19,"0,00")&" x P:"&TEXT(J19,"0.00")&"kg" -> A:2,98 x C:5,42 x L:2,95-3,60 x P:9.800kg | N19: ="0"&LEFT(TEXT(SUBSTITUTE(SUBSTITUTE(SUBSTITUTE(O19,".",""),"/",""),"-",""),"00000000000000"),8) -> 082332735 | O19: 82332735000420 | P19: DUNAPETROL COM E DERIV DE PETROL LTDA II | Q19: POSTO SHELL FRANQUIA | R19: LOG - PONTA GROSSA PR | Y19: Compras | Z19: 000012 | AA19: Retorno: 161
A20: 1 | B20: TRATOR 6000 | C20: TR | D20: 6190 | E20: 6190M | F20: 3.3 | G20: 5.24 | H20: 2.95 | I20: 3.6 | J20: 10650 | K20: ="A:"&TEXT(F20,"0,00")&" x C:"&TEXT(G20,"0,00")&" x L:"&TEXT(H20,"0,00")&"-"&TEXT(I20,"0,00")&" x P:"&TEXT(J20,"0.00")&"kg" -> A:3,30 x C:5,24 x L:2,95-3,60 x P:10.650kg | N20: ="0"&LEFT(TEXT(SUBSTITUTE(SUBSTITUTE(SUBSTITUTE(O20,".",""),"/",""),"-",""),"00000000000000"),8) -> 082332735 | O20: 82332735000268 | P20: DUNAPETROL COM E DERIV DE PETROLEO LTDA | Q20: POSTO SHELL FRANQUIA | R20: LOG - PONTA GROSSA PR | V20: PARA CADASTRAR FORNECEDOR | Y20: Tipo | Z20: Operação, Natureza e Chave
A21: 1 | B21: TRATOR 6000 | C21: TR | D21: 6210 | E21: 6210J | F21: 2.93 | G21: 5.42 | H21: 2.92 | I21: 3.6 | J21: 11000 | K21: ="A:"&TEXT(F21,"0,00")&" x C:"&TEXT(G21,"0,00")&" x L:"&TEXT(H21,"0,00")&"-"&TEXT(I21,"0,00")&" x P:"&TEXT(J21,"0.00")&"kg" -> A:2,93 x C:5,42 x L:2,92-3,60 x P:11.000kg | N21: ="0"&LEFT(TEXT(SUBSTITUTE(SUBSTITUTE(SUBSTITUTE(O21,".",""),"/",""),"-",""),"00000000000000"),8) -> 082332735 | O21: 82332735000853 | P21: DUNAPETROL COM E DERIV DE PETROLEO LTDA | Q21: POSTO SHELL FRANQUIA | R21: LOG - PONTA GROSSA PR | V21: CNPJ: | Y21: DACTE - CTE - Verificar | Z21: Operação: 92 e Natureza: 2130 e Chave:X
A22: 1 | B22: TRATOR 6000 | C22: TR | D22: 6210 | E22: 6210M | F22: 3.31 | G22: 5.02 | H22: 2.92 | I22: 3.6 | J22: 11750 | K22: ="A:"&TEXT(F22,"0,00")&" x C:"&TEXT(G22,"0,00")&" x L:"&TEXT(H22,"0,00")&"-"&TEXT(I22,"0,00")&" x P:"&TEXT(J22,"0.00")&"kg" -> A:3,31 x C:5,02 x L:2,92-3,60 x P:11.750kg | N22: ="0"&LEFT(TEXT(SUBSTITUTE(SUBSTITUTE(SUBSTITUTE(O22,".",""),"/",""),"-",""),"00000000000000"),8) -> 082332735 | O22: 82332735000349 | P22: DUNAPETROL COM.E DERIV.DE PETROLEO LTDA | Q22: POSTO SHELL FRANQUIA | R22: LOG - PONTA GROSSA PR | V22: Razão Social: | Y22: NFS - NFS - N | Z22: Operação: 87 e Natureza: 2130 e Chave:-
A23: 1 | B23: TRATOR 7000 | C23: TR | D23: 7200 | E23: 7200J | F23: 3.17 | G23: 5.82 | H23: 2.43 | I23: 3 | J23: 11400 | K23: ="A:"&TEXT(F23,"0,00")&" x C:"&TEXT(G23,"0,00")&" x L:"&TEXT(H23,"0,00")&"-"&TEXT(I23,"0,00")&" x P:"&TEXT(J23,"0.00")&"kg" -> A:3,17 x C:5,82 x L:2,43-3,00 x P:11.400kg | N23: ="0"&LEFT(TEXT(SUBSTITUTE(SUBSTITUTE(SUBSTITUTE(O23,".",""),"/",""),"-",""),"00000000000000"),8) -> 017489822 | O23: 17489822000180 | P23: AXT LOPES E CIA LTDA | Q23: AXT LOPES - MT | R23: LOG - PONTA GROSSA PR | V23: Nome Fantasia: | Y23: DANFE - SPED - Verificar | Z23: Operação: 51 e Natureza: 2110 e Chave:X
A24: 1 | B24: TRATOR 7000 | C24: TR | D24: 7215 | E24: 7215J | F24: 3.17 | G24: 5.82 | H24: 2.43 | I24: 3 | J24: 11800 | K24: ="A:"&TEXT(F24,"0,00")&" x C:"&TEXT(G24,"0,00")&" x L:"&TEXT(H24,"0,00")&"-"&TEXT(I24,"0,00")&" x P:"&TEXT(J24,"0.00")&"kg" -> A:3,17 x C:5,82 x L:2,43-3,00 x P:11.800kg | N24: ="0"&LEFT(TEXT(SUBSTITUTE(SUBSTITUTE(SUBSTITUTE(O24,".",""),"/",""),"-",""),"00000000000000"),8) -> 006208105 | O24: 6208105001431 | P24: ATRHOL - AGENCIA E TRANSPORTES HORIZONTI | Q24: ATRHOL TRANSPORTES | R24: LOG - LAGES SC | V24: Endereço (Rua e Bairro):
A25: 1 | B25: TRATOR 7000 | C25: TR | D25: 7230 | E25: 7230J | F25: 3.17 | G25: 5.82 | H25: 2.43 | I25: 3 | J25: 12650 | K25: ="A:"&TEXT(F25,"0,00")&" x C:"&TEXT(G25,"0,00")&" x L:"&TEXT(H25,"0,00")&"-"&TEXT(I25,"0,00")&" x P:"&TEXT(J25,"0.00")&"kg" -> A:3,17 x C:5,82 x L:2,43-3,00 x P:12.650kg | N25: ="0"&LEFT(TEXT(SUBSTITUTE(SUBSTITUTE(SUBSTITUTE(O25,".",""),"/",""),"-",""),"00000000000000"),8) -> 006208105 | O25: 6208105000117 | P25: ATRHOL AGENCIA E TRANSP. HORIZONTINA LTA | Q25: ATRHOL TRANSPORTES | R25: LOG - HORIZONTINA RS | V25: Estado:
A26: 1 | B26: TRATOR 8000 | C26: TR | D26: 8250 | E26: 8250R | F26: 3.3 | G26: 6.04 | H26: 2.45 | I26: 3.3 | J26: 13325 | K26: ="A:"&TEXT(F26,"0,00")&" x C:"&TEXT(G26,"0,00")&" x L:"&TEXT(H26,"0,00")&"-"&TEXT(I26,"0,00")&" x P:"&TEXT(J26,"0.00")&"kg" -> A:3,30 x C:6,04 x L:2,45-3,30 x P:13.325kg | N26: ="0"&LEFT(TEXT(SUBSTITUTE(SUBSTITUTE(SUBSTITUTE(O26,".",""),"/",""),"-",""),"00000000000000"),8) -> 006208105 | O26: 6208105001008 | P26: ATRHOL AGENCIA E TRANSP.HORIZONTINA LTDA | Q26: ATRHOL TRANSPORTES | R26: LOG - INDAIATUBA SP | V26: Município: | Y26: LOGIN PRINCESA TRANSP
A27: 1 | B27: TRATOR 8000 | C27: TR | D27: 8270 | E27: 8270R | F27: 3.3 | G27: 6.04 | H27: 2.45 | I27: 3.3 | J27: 14700 | K27: ="A:"&TEXT(F27,"0,00")&" x C:"&TEXT(G27,"0,00")&" x L:"&TEXT(H27,"0,00")&"-"&TEXT(I27,"0,00")&" x P:"&TEXT(J27,"0.00")&"kg" -> A:3,30 x C:6,04 x L:2,45-3,30 x P:14.700kg | N27: ="0"&LEFT(TEXT(SUBSTITUTE(SUBSTITUTE(SUBSTITUTE(O27,".",""),"/",""),"-",""),"00000000000000"),8) -> 006208105 | O27: 6208105000206 | P27: ATRHOL AGENCIA E TRANSPORTES HORIZONTINA | Q27: ATRHOL TRANSPORTES | R27: LOG - CATALAO GO | V27: CEP: | Y27: Cidade | Z27: CNPJ | AA27: Código
A28: 1 | B28: TRATOR 8000 | C28: TR | D28: 8295 | E28: 8295R | F28: 3.3 | G28: 6.04 | H28: 2.45 | I28: 3.3 | J28: 16192 | K28: ="A:"&TEXT(F28,"0,00")&" x C:"&TEXT(G28,"0,00")&" x L:"&TEXT(H28,"0,00")&"-"&TEXT(I28,"0,00")&" x P:"&TEXT(J28,"0.00")&"kg" -> A:3,30 x C:6,04 x L:2,45-3,30 x P:16.192kg | N28: ="0"&LEFT(TEXT(SUBSTITUTE(SUBSTITUTE(SUBSTITUTE(O28,".",""),"/",""),"-",""),"00000000000000"),8) -> 006208105 | O28: 6208105000389 | P28: ATRHOL AG. E TRANSP. HORIZONTINA LTDA | Q28: ATRHOL TRANSPORTES | R28: LOG - MONTE NEGRO RS | V28: Telefone Principal: | Y28: PG | Z28: 00702079000100 | AA28: Mac1060#
A29: 1 | B29: TRATOR 8000 | C29: TR | D29: 8320 | E29: 8320R | F29: 3.3 | G29: 6.04 | H29: 2.45 | I29: 3.3 | J29: 17600 | K29: ="A:"&TEXT(F29,"0,00")&" x C:"&TEXT(G29,"0,00")&" x L:"&TEXT(H29,"0,00")&"-"&TEXT(I29,"0,00")&" x P:"&TEXT(J29,"0.00")&"kg" -> A:3,30 x C:6,04 x L:2,45-3,30 x P:17.600kg | N29: ="0"&LEFT(TEXT(SUBSTITUTE(SUBSTITUTE(SUBSTITUTE(O29,".",""),"/",""),"-",""),"00000000000000"),8) -> 006208105 | O29: 6208105000540 | P29: ATRHOL AGENCIA DE TRANSPORTES | Q29: ATRHOL TRANSPORTES | R29: LOG - CANOAS RS | V29: Ins. Estadual: | Y29: CASTRO | Z29: 00702079000283 | AA29: Mac1062#
A30: 1 | B30: TRATOR 8000 | C30: TR | D30: 8345 | E30: 8345R | F30: 3.3 | G30: 6.04 | H30: 2.45 | I30: 3.3 | J30: 18000 | K30: ="A:"&TEXT(F30,"0,00")&" x C:"&TEXT(G30,"0,00")&" x L:"&TEXT(H30,"0,00")&"-"&TEXT(I30,"0,00")&" x P:"&TEXT(J30,"0.00")&"kg" -> A:3,30 x C:6,04 x L:2,45-3,30 x P:18.000kg | N30: ="0"&LEFT(TEXT(SUBSTITUTE(SUBSTITUTE(SUBSTITUTE(O30,".",""),"/",""),"-",""),"00000000000000"),8) -> 019082116 | O30: 19082116000145 | P30: A. C. BRAZ DE LIMA - ME | Q30: MELANCIA TRANSPORTES | R30: LOG - CASTRO PR | V30: E-mail: | Y30: IRATI | Z30: 00702079000364 | AA30: Mac1063#
A31: 1 | B31: TRATOR 8000 | C31: TR | D31: 8370 | E31: 8370R | F31: 3.3 | G31: 6.04 | H31: 2.45 | I31: 3.3 | J31: 18000 | K31: ="A:"&TEXT(F31,"0,00")&" x C:"&TEXT(G31,"0,00")&" x L:"&TEXT(H31,"0,00")&"-"&TEXT(I31,"0,00")&" x P:"&TEXT(J31,"0.00")&"kg" -> A:3,30 x C:6,04 x L:2,45-3,30 x P:18.000kg | N31: ="0"&LEFT(TEXT(SUBSTITUTE(SUBSTITUTE(SUBSTITUTE(O31,".",""),"/",""),"-",""),"00000000000000"),8) -> 080645922 | O31: 80645922000276 | P31: TRANSPORTES BEGNINI LTDA | Q31: BEGNINI TRANSPORTES | R31: LOG - CARAMBEI PR | V31: PIX: | Y31: ARAPOTI | Z31: 00702079000445 | AA31: Mac1064#
A32: 1 | B32: TRATOR 8000 | C32: TR | D32: 8400 | E32: 8400R | F32: 3.3 | G32: 6.04 | H32: 2.45 | I32: 3.3 | J32: 18000 | K32: ="A:"&TEXT(F32,"0,00")&" x C:"&TEXT(G32,"0,00")&" x L:"&TEXT(H32,"0,00")&"-"&TEXT(I32,"0,00")&" x P:"&TEXT(J32,"0.00")&"kg" -> A:3,30 x C:6,04 x L:2,45-3,30 x P:18.000kg | N32: ="0"&LEFT(TEXT(SUBSTITUTE(SUBSTITUTE(SUBSTITUTE(O32,".",""),"/",""),"-",""),"00000000000000"),8) -> 053102168 | O32: 53102168000174 | P32: NJOTA TRANSPORTES LTDA | Q32: NJOTA TRANSPORTES | R32: LOG - PINHAIS PR | V32: Forma de pagamento: | Y32: GUARAPUAVA | Z32: 00702079000526 | AA32: Mac1065#
A33: 1 | B33: TRATOR 9000 | C33: TR | D33: 9R 440 | E33: 9R 440 | F33: 3.98 | G33: 8.43 | H33: 3.05 | I33: 4.3 | J33: 20856 | K33: ="A:"&TEXT(F33,"0,00")&" x C:"&TEXT(G33,"0,00")&" x L:"&TEXT(H33,"0,00")&"-"&TEXT(I33,"0,00")&" x P:"&TEXT(J33,"0.00")&"kg" -> A:3,98 x C:8,43 x L:3,05-4,30 x P:20.856kg | N33: ="0"&LEFT(TEXT(SUBSTITUTE(SUBSTITUTE(SUBSTITUTE(O33,".",""),"/",""),"-",""),"00000000000000"),8) -> 056953013 | O33: 56953013000130 | P33: NNJOTRANS TRANSPORTES LTDA | Q33: CARGADEDICADA TRANS | R33: LOG - CURITIBA PR | V33: Nome Representante: | Y33: PRUDENTOPOLIS | Z33: 00702079000607 | AA33: Mac1066#
A34: 1 | B34: TRATOR 9000 | C34: TR | D34: 9R 490 | E34: 9R 490 | F34: 3.98 | G34: 8.43 | H34: 3.05 | I34: 4.3 | J34: 20856 | K34: ="A:"&TEXT(F34,"0,00")&" x C:"&TEXT(G34,"0,00")&" x L:"&TEXT(H34,"0,00")&"-"&TEXT(I34,"0,00")&" x P:"&TEXT(J34,"0.00")&"kg" -> A:3,98 x C:8,43 x L:3,05-4,30 x P:20.856kg | N34: ="0"&LEFT(TEXT(SUBSTITUTE(SUBSTITUTE(SUBSTITUTE(O34,".",""),"/",""),"-",""),"00000000000000"),8) -> 020110520 | O34: 20110520000164 | P34: METAL F.A ALMEIDA E FRAGULHA LTDA | Q34: METAL F A - MT | R34: LOG - PONTA GROSSA PR | V34: Form. Pgto.: 45 | Y34: QUEDAS | Z34: 00702079000798 | AA34: Mac1067#
A35: 1 | B35: TRATOR 9000 | C35: TR | D35: 9R 540 | E35: 9R 540 | F35: 3.98 | G35: 8.43 | H35: 3.05 | I35: 4.3 | J35: 20856 | K35: ="A:"&TEXT(F35,"0,00")&" x C:"&TEXT(G35,"0,00")&" x L:"&TEXT(H35,"0,00")&"-"&TEXT(I35,"0,00")&" x P:"&TEXT(J35,"0.00")&"kg" -> A:3,98 x C:8,43 x L:3,05-4,30 x P:20.856kg | N35: ="0"&LEFT(TEXT(SUBSTITUTE(SUBSTITUTE(SUBSTITUTE(O35,".",""),"/",""),"-",""),"00000000000000"),8) -> 050435638 | O35: 50435638000123 | P35: ANDREANI AUTO ELETRICA LTDA | Q35: ANDREANI - MT | R35: LOG - PONTA GROSSA PR | V35: Cond. Pagto: 009 ou 002 | Y35: TIBAGI | Z35: 00702079000879 | AA35: Mac1068#
A36: 1 | B36: TRATOR 9000 | C36: TR | D36: 9R 590 | E36: 9R 590 | F36: 3.98 | G36: 8.43 | H36: 3.05 | I36: 4.3 | J36: 20856 | K36: ="A:"&TEXT(F36,"0,00")&" x C:"&TEXT(G36,"0,00")&" x L:"&TEXT(H36,"0,00")&"-"&TEXT(I36,"0,00")&" x P:"&TEXT(J36,"0.00")&"kg" -> A:3,98 x C:8,43 x L:3,05-4,30 x P:20.856kg | N36: ="0"&LEFT(TEXT(SUBSTITUTE(SUBSTITUTE(SUBSTITUTE(O36,".",""),"/",""),"-",""),"00000000000000"),8) -> 055246903 | O36: 55246903000149 | P36: DENISE PENTEADO ANASTACIO ASA EXPRESS | Q36: ASA EXPRESS TRANSP | R36: LOG - CAMPINAS SP | V36: Grp. Tribut.: F01
A37: 1 | B37: TRATOR 9000 | C37: TR | D37: 9R 640 | E37: 9R 640 | F37: 3.98 | G37: 8.43 | H37: 3.05 | I37: 4.3 | J37: 21174 | K37: ="A:"&TEXT(F37,"0,00")&" x C:"&TEXT(G37,"0,00")&" x L:"&TEXT(H37,"0,00")&"-"&TEXT(I37,"0,00")&" x P:"&TEXT(J37,"0.00")&"kg" -> A:3,98 x C:8,43 x L:3,05-4,30 x P:21.174kg | N37: ="0"&LEFT(TEXT(SUBSTITUTE(SUBSTITUTE(SUBSTITUTE(O37,".",""),"/",""),"-",""),"00000000000000"),8) -> 007424946 | O37: 7424946000124 | P37: VAN BEIK E CIA LTDA | Q37: SERIE4 - MT | R37: LOG - PONTA GROSSA PR | V37: Cod. IBGE: ?
A38: 1 | B38: TRATOR 9000 | C38: TR | D38: 9RX 490 | E38: 9RX 490 | F38: 3.71 | G38: 8.55 | H38: 3.05 | I38: 3.96 | J38: 25546 | K38: ="A:"&TEXT(F38,"0,00")&" x C:"&TEXT(G38,"0,00")&" x L:"&TEXT(H38,"0,00")&"-"&TEXT(I38,"0,00")&" x P:"&TEXT(J38,"0.00")&"kg" -> A:3,71 x C:8,55 x L:3,05-3,96 x P:25.546kg | N38: ="0"&LEFT(TEXT(SUBSTITUTE(SUBSTITUTE(SUBSTITUTE(O38,".",""),"/",""),"-",""),"00000000000000"),8) -> 010273940 | O38: 10273940000108 | P38: PECAS E SERVICOS SERIE 4 AUTO MECANICA | Q38: SERIE4 - MT | R38: LOG - PONTA GROSSA PR
A39: 1 | B39: TRATOR 9000 | C39: TR | D39: 9RX 540 | E39: 9RX 540 | F39: 3.71 | G39: 8.71 | H39: 3.05 | I39: 3.96 | J39: 25546 | K39: ="A:"&TEXT(F39,"0,00")&" x C:"&TEXT(G39,"0,00")&" x L:"&TEXT(H39,"0,00")&"-"&TEXT(I39,"0,00")&" x P:"&TEXT(J39,"0.00")&"kg" -> A:3,71 x C:8,71 x L:3,05-3,96 x P:25.546kg | N39: ="0"&LEFT(TEXT(SUBSTITUTE(SUBSTITUTE(SUBSTITUTE(O39,".",""),"/",""),"-",""),"00000000000000"),8) -> 046304055 | O39: 46304055000196 | P39: RUTE MENDES DA LUZ GRICZYNSKI MEI | Q39: GRICZYNSKI TRANSP | R39: LOG - IRATI PR
A40: 1 | B40: TRATOR 9000 | C40: TR | D40: 9RX 590 | E40: 9RX 590 | F40: 3.71 | G40: 8.55 | H40: 3.05 | I40: 3.96 | J40: 25546 | K40: ="A:"&TEXT(F40,"0,00")&" x C:"&TEXT(G40,"0,00")&" x L:"&TEXT(H40,"0,00")&"-"&TEXT(I40,"0,00")&" x P:"&TEXT(J40,"0.00")&"kg" -> A:3,71 x C:8,55 x L:3,05-3,96 x P:25.546kg | N40: ="0"&LEFT(TEXT(SUBSTITUTE(SUBSTITUTE(SUBSTITUTE(O40,".",""),"/",""),"-",""),"00000000000000"),8) -> 061234985 | O40: 61234985014164 | P40: COMERCIAL E IMPORTADORA DE PNEUS LTDA | Q40: CAMPNEUS | R40: LOG - CASCAVEL PR
A41: 1 | B41: TRATOR 9000 | C41: TR | D41: 9RX 640 | E41: 9RX 640 | F41: 3.78 | G41: 8.55 | H41: 3.05 | I41: 3.96 | J41: 25546 | K41: ="A:"&TEXT(F41,"0,00")&" x C:"&TEXT(G41,"0,00")&" x L:"&TEXT(H41,"0,00")&"-"&TEXT(I41,"0,00")&" x P:"&TEXT(J41,"0.00")&"kg" -> A:3,78 x C:8,55 x L:3,05-3,96 x P:25.546kg | N41: ="0"&LEFT(TEXT(SUBSTITUTE(SUBSTITUTE(SUBSTITUTE(O41,".",""),"/",""),"-",""),"00000000000000"),8) -> 007516914 | O41: 7516914000159 | P41: ECO BRASIL BIOENERGIA LTDA | Q41: ECO BRASIL
A42: 2 | B42: COLHEITADEIRA | C42: CA | D42: S430 | E42: S430 | F42: 4.1 | G42: 7.7 | H42: 3.7 | I42: 4.1 | J42: 10600 | K42: ="A:"&TEXT(F42,"0,00")&" x C:"&TEXT(G42,"0,00")&" x L:"&TEXT(H42,"0,00")&"-"&TEXT(I42,"0,00")&" x P:"&TEXT(J42,"0.00")&"kg" -> A:4,10 x C:7,70 x L:3,70-4,10 x P:10.600kg | N42: ="0"&LEFT(TEXT(SUBSTITUTE(SUBSTITUTE(SUBSTITUTE(O42,".",""),"/",""),"-",""),"00000000000000"),8) -> 013809515 | O42: 13809515000189 | P42: S. T. P. COMERCIO DE FERRAMENTAS LTDA | Q42: PROMAQ FERRAMENTAS | R42: LOG - CASTRO PR
A43: 2 | B43: COLHEITADEIRA | C43: CA | D43: S440 | E43: S440 | F43: 4.1 | G43: 7.7 | H43: 3.4 | I43: 4.1 | J43: 11800 | K43: ="A:"&TEXT(F43,"0,00")&" x C:"&TEXT(G43,"0,00")&" x L:"&TEXT(H43,"0,00")&"-"&TEXT(I43,"0,00")&" x P:"&TEXT(J43,"0.00")&"kg" -> A:4,10 x C:7,70 x L:3,40-4,10 x P:11.800kg | N43: ="0"&LEFT(TEXT(SUBSTITUTE(SUBSTITUTE(SUBSTITUTE(O43,".",""),"/",""),"-",""),"00000000000000"),8) -> 006208105 | O43: 6208105001199 | P43: ATRHOL AGENCIA E TRANSP.HORIZONTINA LTDA | Q43: ATRHOL TRANSPORTES | R43: LOG - CURITIBA PR
A44: 2 | B44: COLHEITADEIRA | C44: CA | D44: S470 | E44: S470 | F44: 4.1 | G44: 6.68 | H44: 3.2 | I44: 3.3 | J44: 14000 | K44: ="A:"&TEXT(F44,"0,00")&" x C:"&TEXT(G44,"0,00")&" x L:"&TEXT(H44,"0,00")&"-"&TEXT(I44,"0,00")&" x P:"&TEXT(J44,"0.00")&"kg" -> A:4,10 x C:6,68 x L:3,20-3,30 x P:14.000kg | N44: ="0"&LEFT(TEXT(SUBSTITUTE(SUBSTITUTE(SUBSTITUTE(O44,".",""),"/",""),"-",""),"00000000000000"),8) -> 019442669 | O44: 19442669000161 | P44: GUINCHO ALTERNATIVA PONTA GROSSA LTDA | Q44: GUINCHO ALTERNATIVA | R44: LOG - PONTA GROSSA PR
A45: 2 | B45: COLHEITADEIRA | C45: CA | D45: S550 | E45: S550 | F45: 3.8 | G45: 10 | H45: 3.7 | I45: 4.2 | J45: 15938 | K45: ="A:"&TEXT(F45,"0,00")&" x C:"&TEXT(G45,"0,00")&" x L:"&TEXT(H45,"0,00")&"-"&TEXT(I45,"0,00")&" x P:"&TEXT(J45,"0.00")&"kg" -> A:3,80 x C:10,00 x L:3,70-4,20 x P:15.938kg | N45: ="0"&LEFT(TEXT(SUBSTITUTE(SUBSTITUTE(SUBSTITUTE(O45,".",""),"/",""),"-",""),"00000000000000"),8) -> 085004729 | O45: 85004729000199 | P45: MANARIM IMPRESSAO DIGITAL LTDA | Q45: MANARIM IMPRESSOES | R45: LOG - PONTA GROSSA PR
A46: 2 | B46: COLHEITADEIRA | C46: CA | D46: S660 | E46: S660 | F46: 3.98 | G46: 10.5 | H46: 3.4 | I46: 5.2 | J46: 18599 | K46: ="A:"&TEXT(F46,"0,00")&" x C:"&TEXT(G46,"0,00")&" x L:"&TEXT(H46,"0,00")&"-"&TEXT(I46,"0,00")&" x P:"&TEXT(J46,"0.00")&"kg" -> A:3,98 x C:10,50 x L:3,40-5,20 x P:18.599kg | N46: ="0"&LEFT(TEXT(SUBSTITUTE(SUBSTITUTE(SUBSTITUTE(O46,".",""),"/",""),"-",""),"00000000000000"),8) -> 000428307 | O46: 428307002301 | P46: EXPRESSO SAO MIGUEL S/A | Q46: EXPRESSO SAO MIGUEL | R46: LOG - CURITIBA PR
A47: 2 | B47: COLHEITADEIRA | C47: CA | D47: S670 | E47: S670 | F47: 3.98 | G47: 10.5 | H47: 3.4 | I47: 5.2 | J47: 19226 | K47: ="A:"&TEXT(F47,"0,00")&" x C:"&TEXT(G47,"0,00")&" x L:"&TEXT(H47,"0,00")&"-"&TEXT(I47,"0,00")&" x P:"&TEXT(J47,"0.00")&"kg" -> A:3,98 x C:10,50 x L:3,40-5,20 x P:19.226kg | N47: ="0"&LEFT(TEXT(SUBSTITUTE(SUBSTITUTE(SUBSTITUTE(O47,".",""),"/",""),"-",""),"00000000000000"),8) -> 059354979 | O47: 59354979000149 | P47: GOES E DEGRAF LTDA | Q47: PRESIDENTE PNEUS -MT | R47: LOG - PONTA GROSSA PR
A48: 2 | B48: COLHEITADEIRA | C48: CA | D48: S680 | E48: S680 | F48: 3.98 | G48: 12.1 | H48: 3.5 | I48: 5.43 | J48: 21921 | K48: ="A:"&TEXT(F48,"0,00")&" x C:"&TEXT(G48,"0,00")&" x L:"&TEXT(H48,"0,00")&"-"&TEXT(I48,"0,00")&" x P:"&TEXT(J48,"0.00")&"kg" -> A:3,98 x C:12,10 x L:3,50-5,43 x P:21.921kg | N48: ="0"&LEFT(TEXT(SUBSTITUTE(SUBSTITUTE(SUBSTITUTE(O48,".",""),"/",""),"-",""),"00000000000000"),8) -> 080227796 | O48: 80227796006785 | P48: EXPRESSO PRINCESA DOS CAMPOS | Q48: PRINCESA DOS CAMPOS | R48: LOG - SUMARE SP
A49: 2 | B49: COLHEITADEIRA | C49: CA | D49: S690 | E49: S690 | F49: 3.98 | G49: 12.1 | H49: 3.5 | I49: 5.43 | J49: 22185 | K49: ="A:"&TEXT(F49,"0,00")&" x C:"&TEXT(G49,"0,00")&" x L:"&TEXT(H49,"0,00")&"-"&TEXT(I49,"0,00")&" x P:"&TEXT(J49,"0.00")&"kg" -> A:3,98 x C:12,10 x L:3,50-5,43 x P:22.185kg | N49: ="0"&LEFT(TEXT(SUBSTITUTE(SUBSTITUTE(SUBSTITUTE(O49,".",""),"/",""),"-",""),"00000000000000"),8) -> 040952314 | O49: 40952314000109 | P49: EMANOEL GERY | Q49: EMANOEL TRANSPORTES | R49: LOG - PRUDENTOPOLIS
A50: 2 | B50: COLHEITADEIRA | C50: CA | D50: S760 | E50: S760 | F50: 4 | G50: 10.6 | H50: 3.5 | I50: 5.2 | J50: 18599 | K50: ="A:"&TEXT(F50,"0,00")&" x C:"&TEXT(G50,"0,00")&" x L:"&TEXT(H50,"0,00")&"-"&TEXT(I50,"0,00")&" x P:"&TEXT(J50,"0.00")&"kg" -> A:4,00 x C:10,60 x L:3,50-5,20 x P:18.599kg | N50: ="0"&LEFT(TEXT(SUBSTITUTE(SUBSTITUTE(SUBSTITUTE(O50,".",""),"/",""),"-",""),"00000000000000"),8) -> 044753925 | O50: 44753925000189 | P50: DYEGO DE OLIVEIRA WOLFF TRANSPORTES LTDA | Q50: WOLFF A.S. TRANSP | R50: LOG - TIBAGI PR
A51: 2 | B51: COLHEITADEIRA | C51: CA | D51: S770 | E51: S770 | F51: 4 | G51: 10.5 | H51: 3.5 | I51: 5.2 | J51: 19226 | K51: ="A:"&TEXT(F51,"0,00")&" x C:"&TEXT(G51,"0,00")&" x L:"&TEXT(H51,"0,00")&"-"&TEXT(I51,"0,00")&" x P:"&TEXT(J51,"0.00")&"kg" -> A:4,00 x C:10,50 x L:3,50-5,20 x P:19.226kg | N51: ="0"&LEFT(TEXT(SUBSTITUTE(SUBSTITUTE(SUBSTITUTE(O51,".",""),"/",""),"-",""),"00000000000000"),8) -> 027525938 | O51: 27525938000181 | P51: ESC TRANSPORTES EXPRESS LTDA | Q51: ESC TRANSPORTES | R51: LOG - PONTA GROSSA PR
A52: 2 | B52: COLHEITADEIRA | C52: CA | D52: S780 | E52: S780 | F52: 4 | G52: 12.1 | H52: 3.5 | I52: 5.43 | J52: 21921 | K52: ="A:"&TEXT(F52,"0,00")&" x C:"&TEXT(G52,"0,00")&" x L:"&TEXT(H52,"0,00")&"-"&TEXT(I52,"0,00")&" x P:"&TEXT(J52,"0.00")&"kg" -> A:4,00 x C:12,10 x L:3,50-5,43 x P:21.921kg | N52: ="0"&LEFT(TEXT(SUBSTITUTE(SUBSTITUTE(SUBSTITUTE(O52,".",""),"/",""),"-",""),"00000000000000"),8) -> 078706751 | O52: 78706751000700 | P52: TRANSPEN CARGAS E ENCOMENDAS LTDA | Q52: TRANSPEN CARGAS | R52: LOG - ITAPEVA SP
A53: 2 | B53: COLHEITADEIRA | C53: CA | D53: S790 | E53: S790 | F53: 4 | G53: 12.1 | H53: 3.5 | I53: 5.43 | J53: 22185 | K53: ="A:"&TEXT(F53,"0,00")&" x C:"&TEXT(G53,"0,00")&" x L:"&TEXT(H53,"0,00")&"-"&TEXT(I53,"0,00")&" x P:"&TEXT(J53,"0.00")&"kg" -> A:4,00 x C:12,10 x L:3,50-5,43 x P:22.185kg | N53: ="0"&LEFT(TEXT(SUBSTITUTE(SUBSTITUTE(SUBSTITUTE(O53,".",""),"/",""),"-",""),"00000000000000"),8) -> 078706751 | O53: 78706751001430 | P53: TRANSPEN CARGAS E ENCOMENDAS LTDA | Q53: TRANSPEN CARGAS | R53: LOG - PONTA GROSSA PR
... A136: 3 | B136: PLATAFORMA | C136: FA | D136: FA25 | E136: FA25 | F136: 1.6 | G136: 7.6 | H136: 1.8 | I136: 1.8 | J136: 2100 | K136: ="A:"&TEXT(F136,"0,00")&" x C:"&TEXT(G136,"0,00")&" x L:"&TEXT(H136,"0,00")&"-"&TEXT(I136,"0,00")&" x P:"&TEXT(J136,"0.00")&"kg" -> A:1,60 x C:7,60 x L:1,80-1,80 x P:2.100kg | N136: ="0"&LEFT(TEXT(SUBSTITUTE(SUBSTITUTE(SUBSTITUTE(O136,".",""),"/",""),"-",""),"00000000000000"),8) -> 010680844 | O136: 10680844000184 | P136: ROTA 151 TRANSPORTE E LOCACAO EIRELI | Q136: ROTA 151 TRANSP | R136: LOG - PONTA GROSSA PR
N137: ="0"&LEFT(TEXT(SUBSTITUTE(SUBSTITUTE(SUBSTITUTE(O137,".",""),"/",""),"-",""),"00000000000000"),8) -> 010741822 | O137: 10741822000187 | P137: MEGA GUINDASTES LTDA | Q137: MEGA GUIND TRANSP | R137: LOG - PONTA GROSSA PR
N138: ="0"&LEFT(TEXT(SUBSTITUTE(SUBSTITUTE(SUBSTITUTE(O138,".",""),"/",""),"-",""),"00000000000000"),8) -> 011780069 | O138: 11780069000100 | P138: PRESIDENTE RECAPAGENS LTDA | Q138: PRESIDENTE PNEUS | R138: LOG - PONTA GROSSA PR
N139: ="0"&LEFT(TEXT(SUBSTITUTE(SUBSTITUTE(SUBSTITUTE(O139,".",""),"/",""),"-",""),"00000000000000"),8) -> 016666005 | O139: 16666005000198 | P139: FABIO LOGISTICA E TRANSPORTES | Q139: FABIO TRANSPORTES | R139: LOG - PONTA GROSSA PR
N140: ="0"&LEFT(TEXT(SUBSTITUTE(SUBSTITUTE(SUBSTITUTE(O140,".",""),"/",""),"-",""),"00000000000000"),8) -> 018252586 | O140: 18252586000147 | P140: DERLI DONEDA TRANSPORTES E LOGISTICA | Q140: DERLI TRANSPORTES | R140: LOG - NAO-ME-TOQUE RS
N141: ="0"&LEFT(TEXT(SUBSTITUTE(SUBSTITUTE(SUBSTITUTE(O141,".",""),"/",""),"-",""),"00000000000000"),8) -> 021272666 | O141: 21272666000179 | P141: R L S MELLO TRANSPORTES | Q141: MELLO TRANSPORTES | R141: LOG - CASTRO PR
N142: ="0"&LEFT(TEXT(SUBSTITUTE(SUBSTITUTE(SUBSTITUTE(O142,".",""),"/",""),"-",""),"00000000000000"),8) -> 035912495 | O142: 35912495000452 | P142: RODONAVES TRANSPORTES MULTIMODAL LTDA | Q142: RODONAVES TRANSP | R142: LOG - SAO JOSE DOS PINHAIS PR
N143: ="0"&LEFT(TEXT(SUBSTITUTE(SUBSTITUTE(SUBSTITUTE(O143,".",""),"/",""),"-",""),"00000000000000"),8) -> 037439159 | O143: 37439159000117 | P143: RUHANN COLLECT SALUM | Q143: R2 AUTO SCRR TRANSP | R143: LOG - CASTRO PR
N144: ="0"&LEFT(TEXT(SUBSTITUTE(SUBSTITUTE(SUBSTITUTE(O144,".",""),"/",""),"-",""),"00000000000000"),8) -> 038126289 | O144: 38126289000162 | P144: S C GARDINAL LTDA | Q144: S C GARDINAL - MT | R144: LOG - PONTA GROSSA PR
N145: ="0"&LEFT(TEXT(SUBSTITUTE(SUBSTITUTE(SUBSTITUTE(O145,".",""),"/",""),"-",""),"00000000000000"),8) -> 041544387 | O145: 41544387000124 | P145: MEZZOMO LUBRIFICANTES EIRELI | Q145: LUBRIQUEDAS | R145: LOG - QUEDAS DO IGUAÇU PR
N146: ="0"&LEFT(TEXT(SUBSTITUTE(SUBSTITUTE(SUBSTITUTE(O146,".",""),"/",""),"-",""),"00000000000000"),8) -> 043197553 | O146: 43197553000199 | P146: EDERSON FABRICIO NICKHORN EIRELI | Q146: EDERSO GABISA TRANSP | R146: LOG - SANTO ANTONIO RS
N147: ="0"&LEFT(TEXT(SUBSTITUTE(SUBSTITUTE(SUBSTITUTE(O147,".",""),"/",""),"-",""),"00000000000000"),8) -> 046570181 | O147: 46570181000192 | P147: TIAGO ANDREGHETTO | Q147: ANDREGHETTO TRANSP | R147: LOG - GUARAPUAVA PR
N148: ="0"&LEFT(TEXT(SUBSTITUTE(SUBSTITUTE(SUBSTITUTE(O148,".",""),"/",""),"-",""),"00000000000000"),8) -> 048269792 | O148: 48269792000120 | P148: L. H. ROSSATO TRANSPORTES LTDA | Q148: LH ROSSATO TRANSPORT | R148: LOG - BANDEIRANTES PR
... N171: ="0"&LEFT(TEXT(SUBSTITUTE(SUBSTITUTE(SUBSTITUTE(O171,".",""),"/",""),"-",""),"00000000000000"),8) -> 058643549 | O171: 58643549000184 | P171: ROBSON DA SILVA | Q171: ROBSON TRANSPORTES | R171: LOG - PONTA GROSSA PR
N172: ="0"&LEFT(TEXT(SUBSTITUTE(SUBSTITUTE(SUBSTITUTE(O172,".",""),"/",""),"-",""),"00000000000000"),8) -> 058219628 | O172: 58.219.628/0001-62 | P172: RODNEY GUIMARAES DE GEUS | Q172: KOMBEX TRANSP | R172: LOG - CARAMBEI PR
N173: ="0"&LEFT(TEXT(SUBSTITUTE(SUBSTITUTE(SUBSTITUTE(O173,".",""),"/",""),"-",""),"00000000000000"),8) -> 044914992 | O173: 44914992002424 | P173: RODONAVES TRANSP. E ENCOMENTDAS LTDA | Q173: RODONAVES TRANSP | R173: LOG - BLUMENAU SC
N174: ="0"&LEFT(TEXT(SUBSTITUTE(SUBSTITUTE(SUBSTITUTE(O174,".",""),"/",""),"-",""),"00000000000000"),8) -> 044914992 | O174: 44914992003315 | P174: RODONAVES TRANSPORTES E ENCOMENDAS LTDA | Q174: RODONAVES TRANSP | R174: LOG - CONTAGEM MG
N175: ="0"&LEFT(TEXT(SUBSTITUTE(SUBSTITUTE(SUBSTITUTE(O175,".",""),"/",""),"-",""),"00000000000000"),8) -> 044914992 | O175: 44914992003820 | P175: RODONAVES TRANSPORTES E ENCOMENDAS LTDA | Q175: RODONAVES TRANSP | R175: LOG - SAO JOSE DOS PINHAIS PR
N176: ="0"&LEFT(TEXT(SUBSTITUTE(SUBSTITUTE(SUBSTITUTE(O176,".",""),"/",""),"-",""),"00000000000000"),8) -> 044914992 | O176: 44914992001886 | P176: RODONAVES-TRANSPORTES E ENCOMENDAS LTDA | Q176: RODONAVES TRANSP | R176: LOG - APARECIDA DE GOIANIA GO
N177: ="0"&LEFT(TEXT(SUBSTITUTE(SUBSTITUTE(SUBSTITUTE(O177,".",""),"/",""),"-",""),"00000000000000"),8) -> 044914992 | O177: 44914992003668 | P177: RODONAVES TRANSPORTES E ENCOMENDAS LTDA | Q177: RODONAVES TRANSP | R177: LOG - ITAJAI SC
N178: ="0"&LEFT(TEXT(SUBSTITUTE(SUBSTITUTE(SUBSTITUTE(O178,".",""),"/",""),"-",""),"00000000000000"),8) -> 044914992 | O178: 44914992001703 | P178: RODONAVES-TRANSPORTES E ENCOM. LTDA | Q178: RODONAVES TRANSP | R178: LOG - LONDRINA PR
N179: ="0"&LEFT(TEXT(SUBSTITUTE(SUBSTITUTE(SUBSTITUTE(O179,".",""),"/",""),"-",""),"00000000000000"),8) -> 044914992 | O179: 44914992002181 | P179: RODONAVES TRANSPORTES ENCOMENDAS | Q179: RODONAVES TRANSP | R179: LOG - PARANAIBA MS
N180: ="0"&LEFT(TEXT(SUBSTITUTE(SUBSTITUTE(SUBSTITUTE(O180,".",""),"/",""),"-",""),"00000000000000"),8) -> 044914992 | O180: 44914992002777 | P180: RODONAVES-TRANSPORTES E ENCOM. LTDA | Q180: RODONAVES TRANSP | R180: LOG - PORTO ALEGRE RS
N181: ="0"&LEFT(TEXT(SUBSTITUTE(SUBSTITUTE(SUBSTITUTE(O181,".",""),"/",""),"-",""),"00000000000000"),8) -> 044914992 | O181: 44914992000138 | P181: RODONAVES TRANSPORTES E ENC. LTDA | Q181: RODONAVES TRANSP | R181: LOG - RIBEIRAO PRETO SP
N182: ="0"&LEFT(TEXT(SUBSTITUTE(SUBSTITUTE(SUBSTITUTE(O182,".",""),"/",""),"-",""),"00000000000000"),8) -> 044914992 | O182: 44914992001371 | P182: RODONAVES - TRANSPORTES E ENCOM. LTDA | Q182: RODONAVES TRANSP | R182: LOG - SAO PAULO SP
N183: ="0"&LEFT(TEXT(SUBSTITUTE(SUBSTITUTE(SUBSTITUTE(O183,".",""),"/",""),"-",""),"00000000000000"),8) -> 044914992 | O183: 44914992001290 | P183: RODONAVES TRANSPORTE E ENCOMENDAS LTDA | Q183: RODONAVES TRANSP | R183: LOG - UBERABA MG
N184: ="0"&LEFT(TEXT(SUBSTITUTE(SUBSTITUTE(SUBSTITUTE(O184,".",""),"/",""),"-",""),"00000000000000"),8) -> 028176140 | O184: 28176140000134 | P184: FLORIANO SILVEIRA ME | Q184: FLORIANO TRANSPORTES | R184: LOG - HORIZONTINA RS
... N197: ="0"&LEFT(TEXT(SUBSTITUTE(SUBSTITUTE(SUBSTITUTE(O197,".",""),"/",""),"-",""),"00000000000000"),8) -> 048501079 | O197: 48501079000160 | P197: ALEXANDRE EING | Q197: ALEXANDRE MUC TRANSP | R197: LOG - PRUDENTOPOLIS PR
N198: ="0"&LEFT(TEXT(SUBSTITUTE(SUBSTITUTE(SUBSTITUTE(O198,".",""),"/",""),"-",""),"00000000000000"),8) -> 021915466 | O198: 21.915.466/0001-97 | P198: SILMARA DA SILVA FERNANDES DE ALMEIDA | Q198: SIL VIAGENS | R198: LOG - JAGUARIAIVA PR
N199: ="0"&LEFT(TEXT(SUBSTITUTE(SUBSTITUTE(SUBSTITUTE(O199,".",""),"/",""),"-",""),"00000000000000"),8) -> 040895870 | O199: 40895870000190 | P199: WESLEY DOUGLAS DA SILVA OLIVEIRA | Q199: WESLEY D. COURIER | R199: LOG - GUARAPUAVA PR
N200: ="0"&LEFT(TEXT(SUBSTITUTE(SUBSTITUTE(SUBSTITUTE(O200,".",""),"/",""),"-",""),"00000000000000"),8) -> 000809068 | O200: 809068000116 | P200: MULLER ROCHA TRANSPORTES TERRESTRES LTDA | Q200: CEZINHA TRANSPORTES | R200: LOG - TURVO PR
N201: ="0"&LEFT(TEXT(SUBSTITUTE(SUBSTITUTE(SUBSTITUTE(O201,".",""),"/",""),"-",""),"00000000000000"),8) -> 078206513 | O201: 78206513000140 | P201: DETRAN PR DEPARTO DE TRANSITO DO PARANA | Q201: DETRAN PR | R201: LOG - CURITIBA PR
N202: ="0"&LEFT(TEXT(SUBSTITUTE(SUBSTITUTE(SUBSTITUTE(O202,".",""),"/",""),"-",""),"00000000000000"),8) -> 0
